Workbook

Sheet Respostas
A1: Desafio 2 — Propensão à conversão: respostas
A2: Abordagem descritiva (o case aceita): a propensão de cada contador é a taxa histórica de conversão de quem tem o mesmo perfil — média das taxas das categorias dele nos 5 drivers do top 5. Sem modelo e sem pesos; a lista completa está na aba Base (coluna AA).
A4: 1. Lógica — quais variáveis e por quê
A5: • Testadas 9 características. Entram as 5 que mais separam quem converte de quem não converte (amplitude = maior taxa − menor taxa, categorias com 30+ contadores). Região, segmento, site e LinkedIn quase não separam.
A6: • Fora: score_potencial_latente (regra do case) e status_omie (não tem sinal e diverge dos contratos).
A7: Endereçáveis (303) na faixa Alta de propensão | B7: =COUNTIFS(Base!$AB$2:$AB$601,"Alta",Base!$S$2:$S$601,1) -> 14
A8: • O topo da propensão já foi quase todo convertido: entre os 303 endereçáveis, poucos estão na faixa Alta.
A10: 2. Como avaliar se está funcionando — em duas etapas
A11: Etapa 1 (base): conversão por faixa — Alta · Média · Baixa (meta: Alta > Média > Baixa) | B11: =Como_Avaliar!C5 -> 91% · 29% · 3%
A12: Etapa 1 (base): % dos convertidos captados pelo top 30% (meta: acima de 30%) | B12: =Como_Avaliar!C6 -> 0.69166667
A13: Etapa 1 (base): win rate real — faixa Alta × demais (meta: Alta acima) | B13: =Como_Avaliar!C7 -> 60% × 65%
A14: Etapa 1 (base): ciclo médio do Ganho — faixa Alta × demais (meta: Alta ≤ demais) | B14: =Como_Avaliar!C10 -> 36 × 48 dias
A15: • Etapa 2 (piloto de 90 dias com grupo de controle): win rate, nMRR por EC e ciclo do grupo piloto melhores que os do controle. Se superar, a priorização vira processo; senão, o perfil é revisto.
A17: 3. Top 5 características (amplitude da taxa de conversão)
A18: ="1. "&INDEX(Drivers!$H$6:$H$14,MATCH(1,Drivers!$J$6:$J$14,0))&" — "&FIXED(INDEX(Drivers!$I$6:$I$14,MATCH(1,Drivers!$J$6:$J$14,0)),0)&" p.p.: Médio e Grande convertem 94–100%; Autônomo 7%" -> 1. Porte — 93 p.p.: Médio e Grande convertem 94–100%; Autônomo 7%
A19: ="2. "&INDEX(Drivers!$H$6:$H$14,MATCH(2,Drivers!$J$6:$J$14,0))&" — "&FIXED(INDEX(Drivers!$I$6:$I$14,MATCH(2,Drivers!$J$6:$J$14,0)),0)&" p.p.: de ~9% (1 a 2 funcionários) a ~97% (16+)" -> 2. Nº de funcionários — 89 p.p.: de ~9% (1 a 2 funcionários) a ~97% (16+)
A20: ="3. "&INDEX(Drivers!$H$6:$H$14,MATCH(3,Drivers!$J$6:$J$14,0))&" — "&FIXED(INDEX(Drivers!$I$6:$I$14,MATCH(3,Drivers!$J$6:$J$14,0)),0)&" p.p.: de ~10% (< 20 clientes) a ~98% (150+); é também o Fit do 1c e do Desafio 3" -> 3. Nº de clientes da carteira — 88 p.p.: de ~10% (< 20 clientes) a ~98% (150+); é também o Fit do 1c e do Desafio 3
A21: ="4. "&INDEX(Drivers!$H$6:$H$14,MATCH(4,Drivers!$J$6:$J$14,0))&" — "&FIXED(INDEX(Drivers!$I$6:$I$14,MATCH(4,Drivers!$J$6:$J$14,0)),0)&" p.p.: ERP de mercado converte muito mais que planilha, nenhum ou ContaAzul" -> 4. ERP atual — 59 p.p.: ERP de mercado converte muito mais que planilha, nenhum ou ContaAzul
A22: ="5. "&INDEX(Drivers!$H$6:$H$14,MATCH(5,Drivers!$J$6:$J$14,0))&" — "&FIXED(INDEX(Drivers!$I$6:$I$14,MATCH(5,Drivers!$J$6:$J$14,0)),0)&" p.p.: 16+ anos convertem mais que o dobro dos com < 8 anos" -> 5. Anos de mercado — 34 p.p.: 16+ anos convertem mais que o dobro dos com < 8 anos
A23: • Porte, funcionários e carteira medem o mesmo conceito (tamanho). Com o ERP, descrevem o perfil do topo (ICP: 50+ clientes, 6+ funcionários e ERP de mercado).
A25: 4. Extra — impacto em nMRR ao priorizar quem tem maior propensão
A26: Uplift no nMRR do canal — cenário base | B26: =Impacto_nMRR!C23 -> 0.25355191
A27: Faixa (conservador a otimista) | B27: =FIXED(Impacto_nMRR!B23*100,0)&"% a "&FIXED(Impacto_nMRR!D23*100,0)&"%" -> 10% a 46%
A28: nMRR incremental/mês nas franquias abaixo da meta (escala oficial, cenário base) | B28: =Impacto_nMRR!C24 -> 31440.437
A29: • Premissas: 50% da capacidade dos ECs vai para o top 30% do score; 40% do lift do topo vira Ganho real (fator de realização, hipótese); ticket = mrr_inicial médio; desconto de churn de 20,5%.
A30: • Teste de estresse: com fator de realização 0, o uplift é 0. O número só se confirma com o piloto.
A32: 5. Previsibilidade de receita: o que o pipeline atual deve gerar no próximo trimestre
A33: Método 1: pipeline aberto ponderado pela chance de fechar de cada estágio (Ganhos) | B33: =Previsao_Receita!D18 -> 6.8686177
A34: Método 2: run-rate histórico do CRM (Ganhos por trimestre) | B34: =Previsao_Receita!B29 -> 8.1111111
A35: nMRR esperado do pipeline no trimestre (R$, escala do CRM) | B35: =Previsao_Receita!B22 -> 5597.2365
A36: Ganhos do CRM ÷ nMRR oficial do canal | B36: =Previsao_Receita!B47 -> 0.0092744271
A37: • Os dois métodos convergem: o pipeline do CRM é previsível. Mas ele explica uma fração mínima do nMRR oficial: sem fonte única de nMRR, não dá para prever a receita oficial do canal.

Sheet Drivers
A1: Drivers de conversão — taxa de conversão por característica (600 contadores)
A2: Amplitude = maior taxa − menor taxa entre as categorias com 30+ contadores. Quanto maior, mais a característica separa quem converte de quem não converte.
A3: Taxa média geral | B3: =AVERAGE(Base!$M$2:$M$601) -> 0.4
A4: Variável | B4: Categoria | C4: Contadores | D4: Convertidos | E4: Taxa | F4: Lift vs média | H4: Ranking das variáveis
A5: Nº de clientes da carteira | B5: 1. < 20 | C5: =COUNTIF(Base!$O$2:$O$601,B5) -> 194 | D5: =COUNTIFS(Base!$O$2:$O$601,B5,Base!$M$2:$M$601,1) -> 20 | E5: =IF(C5>0,D5/C5,0) -> 0.10309278 | F5: =E5/$B$3 -> 0.25773196 | H5: Variável | I5: Amplitude (p.p.) | J5: Ranking
A6: Nº de clientes da carteira | B6: 2. 20 a 49 | C6: =COUNTIF(Base!$O$2:$O$601,B6) -> 170 | D6: =COUNTIFS(Base!$O$2:$O$601,B6,Base!$M$2:$M$601,1) -> 43 | E6: =IF(C6>0,D6/C6,0) -> 0.25294118 | F6: =E6/$B$3 -> 0.63235294 | H6: Nº de clientes da carteira | I6: =(_xlfn.MAXIFS(E5:E8,C5:C8,">=30")-_xlfn.MINIFS(E5:E8,C5:C8,">=30"))*100 -> 87.628866 | J6: =RANK(I6,$I$6:$I$14) -> 3
A7: Nº de clientes da carteira | B7: 3. 50 a 149 | C7: =COUNTIF(Base!$O$2:$O$601,B7) -> 139 | D7: =COUNTIFS(Base!$O$2:$O$601,B7,Base!$M$2:$M$601,1) -> 82 | E7: =IF(C7>0,D7/C7,0) -> 0.58992806 | F7: =E7/$B$3 -> 1.4748201 | H7: Nº de funcionários | I7: =(_xlfn.MAXIFS(E10:E13,C10:C13,">=30")-_xlfn.MINIFS(E10:E13,C10:C13,">=30"))*100 -> 88.593482 | J7: =RANK(I7,$I$6:$I$14) -> 2
A8: Nº de clientes da carteira | B8: 4. 150+ | C8: =COUNTIF(Base!$O$2:$O$601,B8) -> 97 | D8: =COUNTIFS(Base!$O$2:$O$601,B8,Base!$M$2:$M$601,1) -> 95 | E8: =IF(C8>0,D8/C8,0) -> 0.97938144 | F8: =E8/$B$3 -> 2.4484536 | H8: Porte | I8: =(_xlfn.MAXIFS(E15:E18,C15:C18,">=30")-_xlfn.MINIFS(E15:E18,C15:C18,">=30"))*100 -> 93.172691 | J8: =RANK(I8,$I$6:$I$14) -> 1
H9: ERP atual | I9: =(_xlfn.MAXIFS(E20:E27,C20:C27,">=30")-_xlfn.MINIFS(E20:E27,C20:C27,">=30"))*100 -> 58.695652 | J9: =RANK(I9,$I$6:$I$14) -> 4
A10: Nº de funcionários | B10: 1. 1 a 2 | C10: =COUNTIF(Base!$P$2:$P$601,B10) -> 265 | D10: =COUNTIFS(Base!$P$2:$P$601,B10,Base!$M$2:$M$601,1) -> 23 | E10: =IF(C10>0,D10/C10,0) -> 0.086792453 | F10: =E10/$B$3 -> 0.21698113 | H10: Anos de mercado | I10: =(_xlfn.MAXIFS(E29:E31,C29:C31,">=30")-_xlfn.MINIFS(E29:E31,C29:C31,">=30"))*100 -> 34.332146 | J10: =RANK(I10,$I$6:$I$14) -> 5
A11: Nº de funcionários | B11: 2. 3 a 5 | C11: =COUNTIF(Base!$P$2:$P$601,B11) -> 84 | D11: =COUNTIFS(Base!$P$2:$P$601,B11,Base!$M$2:$M$601,1) -> 32 | E11: =IF(C11>0,D11/C11,0) -> 0.38095238 | F11: =E11/$B$3 -> 0.95238095 | H11: Região | I11: =(_xlfn.MAXIFS(E34:E38,C34:C38,">=30")-_xlfn.MINIFS(E34:E38,C34:C38,">=30"))*100 -> 22.83365 | J11: =RANK(I11,$I$6:$I$14) -> 6
A12: Nº de funcionários | B12: 3. 6 a 15 | C12: =COUNTIF(Base!$P$2:$P$601,B12) -> 141 | D12: =COUNTIFS(Base!$P$2:$P$601,B12,Base!$M$2:$M$601,1) -> 78 | E12: =IF(C12>0,D12/C12,0) -> 0.55319149 | F12: =E12/$B$3 -> 1.3829787 | H12: Segmento | I12: =(_xlfn.MAXIFS(E40:E46,C40:C46,">=30")-_xlfn.MINIFS(E40:E46,C40:C46,">=30"))*100 -> 19.230167 | J12: =RANK(I12,$I$6:$I$14) -> 7
A13: Nº de funcionários | B13: 4. 16+ | C13: =COUNTIF(Base!$P$2:$P$601,B13) -> 110 | D13: =COUNTIFS(Base!$P$2:$P$601,B13,Base!$M$2:$M$601,1) -> 107 | E13: =IF(C13>0,D13/C13,0) -> 0.97272727 | F13: =E13/$B$3 -> 2.4318182 | H13: Tem site | I13: =(_xlfn.MAXIFS(E48:E49,C48:C49,">=30")-_xlfn.MINIFS(E48:E49,C48:C49,">=30"))*100 -> 11.25871 | J13: =RANK(I13,$I$6:$I$14) -> 8
H14: LinkedIn | I14: =(_xlfn.MAXIFS(E51:E52,C51:C52,">=30")-_xlfn.MINIFS(E51:E52,C51:C52,">=30"))*100 -> 0.56690012 | J14: =RANK(I14,$I$6:$I$14) -> 9
A15: Porte | B15: Autônomo | C15: =COUNTIF(Base!$D$2:$D$601,B15) -> 249 | D15: =COUNTIFS(Base!$D$2:$D$601,B15,Base!$M$2:$M$601,1) -> 17 | E15: =IF(C15>0,D15/C15,0) -> 0.068273092 | F15: =E15/$B$3 -> 0.17068273
A16: Porte | B16: Grande Escritório | C16: =COUNTIF(Base!$D$2:$D$601,B16) -> 49 | D16: =COUNTIFS(Base!$D$2:$D$601,B16,Base!$M$2:$M$601,1) -> 49 | E16: =IF(C16>0,D16/C16,0) -> 1 | F16: =E16/$B$3 -> 2.5
A17: Porte | B17: Médio Escritório | C17: =COUNTIF(Base!$D$2:$D$601,B17) -> 83 | D17: =COUNTIFS(Base!$D$2:$D$601,B17,Base!$M$2:$M$601,1) -> 78 | E17: =IF(C17>0,D17/C17,0) -> 0.93975904 | F17: =E17/$B$3 -> 2.3493976
A18: Porte | B18: Pequeno Escritório | C18: =COUNTIF(Base!$D$2:$D$601,B18) -> 219 | D18: =COUNTIFS(Base!$D$2:$D$601,B18,Base!$M$2:$M$601,1) -> 96 | E18: =IF(C18>0,D18/C18,0) -> 0.43835616 | F18: =E18/$B$3 -> 1.0958904
A20: ERP atual | B20: Alterdata | C20: =COUNTIF(Base!$I$2:$I$601,B20) -> 46 | D20: =COUNTIFS(Base!$I$2:$I$601,B20,Base!$M$2:$M$601,1) -> 30 | E20: =IF(C20>0,D20/C20,0) -> 0.65217391 | F20: =E20/$B$3 -> 1.6304348
A21: ERP atual | B21: ContaAzul | C21: =COUNTIF(Base!$I$2:$I$601,B21) -> 19 | D21: =COUNTIFS(Base!$I$2:$I$601,B21,Base!$M$2:$M$601,1) -> 0 | E21: =IF(C21>0,D21/C21,0) -> 0 | F21: =E21/$B$3 -> 0
A22: ERP atual | B22: Domínio | C22: =COUNTIF(Base!$I$2:$I$601,B22) -> 154 | D22: =COUNTIFS(Base!$I$2:$I$601,B22,Base!$M$2:$M$601,1) -> 58 | E22: =IF(C22>0,D22/C22,0) -> 0.37662338 | F22: =E22/$B$3 -> 0.94155844
A23: ERP atual | B23: Nenhum | C23: =COUNTIF(Base!$I$2:$I$601,B23) -> 46 | D23: =COUNTIFS(Base!$I$2:$I$601,B23,Base!$M$2:$M$601,1) -> 3 | E23: =IF(C23>0,D23/C23,0) -> 0.065217391 | F23: =E23/$B$3 -> 0.16304348
A24: ERP atual | B24: Planilha | C24: =COUNTIF(Base!$I$2:$I$601,B24) -> 64 | D24: =COUNTIFS(Base!$I$2:$I$601,B24,Base!$M$2:$M$601,1) -> 10 | E24: =IF(C24>0,D24/C24,0) -> 0.15625 | F24: =E24/$B$3 -> 0.390625
A25: ERP atual | B25: Questor | C25: =COUNTIF(Base!$I$2:$I$601,B25) -> 161 | D25: =COUNTIFS(Base!$I$2:$I$601,B25,Base!$M$2:$M$601,1) -> 64 | E25: =IF(C25>0,D25/C25,0) -> 0.39751553 | F25: =E25/$B$3 -> 0.99378882
A26: ERP atual | B26: SAP | C26: =COUNTIF(Base!$I$2:$I$601,B26) -> 26 | D26: =COUNTIFS(Base!$I$2:$I$601,B26,Base!$M$2:$M$601,1) -> 26 | E26: =IF(C26>0,D26/C26,0) -> 1 | F26: =E26/$B$3 -> 2.5 | H26: ICP do canal — perfil ideal de contador (drivers → regra de ação)
A27: ERP atual | B27: Totvs | C27: =COUNTIF(Base!$I$2:$I$601,B27) -> 84 | D27: =COUNTIFS(Base!$I$2:$I$601,B27,Base!$M$2:$M$601,1) -> 49 | E27: =IF(C27>0,D27/C27,0) -> 0.58333333 | F27: =E27/$B$3 -> 1.4583333 | H27: Regra: carteira com 50+ clientes E 6+ funcionários E ERP de mercado (não Nenhum/Planilha/ContaAzul).
H28: Grupo | I28: Contadores | J28: % converteu_omie | K28: Cliente Ativo (status_omie) | L28: Endereçáveis (regra 1a) | M28: Carteira endereçável
A29: Anos de mercado | B29: 1. < 8 anos | C29: =COUNTIF(Base!$N$2:$N$601,B29) -> 152 | D29: =COUNTIFS(Base!$N$2:$N$601,B29,Base!$M$2:$M$601,1) -> 34 | E29: =IF(C29>0,D29/C29,0) -> 0.22368421 | F29: =E29/$B$3 -> 0.55921053 | H29: ICP | I29: =COUNTIF(Base!$R$2:$R$601,1) -> 185 | J29: =AVERAGEIF(Base!$R$2:$R$601,1,Base!$M$2:$M$601) -> 0.83783784 | K29: =COUNTIFS(Base!$R$2:$R$601,1,Base!$L$2:$L$601,"Cliente Ativo") -> 26 | L29: =COUNTIFS(Base!$R$2:$R$601,1,Base!$S$2:$S$601,1) -> 24 | M29: =SUMIFS(Base!$G$2:$G$601,Base!$R$2:$R$601,1,Base!$S$2:$S$601,1) -> 1805
A30: Anos de mercado | B30: 2. 8 a 15 anos | C30: =COUNTIF(Base!$N$2:$N$601,B30) -> 139 | D30: =COUNTIFS(Base!$N$2:$N$601,B30,Base!$M$2:$M$601,1) -> 31 | E30: =IF(C30>0,D30/C30,0) -> 0.22302158 | F30: =E30/$B$3 -> 0.55755396 | H30: Fora do ICP | I30: =COUNTIF(Base!$R$2:$R$601,0) -> 415 | J30: =AVERAGEIF(Base!$R$2:$R$601,0,Base!$M$2:$M$601) -> 0.20481928 | K30: =COUNTIFS(Base!$R$2:$R$601,0,Base!$L$2:$L$601,"Cliente Ativo") -> 69 | L30: =COUNTIFS(Base!$R$2:$R$601,0,Base!$S$2:$S$601,1) -> 279 | M30: =SUMIFS(Base!$G$2:$G$601,Base!$R$2:$R$601,0,Base!$S$2:$S$601,1) -> 6396
A31: Anos de mercado | B31: 3. 16+ anos | C31: =COUNTIF(Base!$N$2:$N$601,B31) -> 309 | D31: =COUNTIFS(Base!$N$2:$N$601,B31,Base!$M$2:$M$601,1) -> 175 | E31: =IF(C31>0,D31/C31,0) -> 0.56634304 | F31: =E31/$B$3 -> 1.4158576 | H31: Lift do ICP vs média (taxa do ICP ÷ média) | J31: =J29/$B$3 -> 2.0945946
H32: Lift do ICP vs fora do ICP | J32: =J29/J30 -> 4.09062
A33: Fora do top 5 (efeito pequeno) | H33: % da carteira endereçável no ICP | J33: =M29/(M29+M30) -> 0.22009511
A34: Região | B34: Centro-Oeste | C34: =COUNTIF(Base!$C$2:$C$601,B34) -> 87 | D34: =COUNTIFS(Base!$C$2:$C$601,B34,Base!$M$2:$M$601,1) -> 38 | E34: =IF(C34>0,D34/C34,0) -> 0.43678161 | F34: =E34/$B$3 -> 1.091954 | H34: Atenção: no pipeline real o win rate do ICP NÃO é maior (aba Como_Avaliar). O ICP é uma hipótese a validar com piloto + grupo de controle.
A35: Região | B35: Nordeste | C35: =COUNTIF(Base!$C$2:$C$601,B35) -> 93 | D35: =COUNTIFS(Base!$C$2:$C$601,B35,Base!$M$2:$M$601,1) -> 28 | E35: =IF(C35>0,D35/C35,0) -> 0.30107527 | F35: =E35/$B$3 -> 0.75268817
A36: Região | B36: Norte | C36: =COUNTIF(Base!$C$2:$C$601,B36) -> 27 | D36: =COUNTIFS(Base!$C$2:$C$601,B36,Base!$M$2:$M$601,1) -> 9 | E36: =IF(C36>0,D36/C36,0) -> 0.33333333 | F36: =E36/$B$3 -> 0.83333333
A37: Região | B37: Sudeste | C37: =COUNTIF(Base!$C$2:$C$601,B37) -> 291 | D37: =COUNTIFS(Base!$C$2:$C$601,B37,Base!$M$2:$M$601,1) -> 111 | E37: =IF(C37>0,D37/C37,0) -> 0.3814433 | F37: =E37/$B$3 -> 0.95360825
A38: Região | B38: Sul | C38: =COUNTIF(Base!$C$2:$C$601,B38) -> 102 | D38: =COUNTIFS(Base!$C$2:$C$601,B38,Base!$M$2:$M$601,1) -> 54 | E38: =IF(C38>0,D38/C38,0) -> 0.52941176 | F38: =E38/$B$3 -> 1.3235294
A40: Segmento | B40: Agronegócio | C40: =COUNTIF(Base!$E$2:$E$601,B40) -> 93 | D40: =COUNTIFS(Base!$E$2:$E$601,B40,Base!$M$2:$M$601,1) -> 38 | E40: =IF(C40>0,D40/C40,0) -> 0.40860215 | F40: =E40/$B$3 -> 1.0215054
A41: Segmento | B41: Construção Civil | C41: =COUNTIF(Base!$E$2:$E$601,B41) -> 86 | D41: =COUNTIFS(Base!$E$2:$E$601,B41,Base!$M$2:$M$601,1) -> 34 | E41: =IF(C41>0,D41/C41,0) -> 0.39534884 | F41: =E41/$B$3 -> 0.98837209
A42: Segmento | B42: Indústria | C42: =COUNTIF(Base!$E$2:$E$601,B42) -> 85 | D42: =COUNTIFS(Base!$E$2:$E$601,B42,Base!$M$2:$M$601,1) -> 35 | E42: =IF(C42>0,D42/C42,0) -> 0.41176471 | F42: =E42/$B$3 -> 1.0294118
A43: Segmento | B43: Saúde | C43: =COUNTIF(Base!$E$2:$E$601,B43) -> 83 | D43: =COUNTIFS(Base!$E$2:$E$601,B43,Base!$M$2:$M$601,1) -> 25 | E43: =IF(C43>0,D43/C43,0) -> 0.30120482 | F43: =E43/$B$3 -> 0.75301205
A44: Segmento | B44: Serviços | C44: =COUNTIF(Base!$E$2:$E$601,B44) -> 93 | D44: =COUNTIFS(Base!$E$2:$E$601,B44,Base!$M$2:$M$601,1) -> 35 | E44: =IF(C44>0,D44/C44,0) -> 0.37634409 | F44: =E44/$B$3 -> 0.94086022
A45: Segmento | B45: Tecnologia | C45: =COUNTIF(Base!$E$2:$E$601,B45) -> 83 | D45: =COUNTIFS(Base!$E$2:$E$601,B45,Base!$M$2:$M$601,1) -> 35 | E45: =IF(C45>0,D45/C45,0) -> 0.42168675 | F45: =E45/$B$3 -> 1.0542169
A46: Segmento | B46: Varejo/Comércio | C46: =COUNTIF(Base!$E$2:$E$601,B46) -> 77 | D46: =COUNTIFS(Base!$E$2:$E$601,B46,Base!$M$2:$M$601,1) -> 38 | E46: =IF(C46>0,D46/C46,0) -> 0.49350649 | F46: =E46/$B$3 -> 1.2337662
A48: Tem site | B48: Não | C48: =COUNTIF(Base!$J$2:$J$601,B48) -> 351 | D48: =COUNTIFS(Base!$J$2:$J$601,B48,Base!$M$2:$M$601,1) -> 124 | E48: =IF(C48>0,D48/C48,0) -> 0.35327635 | F48: =E48/$B$3 -> 0.88319088
A49: Tem site | B49: Sim | C49: =COUNTIF(Base!$J$2:$J$601,B49) -> 249 | D49: =COUNTIFS(Base!$J$2:$J$601,B49,Base!$M$2:$M$601,1) -> 116 | E49: =IF(C49>0,D49/C49,0) -> 0.46586345 | F49: =E49/$B$3 -> 1.1646586
A51: LinkedIn | B51: Não | C51: =COUNTIF(Base!$K$2:$K$601,B51) -> 373 | D51: =COUNTIFS(Base!$K$2:$K$601,B51,Base!$M$2:$M$601,1) -> 150 | E51: =IF(C51>0,D51/C51,0) -> 0.40214477 | F51: =E51/$B$3 -> 1.0053619
A52: LinkedIn | B52: Sim | C52: =COUNTIF(Base!$K$2:$K$601,B52) -> 227 | D52: =COUNTIFS(Base!$K$2:$K$601,B52,Base!$M$2:$M$601,1) -> 90 | E52: =IF(C52>0,D52/C52,0) -> 0.39647577 | F52: =E52/$B$3 -> 0.99118943

Sheet Como_Avaliar
A1: Como avaliar se a abordagem está funcionando
A2: Em duas etapas: (1) validação na base — o score ordena quem converte e o topo fecha mais no pipeline real?; (2) piloto de 90 dias com grupo de controle — priorizar o topo gera mais Ganhos e mais nMRR por EC?
A4: Métrica | B4: O que mede | C4: Hoje | D4: Meta | E4: Etapa
A5: Conversão por faixa de propensão (Alta · Média · Baixa) | B5: Se o score ordena quem converte (target) | C5: =FIXED(C19*100,0)&"% · "&FIXED(C20*100,0)&"% · "&FIXED(C21*100,0)&"%" -> 91% · 29% · 3% | D5: Alta > Média > Baixa | E5: 1. Base
A6: Captura: % dos convertidos no top 30% | B6: Quanto da conversão está no topo | C6: =SUMIF(Base!$AB$2:$AB$601,"Alta",Base!$M$2:$M$601)/SUM(Base!$M$2:$M$601) -> 0.69166667 | D6: Maior que os 30% da base que o topo representa | E6: 1. Base
A7: Win rate real: faixa Alta × demais | B7: Se o topo fecha mais de verdade (Ganho ÷ Ganho + Perdido) | C7: =FIXED(G19*100,0)&"% × "&FIXED(G22*100,0)&"%" -> 60% × 65% | D7: Alta acima das demais | E7: 1. Base e 2. Piloto
A8: Win rate: piloto × controle | B8: Se priorizar o topo gera mais Ganhos | C8: a medir no piloto | D8: Piloto acima do controle | E8: 2. Piloto
A9: nMRR por EC: piloto × controle | B9: Se o ganho de conversão vira receita | C9: a medir no piloto | D9: Piloto acima do controle | E9: 2. Piloto
A10: Ciclo médio do Ganho (dias): faixa Alta × demais | B10: Se priorizar não alonga a venda | C10: =FIXED(H19,0)&" × "&FIXED(H22,0)&" dias" -> 36 × 48 dias | D10: Alta ≤ demais | E10: 1. Base e 2. Piloto
A12: Regra de decisão: se o piloto superar o controle, a priorização pelo score vira processo; senão, o perfil é revisto.
A14: Cortes do score (faixas de propensão dos 600 contadores)
A15: Faixa Alta: score a partir do percentil 70 (top 30%) | B15: =_xlfn.PERCENTILE.INC(Base!$AA$2:$AA$601,0.7) -> 0.47883304
A16: Faixa Média: a partir do percentil 30 | B16: =_xlfn.PERCENTILE.INC(Base!$AA$2:$AA$601,0.3) -> 0.24022495
A18: Faixa de propensão | B18: Contadores | C18: % converteu_omie (target) | D18: Lift vs média | E18: Leads com desfecho (Ganho+Perdido) | F18: Leads Ganhos | G18: Win rate real | H18: Ciclo médio do Ganho (dias)
A19: Alta | B19: =COUNTIF(Base!$AB$2:$AB$601,A19) -> 183 | C19: =AVERAGEIF(Base!$AB$2:$AB$601,A19,Base!$M$2:$M$601) -> 0.90710383 | D19: =C19/Drivers!$B$3 -> 2.2677596 | E19: =COUNTIFS(Leads!$N$2:$N$351,A19,Leads!$J$2:$J$351,1) -> 30 | F19: =COUNTIFS(Leads!$N$2:$N$351,A19,Leads!$K$2:$K$351,1) -> 18 | G19: =IF(E19>0,F19/E19,0) -> 0.6 | H19: =AVERAGEIFS(Leads!$O$2:$O$351,Leads!$N$2:$N$351,A19,Leads!$K$2:$K$351,1) -> 35.666667
A20: Média | B20: =COUNTIF(Base!$AB$2:$AB$601,A20) -> 241 | C20: =AVERAGEIF(Base!$AB$2:$AB$601,A20,Base!$M$2:$M$601) -> 0.28630705 | D20: =C20/Drivers!$B$3 -> 0.71576763 | E20: =COUNTIFS(Leads!$N$2:$N$351,A20,Leads!$J$2:$J$351,1) -> 51 | F20: =COUNTIFS(Leads!$N$2:$N$351,A20,Leads!$K$2:$K$351,1) -> 34 | G20: =IF(E20>0,F20/E20,0) -> 0.66666667 | H20: =AVERAGEIFS(Leads!$O$2:$O$351,Leads!$N$2:$N$351,A20,Leads!$K$2:$K$351,1) -> 44.235294
A21: Baixa | B21: =COUNTIF(Base!$AB$2:$AB$601,A21) -> 176 | C21: =AVERAGEIF(Base!$AB$2:$AB$601,A21,Base!$M$2:$M$601) -> 0.028409091 | D21: =C21/Drivers!$B$3 -> 0.071022727 | E21: =COUNTIFS(Leads!$N$2:$N$351,A21,Leads!$J$2:$J$351,1) -> 33 | F21: =COUNTIFS(Leads!$N$2:$N$351,A21,Leads!$K$2:$K$351,1) -> 21 | G21: =IF(E21>0,F21/E21,0) -> 0.63636364 | H21: =AVERAGEIFS(Leads!$O$2:$O$351,Leads!$N$2:$N$351,A21,Leads!$K$2:$K$351,1) -> 53.095238
A22: Demais (Média + Baixa) | B22: =B20+B21 -> 417 | C22: =(C20*B20+C21*B21)/B22 -> 0.17745803 | D22: =C22/Drivers!$B$3 -> 0.44364508 | E22: =E20+E21 -> 84 | F22: =F20+F21 -> 55 | G22: =IF(E22>0,F22/E22,0) -> 0.6547619 | H22: =AVERAGEIFS(Leads!$O$2:$O$351,Leads!$N$2:$N$351,"<>Alta",Leads!$K$2:$K$351,1) -> 47.618182
A24: O target reflete o fechamento real? (por porte)
A25: Porte | B25: Contadores | C25: % converteu_omie (target) | D25: Leads com desfecho (Ganho+Perdido) | E25: Leads Ganhos | F25: Win rate real | G25: Contratos em clientes_ativos
A26: Autônomo | B26: =COUNTIF(Base!$D$2:$D$601,A26) -> 249 | C26: =AVERAGEIF(Base!$D$2:$D$601,A26,Base!$M$2:$M$601) -> 0.068273092 | D26: =COUNTIFS(Leads!$G$2:$G$351,A26,Leads!$J$2:$J$351,1) -> 52 | E26: =COUNTIFS(Leads!$G$2:$G$351,A26,Leads!$K$2:$K$351,1) -> 35 | F26: =IF(D26>0,E26/D26,0) -> 0.67307692 | G26: =COUNTIF(Clientes!$F$2:$F$74,A26) -> 35
A27: Pequeno Escritório | B27: =COUNTIF(Base!$D$2:$D$601,A27) -> 219 | C27: =AVERAGEIF(Base!$D$2:$D$601,A27,Base!$M$2:$M$601) -> 0.43835616 | D27: =COUNTIFS(Leads!$G$2:$G$351,A27,Leads!$J$2:$J$351,1) -> 42 | E27: =COUNTIFS(Leads!$G$2:$G$351,A27,Leads!$K$2:$K$351,1) -> 27 | F27: =IF(D27>0,E27/D27,0) -> 0.64285714 | G27: =COUNTIF(Clientes!$F$2:$F$74,A27) -> 27
A28: Médio Escritório | B28: =COUNTIF(Base!$D$2:$D$601,A28) -> 83 | C28: =AVERAGEIF(Base!$D$2:$D$601,A28,Base!$M$2:$M$601) -> 0.93975904 | D28: =COUNTIFS(Leads!$G$2:$G$351,A28,Leads!$J$2:$J$351,1) -> 13 | E28: =COUNTIFS(Leads!$G$2:$G$351,A28,Leads!$K$2:$K$351,1) -> 6 | F28: =IF(D28>0,E28/D28,0) -> 0.46153846 | G28: =COUNTIF(Clientes!$F$2:$F$74,A28) -> 6
A29: Grande Escritório | B29: =COUNTIF(Base!$D$2:$D$601,A29) -> 49 | C29: =AVERAGEIF(Base!$D$2:$D$601,A29,Base!$M$2:$M$601) -> 1 | D29: =COUNTIFS(Leads!$G$2:$G$351,A29,Leads!$J$2:$J$351,1) -> 7 | E29: =COUNTIFS(Leads!$G$2:$G$351,A29,Leads!$K$2:$K$351,1) -> 5 | F29: =IF(D29>0,E29/D29,0) -> 0.71428571 | G29: =COUNTIF(Clientes!$F$2:$F$74,A29) -> 5
A30: Total | B30: =SUM(B26:B29) -> 600 | C30: =AVERAGE(Base!$M$2:$M$601) -> 0.4 | D30: =SUM(D26:D29) -> 114 | E30: =SUM(E26:E29) -> 73 | F30: =IF(D30>0,E30/D30,0) -> 0.64035088 | G30: =SUM(G26:G29) -> 73
A32: Leitura
A33: • Etapa 1: pelo target o score ordena muito bem (a faixa Alta converte ~30x a Baixa), mas o target vaza do score_potencial_latente, dominado por tamanho e ERP: a separação é alta por construção.
A34: • No pipeline real o topo fecha mais rápido, mas não fecha mais: só a etapa 2 (piloto com controle) prova se priorizar o score gera receita.

Sheet Impacto_nMRR
A1: Extra — nMRR incremental ao priorizar quem tem maior propensão
A2: Lógica: parte da capacidade mensal dos ECs vai para o topo da propensão (top 30% do score). O ganho de conversão vem do lift do topo (taxa do top 30% ÷ média), descontado pelo fator de realização. O resultado principal é o UPLIFT %.
A4: Premissa | B4: Conservador | C4: Base | D4: Otimista | E4: Fonte / racional
A5: ECs na rede | B5: 44 | C5: =B5 -> 44 | D5: =B5 -> 44 | E5: Soma de num_executivos (aba franquias)
A6: Leads trabalhados por EC/mês | B6: 16.5 | C6: =B6 -> 16.5 | D6: =B6 -> 16.5 | E6: Média de leads_trabalhados (execucao_comercial)
A7: Taxa atual lead trabalhado → fechamento | B7: 0.0398 | C7: =B7 -> 0.0398 | D7: =B7 -> 0.0398 | E7: Σ fechamentos / Σ leads_trabalhados (execucao_comercial)
A8: % da capacidade redirecionada ao topo da propensão | B8: 0.3 | C8: 0.5 | D8: 0.6 | E8: Decisão de gestão (premissa)
A9: Lift do topo da propensão (top 30% ÷ média) | B9: =Como_Avaliar!$D$19 -> 2.2677596 | C9: =B9 -> 2.2677596 | D9: =B9 -> 2.2677596 | E9: Aba Como_Avaliar — descritivo, sem modelo
A10: Fator de realização do lift | B10: 0.25 | C10: 0.4 | D10: 0.6 | E10: Fração do lift que vira Ganho real (o target diverge do real — aba Como_Avaliar)
A11: Ticket MRR por novo cliente (R$) | B11: 590 | C11: =AVERAGE(Clientes!$D$2:$D$74) -> 1025.65 | D11: =AVERAGE(Clientes!$D$2:$D$74) -> 1025.65 | E11: Conservador: nMRR por fechamento da execução. Base/Otimista: mrr_inicial médio (clientes_ativos)
A12: Haircut de churn | B12: =COUNTIF(Clientes!$C$2:$C$74,"Churned")/COUNTA(Clientes!$A$2:$A$74) -> 0.20547945 | C12: =B12 -> 0.20547945 | D12: =B12 -> 0.20547945 | E12: Contratos Churned / total (vida do contrato) — desconto fixo, conservador
A13: nMRR oficial das 9 franquias abaixo da meta (R$/mês) | B13: 124000 | C13: =B13 -> 124000 | D13: =B13 -> 124000 | E13: franquias.realizado_nmrr_mes onde realizado < meta
A16: Cálculo | B16: Conservador | C16: Base | D16: Otimista | E16: Fórmula
A17: Leads trabalhados/mês (rede) | B17: =B5*B6 -> 726 | C17: =C5*C6 -> 726 | D17: =D5*D6 -> 726 | E17: ECs × leads por EC
A18: Leads redirecionados ao topo da propensão | B18: =B17*B8 -> 217.8 | C18: =C17*C8 -> 363 | D18: =D17*D8 -> 435.6 | E18: capacidade × % redirecionada
A19: Conversão nova nesses leads | B19: =B7*(1+(B9-1)*B10) -> 0.052414208 | C19: =C7*(1+(C9-1)*C10) -> 0.059982732 | D19: =D7*(1+(D9-1)*D10) -> 0.070074098 | E19: taxa atual × (1 + (lift − 1) × fator)
A20: Fechamentos incrementais/mês | B20: =B18*(B19-B7) -> 2.7473744 | C20: =C18*(C19-C7) -> 7.3263318 | D20: =D18*(D19-D7) -> 13.187397 | E20: leads redirecionados × ganho de conversão
A21: nMRR incremental/mês — escala da execução | B21: =B20*B11*(1-B12) -> 1287.8788 | C21: =C20*C11*(1-C12) -> 5970.2278 | D21: =D20*D11*(1-D12) -> 10746.41 | E21: fechamentos × ticket × (1 − churn)
A22: nMRR atual/mês — mesma escala | B22: =B17*B7*B11*(1-B12) -> 13544.932 | C22: =C17*C7*C11*(1-C12) -> 23546.373 | D22: =D17*D7*D11*(1-D12) -> 23546.373 | E22: leads × conversão × ticket × (1 − churn)
A23: UPLIFT no nMRR do canal | B23: =B21/B22 -> 0.095081967 | C23: =C21/C22 -> 0.25355191 | D23: =D21/D22 -> 0.45639344 | E23: incremental ÷ atual (independe da escala de receita)
A24: nMRR incremental/mês — escala oficial (franquias abaixo da meta) | B24: =B23*B13 -> 11790.164 | C24: =C23*C13 -> 31440.437 | D24: =D23*D13 -> 56592.787 | E24: uplift × realizado oficial dessas franquias
A27: Premissas assumidas
A28: • Capacidade dos ECs constante; o redirecionamento não muda o ticket nem o ciclo; sem custo adicional de aquisição.
A29: • O lift do topo foi medido no target converteu_omie; só uma fração (fator de realização) vira Ganho real.
A30: • Teste de estresse: com fator de realização = 0 (como o pipeline real sugere hoje), o uplift é zero — por isso o piloto.
A31: • O nMRR da execução é 10 a 27x menor que o oficial das franquias; por isso o uplift % é o número principal (franquias.realizado_nmrr_mes contra execucao_comercial.nmrr_gerado).

Sheet Previsao_Receita
A1: Previsibilidade de receita: quanto o pipeline atual deve gerar no próximo trimestre
A2: Dois métodos independentes, só com dados da base: (1) pipeline aberto ponderado pela chance de fechar de cada estágio; (2) run-rate histórico de Ganhos do CRM. Janela de 90 dias: nenhum Ganho da base fechou depois de 89 dias.
A4: 1. Chance de fechar por estágio (funil de execucao_comercial, 2024)
A5: Etapa do funil | B5: Volume | C5: Taxa da etapa
A6: Leads trabalhados | B6: 8699
A7: Reuniões realizadas | B7: 3617 | C7: =B7/B6 -> 0.41579492 | D7: Lead → reunião
A8: Propostas enviadas | B8: 1797 | C8: =B8/B7 -> 0.49682057 | D8: Reunião → proposta
A9: Fechamentos | B9: 346 | C9: =B9/B8 -> 0.19254313 | D9: Proposta → fechamento
A11: 2. Método 1: pipeline aberto ponderado (leads abertos há até 90 dias)
A12: Estágio do lead | B12: Leads abertos até 90 dias | C12: Chance de fechar | D12: Ganhos esperados | E12: Leads parados (> 90 dias): chance 0 | F12: De onde vem a chance
A13: Proposta Enviada | B13: =COUNTIFS(Leads!$D$2:$D$351,A13,Leads!$O$2:$O$351,"<=90") -> 15 | C13: =C9 -> 0.19254313 | D13: =B13*C13 -> 2.8881469 | E13: =COUNTIFS(Leads!$D$2:$D$351,A13,Leads!$O$2:$O$351,">90") -> 33 | F13: Proposta → fechamento
A14: Reunião Agendada | B14: =COUNTIFS(Leads!$D$2:$D$351,A14,Leads!$O$2:$O$351,"<=90") -> 15 | C14: =C8*C9 -> 0.095659386 | D14: =B14*C14 -> 1.4348908 | E14: =COUNTIFS(Leads!$D$2:$D$351,A14,Leads!$O$2:$O$351,">90") -> 26 | F14: Reunião → proposta → fechamento
A15: Em Contato | B15: =COUNTIFS(Leads!$D$2:$D$351,A15,Leads!$O$2:$O$351,"<=90") -> 31 | C15: =C7*C8*C9 -> 0.039774687 | D15: =B15*C15 -> 1.2330153 | E15: =COUNTIFS(Leads!$D$2:$D$351,A15,Leads!$O$2:$O$351,">90") -> 38 | F15: Lead → reunião → proposta → fechamento
A16: Novo | B16: =COUNTIFS(Leads!$D$2:$D$351,A16,Leads!$O$2:$O$351,"<=90") -> 33 | C16: =C7*C8*C9 -> 0.039774687 | D16: =B16*C16 -> 1.3125647 | E16: =COUNTIFS(Leads!$D$2:$D$351,A16,Leads!$O$2:$O$351,">90") -> 24 | F16: Lead → reunião → proposta → fechamento
A17: Sem Resposta | B17: =COUNTIFS(Leads!$D$2:$D$351,A17,Leads!$O$2:$O$351,"<=90") -> 9 | C17: 0 | D17: =B17*C17 -> 0 | E17: =COUNTIFS(Leads!$D$2:$D$351,A17,Leads!$O$2:$O$351,">90") -> 12 | F17: Fora do funil: o contador não respondeu
A18: Total | B18: =SUM(B13:B17) -> 103 | D18: =SUM(D13:D17) -> 6.8686177 | E18: =SUM(E13:E17) -> 133
A20: Ticket médio do Ganho (R$) | B20: =AVERAGEIF(Leads!$D$2:$D$351,"Ganho",Leads!$E$2:$E$351) -> 1025.65
A21: Churn dos contratos | B21: =COUNTIF(Clientes!$C$2:$C$74,"Churned")/COUNTA(Clientes!$A$2:$A$74) -> 0.20547945
A22: nMRR esperado do pipeline no trimestre (R$, escala do CRM) | B22: =D18*B20*(1-B21) -> 5597.2365
A24: 3. Método 2: run-rate histórico de Ganhos (CRM)
A25: Primeiro Ganho | B25: =MIN(Leads!$P$2:$P$351) -> 45304
A26: Último Ganho | B26: =MAX(Leads!$P$2:$P$351) -> 46088
A27: Meses de histórico | B27: =(YEAR(B26)-YEAR(B25))*12+MONTH(B26)-MONTH(B25)+1 -> 27
A28: Ganhos no período | B28: =COUNTIF(Leads!$D$2:$D$351,"Ganho") -> 73
A29: Ganhos por trimestre (run-rate) | B29: =B28/B27*3 -> 8.1111111
A30: Menor e maior trimestre fechado | B30: =MIN(D33:D40)&" a "&MAX(D33:D40) -> 3 a 12
A32: Trimestre | B32: Início | C32: Fim | D32: Ganhos
A33: 2024 T1 | B33: =DATE(2024,1,1) -> 45292 | C33: =EOMONTH(B33,2) -> 45382 | D33: =COUNTIFS(Leads!$D$2:$D$351,"Ganho",Leads!$P$2:$P$351,">="&B33,Leads!$P$2:$P$351,"<="&C33) -> 3
A34: 2024 T2 | B34: =DATE(2024,4,1) -> 45383 | C34: =EOMONTH(B34,2) -> 45473 | D34: =COUNTIFS(Leads!$D$2:$D$351,"Ganho",Leads!$P$2:$P$351,">="&B34,Leads!$P$2:$P$351,"<="&C34) -> 11
A35: 2024 T3 | B35: =DATE(2024,7,1) -> 45474 | C35: =EOMONTH(B35,2) -> 45565 | D35: =COUNTIFS(Leads!$D$2:$D$351,"Ganho",Leads!$P$2:$P$351,">="&B35,Leads!$P$2:$P$351,"<="&C35) -> 7
A36: 2024 T4 | B36: =DATE(2024,10,1) -> 45566 | C36: =EOMONTH(B36,2) -> 45657 | D36: =COUNTIFS(Leads!$D$2:$D$351,"Ganho",Leads!$P$2:$P$351,">="&B36,Leads!$P$2:$P$351,"<="&C36) -> 7
A37: 2025 T1 | B37: =DATE(2025,1,1) -> 45658 | C37: =EOMONTH(B37,2) -> 45747 | D37: =COUNTIFS(Leads!$D$2:$D$351,"Ganho",Leads!$P$2:$P$351,">="&B37,Leads!$P$2:$P$351,"<="&C37) -> 5
A38: 2025 T2 | B38: =DATE(2025,4,1) -> 45748 | C38: =EOMONTH(B38,2) -> 45838 | D38: =COUNTIFS(Leads!$D$2:$D$351,"Ganho",Leads!$P$2:$P$351,">="&B38,Leads!$P$2:$P$351,"<="&C38) -> 10
A39: 2025 T3 | B39: =DATE(2025,7,1) -> 45839 | C39: =EOMONTH(B39,2) -> 45930 | D39: =COUNTIFS(Leads!$D$2:$D$351,"Ganho",Leads!$P$2:$P$351,">="&B39,Leads!$P$2:$P$351,"<="&C39) -> 12
A40: 2025 T4 | B40: =DATE(2025,10,1) -> 45931 | C40: =EOMONTH(B40,2) -> 46022 | D40: =COUNTIFS(Leads!$D$2:$D$351,"Ganho",Leads!$P$2:$P$351,">="&B40,Leads!$P$2:$P$351,"<="&C40) -> 10
A41: 2026 T1 (parcial, até 07/03) | B41: =DATE(2026,1,1) -> 46023 | C41: =EOMONTH(B41,2) -> 46112 | D41: =COUNTIFS(Leads!$D$2:$D$351,"Ganho",Leads!$P$2:$P$351,">="&B41,Leads!$P$2:$P$351,"<="&C41) -> 8
A44: 4. Lacuna de previsibilidade e alavanca
A45: nMRR de Ganhos do CRM por mês (R$) | B45: =SUMIF(Leads!$D$2:$D$351,"Ganho",Leads!$E$2:$E$351)/B27 -> 2773.0537
A46: nMRR oficial da rede por mês (R$, aba franquias) | B46: 299000
A47: CRM ÷ oficial | B47: =B45/B46 -> 0.0092744271
A48: Ganhos previstos no trimestre com a priorização (cenário base do Impacto_nMRR) | B48: =D18*(1+Impacto_nMRR!C23) -> 8.6101688
A50: Leitura
A51: • Os dois métodos convergem (pipeline ponderado × run-rate): o pipeline do CRM é previsível no curto prazo.
A52: • Os leads parados há mais de 90 dias entram com chance zero: o pipeline nominal superestima o que vai fechar.
A53: • A chance de fechar por estágio vem de execucao_comercial (outra fonte) aplicada aos leads do CRM: é a melhor evidência da base, e a convergência com o run-rate mostra que funciona.
A54: • Lacuna: os Ganhos do CRM explicam uma fração mínima do nMRR oficial. Sem uma fonte única de nMRR, dá para prever o pipeline do CRM, mas não a receita oficial do canal.

Sheet Base
A1: id_contador | B1: estado | C1: regiao | D1: porte | E1: segmento_principal | F1: anos_mercado | G1: num_clientes_ativos | H1: num_funcionarios | I1: erp_atual | J1: tem_site | K1: presenca_linkedin | L1: status_omie | M1: converteu_omie | N1: faixa_anos | O1: faixa_clientes | P1: faixa_funcionarios | Q1: sem_erp | R1: icp | S1: enderecavel (regra 1a) | T1: score Fit + Engajamento (1c, 1 a 5) | U1: tier de prioridade (1c) | V1: taxa do porte | W1: taxa da faixa de funcionários | X1: taxa da faixa de clientes | Y1: taxa do ERP | Z1: taxa da faixa de anos | AA1: PROPENSÃO (média das 5 taxas) | AB1: faixa de propensão
A2: CTD00001 | B2: RS | C2: Sul | D2: Pequeno Escritório | E2: Construção Civil | F2: 7 | G2: 32 | H2: 10 | I2: Questor | J2: Sim | K2: Sim | L2: Prospect | M2: 1 | N2: =IF(F2<8,"1. < 8 anos",IF(F2<16,"2. 8 a 15 anos","3. 16+ anos")) -> 1. < 8 anos | O2: =IF(G2<20,"1. < 20",IF(G2<50,"2. 20 a 49",IF(G2<150,"3. 50 a 149","4. 150+"))) -> 2. 20 a 49 | P2: =IF(H2<=2,"1. 1 a 2",IF(H2<=5,"2. 3 a 5",IF(H2<=15,"3. 6 a 15","4. 16+"))) -> 3. 6 a 15 | Q2: =IF(OR(I2="Nenhum",I2="Planilha",I2="ContaAzul"),1,0) -> 0 | R2: =IF(AND(G2>=50,H2>=6,Q2=0),1,0) -> 0 | S2: =IF(AND(L2<>"Cliente Ativo",M2=0),1,0) -> 0 | V2: =AVERAGEIF($D$2:$D$601,D2,$M$2:$M$601) -> 0.43835616 | W2: =AVERAGEIF($P$2:$P$601,P2,$M$2:$M$601) -> 0.55319149 | X2: =AVERAGEIF($O$2:$O$601,O2,$M$2:$M$601) -> 0.25294118 | Y2: =AVERAGEIF($I$2:$I$601,I2,$M$2:$M$601) -> 0.39751553 | Z2: =AVERAGEIF($N$2:$N$601,N2,$M$2:$M$601) -> 0.22368421 | AA2: =ROUND(AVERAGE(V2:Z2),10) -> 0.37313771 | AB2: =IF(AA2>=Como_Avaliar!$B$15,"Alta",IF(AA2>=Como_Avaliar!$B$16,"Média","Baixa")) -> Média
A3: CTD00002 | B3: SP | C3: Sudeste | D3: Médio Escritório | E3: Saúde | F3: 20 | G3: 143 | H3: 20 | I3: Domínio | J3: Não | K3: Sim | L3: Prospect | M3: 1 | N3: =IF(F3<8,"1. < 8 anos",IF(F3<16,"2. 8 a 15 anos","3. 16+ anos")) -> 3. 16+ anos | O3: =IF(G3<20,"1. < 20",IF(G3<50,"2. 20 a 49",IF(G3<150,"3. 50 a 149","4. 150+"))) -> 3. 50 a 149 | P3: =IF(H3<=2,"1. 1 a 2",IF(H3<=5,"2. 3 a 5",IF(H3<=15,"3. 6 a 15","4. 16+"))) -> 4. 16+ | Q3: =IF(OR(I3="Nenhum",I3="Planilha",I3="ContaAzul"),1,0) -> 0 | R3: =IF(AND(G3>=50,H3>=6,Q3=0),1,0) -> 1 | S3: =IF(AND(L3<>"Cliente Ativo",M3=0),1,0) -> 0 | V3: =AVERAGEIF($D$2:$D$601,D3,$M$2:$M$601) -> 0.93975904 | W3: =AVERAGEIF($P$2:$P$601,P3,$M$2:$M$601) -> 0.97272727 | X3: =AVERAGEIF($O$2:$O$601,O3,$M$2:$M$601) -> 0.58992806 | Y3: =AVERAGEIF($I$2:$I$601,I3,$M$2:$M$601) -> 0.37662338 | Z3: =AVERAGEIF($N$2:$N$601,N3,$M$2:$M$601) -> 0.56634304 | AA3: =ROUND(AVERAGE(V3:Z3),10) -> 0.68907616 | AB3: =IF(AA3>=Como_Avaliar!$B$15,"Alta",IF(AA3>=Como_Avaliar!$B$16,"Média","Baixa")) -> Alta
A4: CTD00003 | B4: RJ | C4: Sudeste | D4: Grande Escritório | E4: Construção Civil | F4: 29 | G4: 526 | H4: 80 | I4: SAP | J4: Sim | K4: Não | L4: Lead Frio | M4: 1 | N4: =IF(F4<8,"1. < 8 anos",IF(F4<16,"2. 8 a 15 anos","3. 16+ anos")) -> 3. 16+ anos | O4: =IF(G4<20,"1. < 20",IF(G4<50,"2. 20 a 49",IF(G4<150,"3. 50 a 149","4. 150+"))) -> 4. 150+ | P4: =IF(H4<=2,"1. 1 a 2",IF(H4<=5,"2. 3 a 5",IF(H4<=15,"3. 6 a 15","4. 16+"))) -> 4. 16+ | Q4: =IF(OR(I4="Nenhum",I4="Planilha",I4="ContaAzul"),1,0) -> 0 | R4: =IF(AND(G4>=50,H4>=6,Q4=0),1,0) -> 1 | S4: =IF(AND(L4<>"Cliente Ativo",M4=0),1,0) -> 0 | V4: =AVERAGEIF($D$2:$D$601,D4,$M$2:$M$601) -> 1 | W4: =AVERAGEIF($P$2:$P$601,P4,$M$2:$M$601) -> 0.97272727 | X4: =AVERAGEIF($O$2:$O$601,O4,$M$2:$M$601) -> 0.97938144 | Y4: =AVERAGEIF($I$2:$I$601,I4,$M$2:$M$601) -> 1 | Z4: =AVERAGEIF($N$2:$N$601,N4,$M$2:$M$601) -> 0.56634304 | AA4: =ROUND(AVERAGE(V4:Z4),10) -> 0.90369035 | AB4: =IF(AA4>=Como_Avaliar!$B$15,"Alta",IF(AA4>=Como_Avaliar!$B$16,"Média","Baixa")) -> Alta
A5: CTD00004 | B5: RJ | C5: Sudeste | D5: Pequeno Escritório | E5: Tecnologia | F5: 15 | G5: 35 | H5: 4 | I5: Questor | J5: Não | K5: Sim | L5: Prospect | M5: 0 | N5: =IF(F5<8,"1. < 8 anos",IF(F5<16,"2. 8 a 15 anos","3. 16+ anos")) -> 2. 8 a 15 anos | O5: =IF(G5<20,"1. < 20",IF(G5<50,"2. 20 a 49",IF(G5<150,"3. 50 a 149","4. 150+"))) -> 2. 20 a 49 | P5: =IF(H5<=2,"1. 1 a 2",IF(H5<=5,"2. 3 a 5",IF(H5<=15,"3. 6 a 15","4. 16+"))) -> 2. 3 a 5 | Q5: =IF(OR(I5="Nenhum",I5="Planilha",I5="ContaAzul"),1,0) -> 0 | R5: =IF(AND(G5>=50,H5>=6,Q5=0),1,0) -> 0 | S5: =IF(AND(L5<>"Cliente Ativo",M5=0),1,0) -> 1 | T5: 4 | U5: Alta | V5: =AVERAGEIF($D$2:$D$601,D5,$M$2:$M$601) -> 0.43835616 | W5: =AVERAGEIF($P$2:$P$601,P5,$M$2:$M$601) -> 0.38095238 | X5: =AVERAGEIF($O$2:$O$601,O5,$M$2:$M$601) -> 0.25294118 | Y5: =AVERAGEIF($I$2:$I$601,I5,$M$2:$M$601) -> 0.39751553 | Z5: =AVERAGEIF($N$2:$N$601,N5,$M$2:$M$601) -> 0.22302158 | AA5: =ROUND(AVERAGE(V5:Z5),10) -> 0.33855737 | AB5: =IF(AA5>=Como_Avaliar!$B$15,"Alta",IF(AA5>=Como_Avaliar!$B$16,"Média","Baixa")) -> Média
A6: CTD00005 | B6: MT | C6: Centro-Oeste | D6: Médio Escritório | E6: Construção Civil | F6: 11 | G6: 160 | H6: 29 | I6: Domínio | J6: Sim | K6: Não | L6: Churned | M6: 0 | N6: =IF(F6<8,"1. < 8 anos",IF(F6<16,"2. 8 a 15 anos","3. 16+ anos")) -> 2. 8 a 15 anos | O6: =IF(G6<20,"1. < 20",IF(G6<50,"2. 20 a 49",IF(G6<150,"3. 50 a 149","4. 150+"))) -> 4. 150+ | P6: =IF(H6<=2,"1. 1 a 2",IF(H6<=5,"2. 3 a 5",IF(H6<=15,"3. 6 a 15","4. 16+"))) -> 4. 16+ | Q6: =IF(OR(I6="Nenhum",I6="Planilha",I6="ContaAzul"),1,0) -> 0 | R6: =IF(AND(G6>=50,H6>=6,Q6=0),1,0) -> 1 | S6: =IF(AND(L6<>"Cliente Ativo",M6=0),1,0) -> 1 | T6: 3 | U6: Média | V6: =AVERAGEIF($D$2:$D$601,D6,$M$2:$M$601) -> 0.93975904 | W6: =AVERAGEIF($P$2:$P$601,P6,$M$2:$M$601) -> 0.97272727 | X6: =AVERAGEIF($O$2:$O$601,O6,$M$2:$M$601) -> 0.97938144 | Y6: =AVERAGEIF($I$2:$I$601,I6,$M$2:$M$601) -> 0.37662338 | Z6: =AVERAGEIF($N$2:$N$601,N6,$M$2:$M$601) -> 0.22302158 | AA6: =ROUND(AVERAGE(V6:Z6),10) -> 0.69830254 | AB6: =IF(AA6>=Como_Avaliar!$B$15,"Alta",IF(AA6>=Como_Avaliar!$B$16,"Média","Baixa")) -> Alta
A7: CTD00006 | B7: GO | C7: Centro-Oeste | D7: Autônomo | E7: Tecnologia | F7: 8 | G7: 22 | H7: 2 | I7: ContaAzul | J7: Não | K7: Não | L7: Prospect | M7: 0 | N7: =IF(F7<8,"1. < 8 anos",IF(F7<16,"2. 8 a 15 anos","3. 16+ anos")) -> 2. 8 a 15 anos | O7: =IF(G7<20,"1. < 20",IF(G7<50,"2. 20 a 49",IF(G7<150,"3. 50 a 149","4. 150+"))) -> 2. 20 a 49 | P7: =IF(H7<=2,"1. 1 a 2",IF(H7<=5,"2. 3 a 5",IF(H7<=15,"3. 6 a 15","4. 16+"))) -> 1. 1 a 2 | Q7: =IF(OR(I7="Nenhum",I7="Planilha",I7="ContaAzul"),1,0) -> 1 | R7: =IF(AND(G7>=50,H7>=6,Q7=0),1,0) -> 0 | S7: =IF(AND(L7<>"Cliente Ativo",M7=0),1,0) -> 1 | T7: 2 | U7: Baixa | V7: =AVERAGEIF($D$2:$D$601,D7,$M$2:$M$601) -> 0.068273092 | W7: =AVERAGEIF($P$2:$P$601,P7,$M$2:$M$601) -> 0.086792453 | X7: =AVERAGEIF($O$2:$O$601,O7,$M$2:$M$601) -> 0.25294118 | Y7: =AVERAGEIF($I$2:$I$601,I7,$M$2:$M$601) -> 0 | Z7: =AVERAGEIF($N$2:$N$601,N7,$M$2:$M$601) -> 0.22302158 | AA7: =ROUND(AVERAGE(V7:Z7),10) -> 0.12620566 | AB7: =IF(AA7>=Como_Avaliar!$B$15,"Alta",IF(AA7>=Como_Avaliar!$B$16,"Média","Baixa")) -> Baixa
A8: CTD00007 | B8: PE | C8: Nordeste | D8: Autônomo | E8: Construção Civil | F8: 29 | G8: 12 | H8: 1 | I8: Planilha | J8: Não | K8: Sim | L8: Lead Quente | M8: 1 | N8: =IF(F8<8,"1. < 8 anos",IF(F8<16,"2. 8 a 15 anos","3. 16+ anos")) -> 3. 16+ anos | O8: =IF(G8<20,"1. < 20",IF(G8<50,"2. 20 a 49",IF(G8<150,"3. 50 a 149","4. 150+"))) -> 1. < 20 | P8: =IF(H8<=2,"1. 1 a 2",IF(H8<=5,"2. 3 a 5",IF(H8<=15,"3. 6 a 15","4. 16+"))) -> 1. 1 a 2 | Q8: =IF(OR(I8="Nenhum",I8="Planilha",I8="ContaAzul"),1,0) -> 1 | R8: =IF(AND(G8>=50,H8>=6,Q8=0),1,0) -> 0 | S8: =IF(AND(L8<>"Cliente Ativo",M8=0),1,0) -> 0 | V8: =AVERAGEIF($D$2:$D$601,D8,$M$2:$M$601) -> 0.068273092 | W8: =AVERAGEIF($P$2:$P$601,P8,$M$2:$M$601) -> 0.086792453 | X8: =AVERAGEIF($O$2:$O$601,O8,$M$2:$M$601) -> 0.10309278 | Y8: =AVERAGEIF($I$2:$I$601,I8,$M$2:$M$601) -> 0.15625 | Z8: =AVERAGEIF($N$2:$N$601,N8,$M$2:$M$601) -> 0.56634304 | AA8: =ROUND(AVERAGE(V8:Z8),10) -> 0.19615027 | AB8: =IF(AA8>=Como_Avaliar!$B$15,"Alta",IF(AA8>=Como_Avaliar!$B$16,"Média","Baixa")) -> Baixa
A9: CTD00008 | B9: SP | C9: Sudeste | D9: Autônomo | E9: Serviços | F9: 21 | G9: 21 | H9: 2 | I9: Planilha | J9: Sim | K9: Sim | L9: Prospect | M9: 0 | N9: =IF(F9<8,"1. < 8 anos",IF(F9<16,"2. 8 a 15 anos","3. 16+ anos")) -> 3. 16+ anos | O9: =IF(G9<20,"1. < 20",IF(G9<50,"2. 20 a 49",IF(G9<150,"3. 50 a 149","4. 150+"))) -> 2. 20 a 49 | P9: =IF(H9<=2,"1. 1 a 2",IF(H9<=5,"2. 3 a 5",IF(H9<=15,"3. 6 a 15","4. 16+"))) -> 1. 1 a 2 | Q9: =IF(OR(I9="Nenhum",I9="Planilha",I9="ContaAzul"),1,0) -> 1 | R9: =IF(AND(G9>=50,H9>=6,Q9=0),1,0) -> 0 | S9: =IF(AND(L9<>"Cliente Ativo",M9=0),1,0) -> 1 | T9: 2 | U9: Baixa | V9: =AVERAGEIF($D$2:$D$601,D9,$M$2:$M$601) -> 0.068273092 | W9: =AVERAGEIF($P$2:$P$601,P9,$M$2:$M$601) -> 0.086792453 | X9: =AVERAGEIF($O$2:$O$601,O9,$M$2:$M$601) -> 0.25294118 | Y9: =AVERAGEIF($I$2:$I$601,I9,$M$2:$M$601) -> 0.15625 | Z9: =AVERAGEIF($N$2:$N$601,N9,$M$2:$M$601) -> 0.56634304 | AA9: =ROUND(AVERAGE(V9:Z9),10) -> 0.22611995 | AB9: =IF(AA9>=Como_Avaliar!$B$15,"Alta",IF(AA9>=Como_Avaliar!$B$16,"Média","Baixa")) -> Baixa
A10: CTD00009 | B10: MG | C10: Sudeste | D10: Autônomo | E10: Varejo/Comércio | F10: 7 | G10: 13 | H10: 1 | I10: Nenhum | J10: Não | K10: Não | L10: Lead Frio | M10: 0 | N10: =IF(F10<8,"1. < 8 anos",IF(F10<16,"2. 8 a 15 anos","3. 16+ anos")) -> 1. < 8 anos | O10: =IF(G10<20,"1. < 20",IF(G10<50,"2. 20 a 49",IF(G10<150,"3. 50 a 149","4. 150+"))) -> 1. < 20 | P10: =IF(H10<=2,"1. 1 a 2",IF(H10<=5,"2. 3 a 5",IF(H10<=15,"3. 6 a 15","4. 16+"))) -> 1. 1 a 2 | Q10: =IF(OR(I10="Nenhum",I10="Planilha",I10="ContaAzul"),1,0) -> 1 | R10: =IF(AND(G10>=50,H10>=6,Q10=0),1,0) -> 0 | S10: =IF(AND(L10<>"Cliente Ativo",M10=0),1,0) -> 1 | T10: 2 | U10: Baixa | V10: =AVERAGEIF($D$2:$D$601,D10,$M$2:$M$601) -> 0.068273092 | W10: =AVERAGEIF($P$2:$P$601,P10,$M$2:$M$601) -> 0.086792453 | X10: =AVERAGEIF($O$2:$O$601,O10,$M$2:$M$601) -> 0.10309278 | Y10: =AVERAGEIF($I$2:$I$601,I10,$M$2:$M$601) -> 0.065217391 | Z10: =AVERAGEIF($N$2:$N$601,N10,$M$2:$M$601) -> 0.22368421 | AA10: =ROUND(AVERAGE(V10:Z10),10) -> 0.10941199 | AB10: =IF(AA10>=Como_Avaliar!$B$15,"Alta",IF(AA10>=Como_Avaliar!$B$16,"Média","Baixa")) -> Baixa
A11: CTD00010 | B11: SP | C11: Sudeste | D11: Pequeno Escritório | E11: Serviços | F11: 26 | G11: 79 | H11: 3 | I11: Alterdata | J11: Não | K11: Não | L11: Prospect | M11: 1 | N11: =IF(F11<8,"1. < 8 anos",IF(F11<16,"2. 8 a 15 anos","3. 16+ anos")) -> 3. 16+ anos | O11: =IF(G11<20,"1. < 20",IF(G11<50,"2. 20 a 49",IF(G11<150,"3. 50 a 149","4. 150+"))) -> 3. 50 a 149 | P11: =IF(H11<=2,"1. 1 a 2",IF(H11<=5,"2. 3 a 5",IF(H11<=15,"3. 6 a 15","4. 16+"))) -> 2. 3 a 5 | Q11: =IF(OR(I11="Nenhum",I11="Planilha",I11="ContaAzul"),1,0) -> 0 | R11: =IF(AND(G11>=50,H11>=6,Q11=0),1,0) -> 0 | S11: =IF(AND(L11<>"Cliente Ativo",M11=0),1,0) -> 0 | V11: =AVERAGEIF($D$2:$D$601,D11,$M$2:$M$601) -> 0.43835616 | W11: =AVERAGEIF($P$2:$P$601,P11,$M$2:$M$601) -> 0.38095238 | X11: =AVERAGEIF($O$2:$O$601,O11,$M$2:$M$601) -> 0.58992806 | Y11: =AVERAGEIF($I$2:$I$601,I11,$M$2:$M$601) -> 0.65217391 | Z11: =AVERAGEIF($N$2:$N$601,N11,$M$2:$M$601) -> 0.56634304 | AA11: =ROUND(AVERAGE(V11:Z11),10) -> 0.52555071 | AB11: =IF(AA11>=Como_Avaliar!$B$15,"Alta",IF(AA11>=Como_Avaliar!$B$16,"Média","Baixa")) -> Alta
A12: CTD00011 | B12: SP | C12: Sudeste | D12: Autônomo | E12: Saúde | F12: 19 | G12: 19 | H12: 1 | I12: ContaAzul | J12: Sim | K12: Não | L12: Lead Quente | M12: 0 | N12: =IF(F12<8,"1. < 8 anos",IF(F12<16,"2. 8 a 15 anos","3. 16+ anos")) -> 3. 16+ anos | O12: =IF(G12<20,"1. < 20",IF(G12<50,"2. 20 a 49",IF(G12<150,"3. 50 a 149","4. 150+"))) -> 1. < 20 | P12: =IF(H12<=2,"1. 1 a 2",IF(H12<=5,"2. 3 a 5",IF(H12<=15,"3. 6 a 15","4. 16+"))) -> 1. 1 a 2 | Q12: =IF(OR(I12="Nenhum",I12="Planilha",I12="ContaAzul"),1,0) -> 1 | R12: =IF(AND(G12>=50,H12>=6,Q12=0),1,0) -> 0 | S12: =IF(AND(L12<>"Cliente Ativo",M12=0),1,0) -> 1 | T12: 2 | U12: Baixa | V12: =AVERAGEIF($D$2:$D$601,D12,$M$2:$M$601) -> 0.068273092 | W12: =AVERAGEIF($P$2:$P$601,P12,$M$2:$M$601) -> 0.086792453 | X12: =AVERAGEIF($O$2:$O$601,O12,$M$2:$M$601) -> 0.10309278 | Y12: =AVERAGEIF($I$2:$I$601,I12,$M$2:$M$601) -> 0 | Z12: =AVERAGEIF($N$2:$N$601,N12,$M$2:$M$601) -> 0.56634304 | AA12: =ROUND(AVERAGE(V12:Z12),10) -> 0.16490027 | AB12: =IF(AA12>=Como_Avaliar!$B$15,"Alta",IF(AA12>=Como_Avaliar!$B$16,"Média","Baixa")) -> Baixa
A13: CTD00012 | B13: PR | C13: Sul | D13: Pequeno Escritório | E13: Agronegócio | F13: 23 | G13: 77 | H13: 6 | I13: Planilha | J13: Sim | K13: Sim | L13: Prospect | M13: 1 | N13: =IF(F13<8,"1. < 8 anos",IF(F13<16,"2. 8 a 15 anos","3. 16+ anos")) -> 3. 16+ anos | O13: =IF(G13<20,"1. < 20",IF(G13<50,"2. 20 a 49",IF(G13<150,"3. 50 a 149","4. 150+"))) -> 3. 50 a 149 | P13: =IF(H13<=2,"1. 1 a 2",IF(H13<=5,"2. 3 a 5",IF(H13<=15,"3. 6 a 15","4. 16+"))) -> 3. 6 a 15 | Q13: =IF(OR(I13="Nenhum",I13="Planilha",I13="ContaAzul"),1,0) -> 1 | R13: =IF(AND(G13>=50,H13>=6,Q13=0),1,0) -> 0 | S13: =IF(AND(L13<>"Cliente Ativo",M13=0),1,0) -> 0 | V13: =AVERAGEIF($D$2:$D$601,D13,$M$2:$M$601) -> 0.43835616 | W13: =AVERAGEIF($P$2:$P$601,P13,$M$2:$M$601) -> 0.55319149 | X13: =AVERAGEIF($O$2:$O$601,O13,$M$2:$M$601) -> 0.58992806 | Y13: =AVERAGEIF($I$2:$I$601,I13,$M$2:$M$601) -> 0.15625 | Z13: =AVERAGEIF($N$2:$N$601,N13,$M$2:$M$601) -> 0.56634304 | AA13: =ROUND(AVERAGE(V13:Z13),10) -> 0.46081375 | AB13: =IF(AA13>=Como_Avaliar!$B$15,"Alta",IF(AA13>=Como_Avaliar!$B$16,"Média","Baixa")) -> Média
A14: CTD00013 | B14: SP | C14: Sudeste | D14: Médio Escritório | E14: Tecnologia | F14: 11 | G14: 241 | H14: 12 | I14: Totvs | J14: Não | K14: Não | L14: Lead Frio | M14: 1 | N14: =IF(F14<8,"1. < 8 anos",IF(F14<16,"2. 8 a 15 anos","3. 16+ anos")) -> 2. 8 a 15 anos | O14: =IF(G14<20,"1. < 20",IF(G14<50,"2. 20 a 49",IF(G14<150,"3. 50 a 149","4. 150+"))) -> 4. 150+ | P14: =IF(H14<=2,"1. 1 a 2",IF(H14<=5,"2. 3 a 5",IF(H14<=15,"3. 6 a 15","4. 16+"))) -> 3. 6 a 15 | Q14: =IF(OR(I14="Nenhum",I14="Planilha",I14="ContaAzul"),1,0) -> 0 | R14: =IF(AND(G14>=50,H14>=6,Q14=0),1,0) -> 1 | S14: =IF(AND(L14<>"Cliente Ativo",M14=0),1,0) -> 0 | V14: =AVERAGEIF($D$2:$D$601,D14,$M$2:$M$601) -> 0.93975904 | W14: =AVERAGEIF($P$2:$P$601,P14,$M$2:$M$601) -> 0.55319149 | X14: =AVERAGEIF($O$2:$O$601,O14,$M$2:$M$601) -> 0.97938144 | Y14: =AVERAGEIF($I$2:$I$601,I14,$M$2:$M$601) -> 0.58333333 | Z14: =AVERAGEIF($N$2:$N$601,N14,$M$2:$M$601) -> 0.22302158 | AA14: =ROUND(AVERAGE(V14:Z14),10) -> 0.65573738 | AB14: =IF(AA14>=Como_Avaliar!$B$15,"Alta",IF(AA14>=Como_Avaliar!$B$16,"Média","Baixa")) -> Alta
A15: CTD00014 | B15: SP | C15: Sudeste | D15: Autônomo | E15: Serviços | F15: 11 | G15: 21 | H15: 2 | I15: Domínio | J15: Sim | K15: Sim | L15: Lead Frio | M15: 0 | N15: =IF(F15<8,"1. < 8 anos",IF(F15<16,"2. 8 a 15 anos","3. 16+ anos")) -> 2. 8 a 15 anos | O15: =IF(G15<20,"1. < 20",IF(G15<50,"2. 20 a 49",IF(G15<150,"3. 50 a 149","4. 150+"))) -> 2. 20 a 49 | P15: =IF(H15<=2,"1. 1 a 2",IF(H15<=5,"2. 3 a 5",IF(H15<=15,"3. 6 a 15","4. 16+"))) -> 1. 1 a 2 | Q15: =IF(OR(I15="Nenhum",I15="Planilha",I15="ContaAzul"),1,0) -> 0 | R15: =IF(AND(G15>=50,H15>=6,Q15=0),1,0) -> 0 | S15: =IF(AND(L15<>"Cliente Ativo",M15=0),1,0) -> 1 | T15: 2 | U15: Baixa | V15: =AVERAGEIF($D$2:$D$601,D15,$M$2:$M$601) -> 0.068273092 | W15: =AVERAGEIF($P$2:$P$601,P15,$M$2:$M$601) -> 0.086792453 | X15: =AVERAGEIF($O$2:$O$601,O15,$M$2:$M$601) -> 0.25294118 | Y15: =AVERAGEIF($I$2:$I$601,I15,$M$2:$M$601) -> 0.37662338 | Z15: =AVERAGEIF($N$2:$N$601,N15,$M$2:$M$601) -> 0.22302158 | AA15: =ROUND(AVERAGE(V15:Z15),10) -> 0.20153034 | AB15: =IF(AA15>=Como_Avaliar!$B$15,"Alta",IF(AA15>=Como_Avaliar!$B$16,"Média","Baixa")) -> Baixa
A16: CTD00015 | B16: RS | C16: Sul | D16: Pequeno Escritório | E16: Indústria | F16: 24 | G16: 53 | H16: 4 | I16: Domínio | J16: Sim | K16: Não | L16: Prospect | M16: 1 | N16: =IF(F16<8,"1. < 8 anos",IF(F16<16,"2. 8 a 15 anos","3. 16+ anos")) -> 3. 16+ anos | O16: =IF(G16<20,"1. < 20",IF(G16<50,"2. 20 a 49",IF(G16<150,"3. 50 a 149","4. 150+"))) -> 3. 50 a 149 | P16: =IF(H16<=2,"1. 1 a 2",IF(H16<=5,"2. 3 a 5",IF(H16<=15,"3. 6 a 15","4. 16+"))) -> 2. 3 a 5 | Q16: =IF(OR(I16="Nenhum",I16="Planilha",I16="ContaAzul"),1,0) -> 0 | R16: =IF(AND(G16>=50,H16>=6,Q16=0),1,0) -> 0 | S16: =IF(AND(L16<>"Cliente Ativo",M16=0),1,0) -> 0 | V16: =AVERAGEIF($D$2:$D$601,D16,$M$2:$M$601) -> 0.43835616 | W16: =AVERAGEIF($P$2:$P$601,P16,$M$2:$M$601) -> 0.38095238 | X16: =AVERAGEIF($O$2:$O$601,O16,$M$2:$M$601) -> 0.58992806 | Y16: =AVERAGEIF($I$2:$I$601,I16,$M$2:$M$601) -> 0.37662338 | Z16: =AVERAGEIF($N$2:$N$601,N16,$M$2:$M$601) -> 0.56634304 | AA16: =ROUND(AVERAGE(V16:Z16),10) -> 0.4704406 | AB16: =IF(AA16>=Como_Avaliar!$B$15,"Alta",IF(AA16>=Como_Avaliar!$B$16,"Média","Baixa")) -> Média
A17: CTD00016 | B17: PR | C17: Sul | D17: Autônomo | E17: Saúde | F17: 21 | G17: 18 | H17: 2 | I17: Domínio | J17: Não | K17: Sim | L17: Lead Frio | M17: 1 | N17: =IF(F17<8,"1. < 8 anos",IF(F17<16,"2. 8 a 15 anos","3. 16+ anos")) -> 3. 16+ anos | O17: =IF(G17<20,"1. < 20",IF(G17<50,"2. 20 a 49",IF(G17<150,"3. 50 a 149","4. 150+"))) -> 1. < 20 | P17: =IF(H17<=2,"1. 1 a 2",IF(H17<=5,"2. 3 a 5",IF(H17<=15,"3. 6 a 15","4. 16+"))) -> 1. 1 a 2 | Q17: =IF(OR(I17="Nenhum",I17="Planilha",I17="ContaAzul"),1,0) -> 0 | R17: =IF(AND(G17>=50,H17>=6,Q17=0),1,0) -> 0 | S17: =IF(AND(L17<>"Cliente Ativo",M17=0),1,0) -> 0 | V17: =AVERAGEIF($D$2:$D$601,D17,$M$2:$M$601) -> 0.068273092 | W17: =AVERAGEIF($P$2:$P$601,P17,$M$2:$M$601) -> 0.086792453 | X17: =AVERAGEIF($O$2:$O$601,O17,$M$2:$M$601) -> 0.10309278 | Y17: =AVERAGEIF($I$2:$I$601,I17,$M$2:$M$601) -> 0.37662338 | Z17: =AVERAGEIF($N$2:$N$601,N17,$M$2:$M$601) -> 0.56634304 | AA17: =ROUND(AVERAGE(V17:Z17),10) -> 0.24022495 | AB17: =IF(AA17>=Como_Avaliar!$B$15,"Alta",IF(AA17>=Como_Avaliar!$B$16,"Média","Baixa")) -> Média
A18: CTD00017 | B18: RJ | C18: Sudeste | D18: Autônomo | E18: Tecnologia | F18: 4 | G18: 3 | H18: 2 | I18: Nenhum | J18: Não | K18: Sim | L18: Prospect | M18: 0 | N18: =IF(F18<8,"1. < 8 anos",IF(F18<16,"2. 8 a 15 anos","3. 16+ anos")) -> 1. < 8 anos | O18: =IF(G18<20,"1. < 20",IF(G18<50,"2. 20 a 49",IF(G18<150,"3. 50 a 149","4. 150+"))) -> 1. < 20 | P18: =IF(H18<=2,"1. 1 a 2",IF(H18<=5,"2. 3 a 5",IF(H18<=15,"3. 6 a 15","4. 16+"))) -> 1. 1 a 2 | Q18: =IF(OR(I18="Nenhum",I18="Planilha",I18="ContaAzul"),1,0) -> 1 | R18: =IF(AND(G18>=50,H18>=6,Q18=0),1,0) -> 0 | S18: =IF(AND(L18<>"Cliente Ativo",M18=0),1,0) -> 1 | T18: 2 | U18: Baixa | V18: =AVERAGEIF($D$2:$D$601,D18,$M$2:$M$601) -> 0.068273092 | W18: =AVERAGEIF($P$2:$P$601,P18,$M$2:$M$601) -> 0.086792453 | X18: =AVERAGEIF($O$2:$O$601,O18,$M$2:$M$601) -> 0.10309278 | Y18: =AVERAGEIF($I$2:$I$601,I18,$M$2:$M$601) -> 0.065217391 | Z18: =AVERAGEIF($N$2:$N$601,N18,$M$2:$M$601) -> 0.22368421 | AA18: =ROUND(AVERAGE(V18:Z18),10) -> 0.10941199 | AB18: =IF(AA18>=Como_Avaliar!$B$15,"Alta",IF(AA18>=Como_Avaliar!$B$16,"Média","Baixa")) -> Baixa
A19: CTD00018 | B19: SC | C19: Sul | D19: Autônomo | E19: Saúde | F19: 8 | G19: 14 | H19: 2 | I19: Questor | J19: Não | K19: Sim | L19: Prospect | M19: 0 | N19: =IF(F19<8,"1. < 8 anos",IF(F19<16,"2. 8 a 15 anos","3. 16+ anos")) -> 2. 8 a 15 anos | O19: =IF(G19<20,"1. < 20",IF(G19<50,"2. 20 a 49",IF(G19<150,"3. 50 a 149","4. 150+"))) -> 1. < 20 | P19: =IF(H19<=2,"1. 1 a 2",IF(H19<=5,"2. 3 a 5",IF(H19<=15,"3. 6 a 15","4. 16+"))) -> 1. 1 a 2 | Q19: =IF(OR(I19="Nenhum",I19="Planilha",I19="ContaAzul"),1,0) -> 0 | R19: =IF(AND(G19>=50,H19>=6,Q19=0),1,0) -> 0 | S19: =IF(AND(L19<>"Cliente Ativo",M19=0),1,0) -> 1 | T19: 3 | U19: Média | V19: =AVERAGEIF($D$2:$D$601,D19,$M$2:$M$601) -> 0.068273092 | W19: =AVERAGEIF($P$2:$P$601,P19,$M$2:$M$601) -> 0.086792453 | X19: =AVERAGEIF($O$2:$O$601,O19,$M$2:$M$601) -> 0.10309278 | Y19: =AVERAGEIF($I$2:$I$601,I19,$M$2:$M$601) -> 0.39751553 | Z19: =AVERAGEIF($N$2:$N$601,N19,$M$2:$M$601) -> 0.22302158 | AA19: =ROUND(AVERAGE(V19:Z19),10) -> 0.17573909 | AB19: =IF(AA19>=Como_Avaliar!$B$15,"Alta",IF(AA19>=Como_Avaliar!$B$16,"Média","Baixa")) -> Baixa
A20: CTD00019 | B20: DF | C20: Centro-Oeste | D20: Pequeno Escritório | E20: Varejo/Comércio | F20: 24 | G20: 57 | H20: 3 | I20: Totvs | J20: Não | K20: Não | L20: Prospect | M20: 1 | N20: =IF(F20<8,"1. < 8 anos",IF(F20<16,"2. 8 a 15 anos","3. 16+ anos")) -> 3. 16+ anos | O20: =IF(G20<20,"1. < 20",IF(G20<50,"2. 20 a 49",IF(G20<150,"3. 50 a 149","4. 150+"))) -> 3. 50 a 149 | P20: =IF(H20<=2,"1. 1 a 2",IF(H20<=5,"2. 3 a 5",IF(H20<=15,"3. 6 a 15","4. 16+"))) -> 2. 3 a 5 | Q20: =IF(OR(I20="Nenhum",I20="Planilha",I20="ContaAzul"),1,0) -> 0 | R20: =IF(AND(G20>=50,H20>=6,Q20=0),1,0) -> 0 | S20: =IF(AND(L20<>"Cliente Ativo",M20=0),1,0) -> 0 | V20: =AVERAGEIF($D$2:$D$601,D20,$M$2:$M$601) -> 0.43835616 | W20: =AVERAGEIF($P$2:$P$601,P20,$M$2:$M$601) -> 0.38095238 | X20: =AVERAGEIF($O$2:$O$601,O20,$M$2:$M$601) -> 0.58992806 | Y20: =AVERAGEIF($I$2:$I$601,I20,$M$2:$M$601) -> 0.58333333 | Z20: =AVERAGEIF($N$2:$N$601,N20,$M$2:$M$601) -> 0.56634304 | AA20: =ROUND(AVERAGE(V20:Z20),10) -> 0.5117826 | AB20: =IF(AA20>=Como_Avaliar!$B$15,"Alta",IF(AA20>=Como_Avaliar!$B$16,"Média","Baixa")) -> Alta
A21: CTD00020 | B21: SP | C21: Sudeste | D21: Pequeno Escritório | E21: Agronegócio | F21: 3 | G21: 29 | H21: 3 | I21: Domínio | J21: Não | K21: Não | L21: Lead Quente | M21: 0 | N21: =IF(F21<8,"1. < 8 anos",IF(F21<16,"2. 8 a 15 anos","3. 16+ anos")) -> 1. < 8 anos | O21: =IF(G21<20,"1. < 20",IF(G21<50,"2. 20 a 49",IF(G21<150,"3. 50 a 149","4. 150+"))) -> 2. 20 a 49 | P21: =IF(H21<=2,"1. 1 a 2",IF(H21<=5,"2. 3 a 5",IF(H21<=15,"3. 6 a 15","4. 16+"))) -> 2. 3 a 5 | Q21: =IF(OR(I21="Nenhum",I21="Planilha",I21="ContaAzul"),1,0) -> 0 | R21: =IF(AND(G21>=50,H21>=6,Q21=0),1,0) -> 0 | S21: =IF(AND(L21<>"Cliente Ativo",M21=0),1,0) -> 1 | T21: 3 | U21: Média | V21: =AVERAGEIF($D$2:$D$601,D21,$M$2:$M$601) -> 0.43835616 | W21: =AVERAGEIF($P$2:$P$601,P21,$M$2:$M$601) -> 0.38095238 | X21: =AVERAGEIF($O$2:$O$601,O21,$M$2:$M$601) -> 0.25294118 | Y21: =AVERAGEIF($I$2:$I$601,I21,$M$2:$M$601) -> 0.37662338 | Z21: =AVERAGEIF($N$2:$N$601,N21,$M$2:$M$601) -> 0.22368421 | AA21: =ROUND(AVERAGE(V21:Z21),10) -> 0.33451146 | AB21: =IF(AA21>=Como_Avaliar!$B$15,"Alta",IF(AA21>=Como_Avaliar!$B$16,"Média","Baixa")) -> Média
A22: CTD00021 | B22: DF | C22: Centro-Oeste | D22: Médio Escritório | E22: Varejo/Comércio | F22: 22 | G22: 166 | H22: 8 | I22: Domínio | J22: Não | K22: Não | L22: Prospect | M22: 1 | N22: =IF(F22<8,"1. < 8 anos",IF(F22<16,"2. 8 a 15 anos","3. 16+ anos")) -> 3. 16+ anos | O22: =IF(G22<20,"1. < 20",IF(G22<50,"2. 20 a 49",IF(G22<150,"3. 50 a 149","4. 150+"))) -> 4. 150+ | P22: =IF(H22<=2,"1. 1 a 2",IF(H22<=5,"2. 3 a 5",IF(H22<=15,"3. 6 a 15","4. 16+"))) -> 3. 6 a 15 | Q22: =IF(OR(I22="Nenhum",I22="Planilha",I22="ContaAzul"),1,0) -> 0 | R22: =IF(AND(G22>=50,H22>=6,Q22=0),1,0) -> 1 | S22: =IF(AND(L22<>"Cliente Ativo",M22=0),1,0) -> 0 | V22: =AVERAGEIF($D$2:$D$601,D22,$M$2:$M$601) -> 0.93975904 | W22: =AVERAGEIF($P$2:$P$601,P22,$M$2:$M$601) -> 0.55319149 | X22: =AVERAGEIF($O$2:$O$601,O22,$M$2:$M$601) -> 0.97938144 | Y22: =AVERAGEIF($I$2:$I$601,I22,$M$2:$M$601) -> 0.37662338 | Z22: =AVERAGEIF($N$2:$N$601,N22,$M$2:$M$601) -> 0.56634304 | AA22: =ROUND(AVERAGE(V22:Z22),10) -> 0.68305968 | AB22: =IF(AA22>=Como_Avaliar!$B$15,"Alta",IF(AA22>=Como_Avaliar!$B$16,"Média","Baixa")) -> Alta
A23: CTD00022 | B23: GO | C23: Centro-Oeste | D23: Pequeno Escritório | E23: Indústria | F23: 21 | G23: 54 | H23: 6 | I23: Totvs | J23: Sim | K23: Sim | L23: Prospect | M23: 0 | N23: =IF(F23<8,"1. < 8 anos",IF(F23<16,"2. 8 a 15 anos","3. 16+ anos")) -> 3. 16+ anos | O23: =IF(G23<20,"1. < 20",IF(G23<50,"2. 20 a 49",IF(G23<150,"3. 50 a 149","4. 150+"))) -> 3. 50 a 149 | P23: =IF(H23<=2,"1. 1 a 2",IF(H23<=5,"2. 3 a 5",IF(H23<=15,"3. 6 a 15","4. 16+"))) -> 3. 6 a 15 | Q23: =IF(OR(I23="Nenhum",I23="Planilha",I23="ContaAzul"),1,0) -> 0 | R23: =IF(AND(G23>=50,H23>=6,Q23=0),1,0) -> 1 | S23: =IF(AND(L23<>"Cliente Ativo",M23=0),1,0) -> 1 | T23: 3 | U23: Média | V23: =AVERAGEIF($D$2:$D$601,D23,$M$2:$M$601) -> 0.43835616 | W23: =AVERAGEIF($P$2:$P$601,P23,$M$2:$M$601) -> 0.55319149 | X23: =AVERAGEIF($O$2:$O$601,O23,$M$2:$M$601) -> 0.58992806 | Y23: =AVERAGEIF($I$2:$I$601,I23,$M$2:$M$601) -> 0.58333333 | Z23: =AVERAGEIF($N$2:$N$601,N23,$M$2:$M$601) -> 0.56634304 | AA23: =ROUND(AVERAGE(V23:Z23),10) -> 0.54623042 | AB23: =IF(AA23>=Como_Avaliar!$B$15,"Alta",IF(AA23>=Como_Avaliar!$B$16,"Média","Baixa")) -> Alta
A24: CTD00023 | B24: MG | C24: Sudeste | D24: Pequeno Escritório | E24: Varejo/Comércio | F24: 2 | G24: 18 | H24: 9 | I24: Totvs | J24: Não | K24: Sim | L24: Lead Frio | M24: 0 | N24: =IF(F24<8,"1. < 8 anos",IF(F24<16,"2. 8 a 15 anos","3. 16+ anos")) -> 1. < 8 anos | O24: =IF(G24<20,"1. < 20",IF(G24<50,"2. 20 a 49",IF(G24<150,"3. 50 a 149","4. 150+"))) -> 1. < 20 | P24: =IF(H24<=2,"1. 1 a 2",IF(H24<=5,"2. 3 a 5",IF(H24<=15,"3. 6 a 15","4. 16+"))) -> 3. 6 a 15 | Q24: =IF(OR(I24="Nenhum",I24="Planilha",I24="ContaAzul"),1,0) -> 0 | R24: =IF(AND(G24>=50,H24>=6,Q24=0),1,0) -> 0 | S24: =IF(AND(L24<>"Cliente Ativo",M24=0),1,0) -> 1 | T24: 2 | U24: Baixa | V24: =AVERAGEIF($D$2:$D$601,D24,$M$2:$M$601) -> 0.43835616 | W24: =AVERAGEIF($P$2:$P$601,P24,$M$2:$M$601) -> 0.55319149 | X24: =AVERAGEIF($O$2:$O$601,O24,$M$2:$M$601) -> 0.10309278 | Y24: =AVERAGEIF($I$2:$I$601,I24,$M$2:$M$601) -> 0.58333333 | Z24: =AVERAGEIF($N$2:$N$601,N24,$M$2:$M$601) -> 0.22368421 | AA24: =ROUND(AVERAGE(V24:Z24),10) -> 0.3803316 | AB24: =IF(AA24>=Como_Avaliar!$B$15,"Alta",IF(AA24>=Como_Avaliar!$B$16,"Média","Baixa")) -> Média
A25: CTD00024 | B25: SP | C25: Sudeste | D25: Pequeno Escritório | E25: Serviços | F25: 24 | G25: 75 | H25: 7 | I25: Questor | J25: Não | K25: Não | L25: Lead Frio | M25: 1 | N25: =IF(F25<8,"1. < 8 anos",IF(F25<16,"2. 8 a 15 anos","3. 16+ anos")) -> 3. 16+ anos | O25: =IF(G25<20,"1. < 20",IF(G25<50,"2. 20 a 49",IF(G25<150,"3. 50 a 149","4. 150+"))) -> 3. 50 a 149 | P25: =IF(H25<=2,"1. 1 a 2",IF(H25<=5,"2. 3 a 5",IF(H25<=15,"3. 6 a 15","4. 16+"))) -> 3. 6 a 15 | Q25: =IF(OR(I25="Nenhum",I25="Planilha",I25="ContaAzul"),1,0) -> 0 | R25: =IF(AND(G25>=50,H25>=6,Q25=0),1,0) -> 1 | S25: =IF(AND(L25<>"Cliente Ativo",M25=0),1,0) -> 0 | V25: =AVERAGEIF($D$2:$D$601,D25,$M$2:$M$601) -> 0.43835616 | W25: =AVERAGEIF($P$2:$P$601,P25,$M$2:$M$601) -> 0.55319149 | X25: =AVERAGEIF($O$2:$O$601,O25,$M$2:$M$601) -> 0.58992806 | Y25: =AVERAGEIF($I$2:$I$601,I25,$M$2:$M$601) -> 0.39751553 | Z25: =AVERAGEIF($N$2:$N$601,N25,$M$2:$M$601) -> 0.56634304 | AA25: =ROUND(AVERAGE(V25:Z25),10) -> 0.50906686 | AB25: =IF(AA25>=Como_Avaliar!$B$15,"Alta",IF(AA25>=Como_Avaliar!$B$16,"Média","Baixa")) -> Alta
A26: CTD00025 | B26: MA | C26: Nordeste | D26: Pequeno Escritório | E26: Saúde | F26: 12 | G26: 48 | H26: 6 | I26: Questor | J26: Não | K26: Não | L26: Cliente Ativo | M26: 0 | N26: =IF(F26<8,"1. < 8 anos",IF(F26<16,"2. 8 a 15 anos","3. 16+ anos")) -> 2. 8 a 15 anos | O26: =IF(G26<20,"1. < 20",IF(G26<50,"2. 20 a 49",IF(G26<150,"3. 50 a 149","4. 150+"))) -> 2. 20 a 49 | P26: =IF(H26<=2,"1. 1 a 2",IF(H26<=5,"2. 3 a 5",IF(H26<=15,"3. 6 a 15","4. 16+"))) -> 3. 6 a 15 | Q26: =IF(OR(I26="Nenhum",I26="Planilha",I26="ContaAzul"),1,0) -> 0 | R26: =IF(AND(G26>=50,H26>=6,Q26=0),1,0) -> 0 | S26: =IF(AND(L26<>"Cliente Ativo",M26=0),1,0) -> 0 | V26: =AVERAGEIF($D$2:$D$601,D26,$M$2:$M$601) -> 0.43835616 | W26: =AVERAGEIF($P$2:$P$601,P26,$M$2:$M$601) -> 0.55319149 | X26: =AVERAGEIF($O$2:$O$601,O26,$M$2:$M$601) -> 0.25294118 | Y26: =AVERAGEIF($I$2:$I$601,I26,$M$2:$M$601) -> 0.39751553 | Z26: =AVERAGEIF($N$2:$N$601,N26,$M$2:$M$601) -> 0.22302158 | AA26: =ROUND(AVERAGE(V26:Z26),10) -> 0.37300519 | AB26: =IF(AA26>=Como_Avaliar!$B$15,"Alta",IF(AA26>=Como_Avaliar!$B$16,"Média","Baixa")) -> Média
A27: CTD00026 | B27: RJ | C27: Sudeste | D27: Pequeno Escritório | E27: Saúde | F27: 6 | G27: 44 | H27: 3 | I27: Planilha | J27: Não | K27: Sim | L27: Prospect | M27: 0 | N27: =IF(F27<8,"1. < 8 anos",IF(F27<16,"2. 8 a 15 anos","3. 16+ anos")) -> 1. < 8 anos | O27: =IF(G27<20,"1. < 20",IF(G27<50,"2. 20 a 49",IF(G27<150,"3. 50 a 149","4. 150+"))) -> 2. 20 a 49 | P27: =IF(H27<=2,"1. 1 a 2",IF(H27<=5,"2. 3 a 5",IF(H27<=15,"3. 6 a 15","4. 16+"))) -> 2. 3 a 5 | Q27: =IF(OR(I27="Nenhum",I27="Planilha",I27="ContaAzul"),1,0) -> 1 | R27: =IF(AND(G27>=50,H27>=6,Q27=0),1,0) -> 0 | S27: =IF(AND(L27<>"Cliente Ativo",M27=0),1,0) -> 1 | T27: 4 | U27: Alta | V27: =AVERAGEIF($D$2:$D$601,D27,$M$2:$M$601) -> 0.43835616 | W27: =AVERAGEIF($P$2:$P$601,P27,$M$2:$M$601) -> 0.38095238 | X27: =AVERAGEIF($O$2:$O$601,O27,$M$2:$M$601) -> 0.25294118 | Y27: =AVERAGEIF($I$2:$I$601,I27,$M$2:$M$601) -> 0.15625 | Z27: =AVERAGEIF($N$2:$N$601,N27,$M$2:$M$601) -> 0.22368421 | AA27: =ROUND(AVERAGE(V27:Z27),10) -> 0.29043679 | AB27: =IF(AA27>=Como_Avaliar!$B$15,"Alta",IF(AA27>=Como_Avaliar!$B$16,"Média","Baixa")) -> Média
A28: CTD00027 | B28: SP | C28: Sudeste | D28: Pequeno Escritório | E28: Tecnologia | F28: 2 | G28: 21 | H28: 4 | I28: Alterdata | J28: Sim | K28: Sim | L28: Prospect | M28: 0 | N28: =IF(F28<8,"1. < 8 anos",IF(F28<16,"2. 8 a 15 anos","3. 16+ anos")) -> 1. < 8 anos | O28: =IF(G28<20,"1. < 20",IF(G28<50,"2. 20 a 49",IF(G28<150,"3. 50 a 149","4. 150+"))) -> 2. 20 a 49 | P28: =IF(H28<=2,"1. 1 a 2",IF(H28<=5,"2. 3 a 5",IF(H28<=15,"3. 6 a 15","4. 16+"))) -> 2. 3 a 5 | Q28: =IF(OR(I28="Nenhum",I28="Planilha",I28="ContaAzul"),1,0) -> 0 | R28: =IF(AND(G28>=50,H28>=6,Q28=0),1,0) -> 0 | S28: =IF(AND(L28<>"Cliente Ativo",M28=0),1,0) -> 1 | T28: 2 | U28: Baixa | V28: =AVERAGEIF($D$2:$D$601,D28,$M$2:$M$601) -> 0.43835616 | W28: =AVERAGEIF($P$2:$P$601,P28,$M$2:$M$601) -> 0.38095238 | X28: =AVERAGEIF($O$2:$O$601,O28,$M$2:$M$601) -> 0.25294118 | Y28: =AVERAGEIF($I$2:$I$601,I28,$M$2:$M$601) -> 0.65217391 | Z28: =AVERAGEIF($N$2:$N$601,N28,$M$2:$M$601) -> 0.22368421 | AA28: =ROUND(AVERAGE(V28:Z28),10) -> 0.38962157 | AB28: =IF(AA28>=Como_Avaliar!$B$15,"Alta",IF(AA28>=Como_Avaliar!$B$16,"Média","Baixa")) -> Média
A29: CTD00028 | B29: SP | C29: Sudeste | D29: Autônomo | E29: Construção Civil | F29: 28 | G29: 21 | H29: 1 | I29: Questor | J29: Não | K29: Não | L29: Prospect | M29: 0 | N29: =IF(F29<8,"1. < 8 anos",IF(F29<16,"2. 8 a 15 anos","3. 16+ anos")) -> 3. 16+ anos | O29: =IF(G29<20,"1. < 20",IF(G29<50,"2. 20 a 49",IF(G29<150,"3. 50 a 149","4. 150+"))) -> 2. 20 a 49 | P29: =IF(H29<=2,"1. 1 a 2",IF(H29<=5,"2. 3 a 5",IF(H29<=15,"3. 6 a 15","4. 16+"))) -> 1. 1 a 2 | Q29: =IF(OR(I29="Nenhum",I29="Planilha",I29="ContaAzul"),1,0) -> 0 | R29: =IF(AND(G29>=50,H29>=6,Q29=0),1,0) -> 0 | S29: =IF(AND(L29<>"Cliente Ativo",M29=0),1,0) -> 1 | T29: 2 | U29: Baixa | V29: =AVERAGEIF($D$2:$D$601,D29,$M$2:$M$601) -> 0.068273092 | W29: =AVERAGEIF($P$2:$P$601,P29,$M$2:$M$601) -> 0.086792453 | X29: =AVERAGEIF($O$2:$O$601,O29,$M$2:$M$601) -> 0.25294118 | Y29: =AVERAGEIF($I$2:$I$601,I29,$M$2:$M$601) -> 0.39751553 | Z29: =AVERAGEIF($N$2:$N$601,N29,$M$2:$M$601) -> 0.56634304 | AA29: =ROUND(AVERAGE(V29:Z29),10) -> 0.27437306 | AB29: =IF(AA29>=Como_Avaliar!$B$15,"Alta",IF(AA29>=Como_Avaliar!$B$16,"Média","Baixa")) -> Média
A30: CTD00029 | B30: BA | C30: Nordeste | D30: Autônomo | E30: Varejo/Comércio | F30: 21 | G30: 18 | H30: 1 | I30: Domínio | J30: Sim | K30: Sim | L30: Cliente Ativo | M30: 0 | N30: =IF(F30<8,"1. < 8 anos",IF(F30<16,"2. 8 a 15 anos","3. 16+ anos")) -> 3. 16+ anos | O30: =IF(G30<20,"1. < 20",IF(G30<50,"2. 20 a 49",IF(G30<150,"3. 50 a 149","4. 150+"))) -> 1. < 20 | P30: =IF(H30<=2,"1. 1 a 2",IF(H30<=5,"2. 3 a 5",IF(H30<=15,"3. 6 a 15","4. 16+"))) -> 1. 1 a 2 | Q30: =IF(OR(I30="Nenhum",I30="Planilha",I30="ContaAzul"),1,0) -> 0 | R30: =IF(AND(G30>=50,H30>=6,Q30=0),1,0) -> 0 | S30: =IF(AND(L30<>"Cliente Ativo",M30=0),1,0) -> 0 | V30: =AVERAGEIF($D$2:$D$601,D30,$M$2:$M$601) -> 0.068273092 | W30: =AVERAGEIF($P$2:$P$601,P30,$M$2:$M$601) -> 0.086792453 | X30: =AVERAGEIF($O$2:$O$601,O30,$M$2:$M$601) -> 0.10309278 | Y30: =AVERAGEIF($I$2:$I$601,I30,$M$2:$M$601) -> 0.37662338 | Z30: =AVERAGEIF($N$2:$N$601,N30,$M$2:$M$601) -> 0.56634304 | AA30: =ROUND(AVERAGE(V30:Z30),10) -> 0.24022495 | AB30: =IF(AA30>=Como_Avaliar!$B$15,"Alta",IF(AA30>=Como_Avaliar!$B$16,"Média","Baixa")) -> Média
A31: CTD00030 | B31: RS | C31: Sul | D31: Médio Escritório | E31: Serviços | F31: 1 | G31: 103 | H31: 21 | I31: Alterdata | J31: Não | K31: Não | L31: Sem Contato | M31: 1 | N31: =IF(F31<8,"1. < 8 anos",IF(F31<16,"2. 8 a 15 anos","3. 16+ anos")) -> 1. < 8 anos | O31: =IF(G31<20,"1. < 20",IF(G31<50,"2. 20 a 49",IF(G31<150,"3. 50 a 149","4. 150+"))) -> 3. 50 a 149 | P31: =IF(H31<=2,"1. 1 a 2",IF(H31<=5,"2. 3 a 5",IF(H31<=15,"3. 6 a 15","4. 16+"))) -> 4. 16+ | Q31: =IF(OR(I31="Nenhum",I31="Planilha",I31="ContaAzul"),1,0) -> 0 | R31: =IF(AND(G31>=50,H31>=6,Q31=0),1,0) -> 1 | S31: =IF(AND(L31<>"Cliente Ativo",M31=0),1,0) -> 0 | V31: =AVERAGEIF($D$2:$D$601,D31,$M$2:$M$601) -> 0.93975904 | W31: =AVERAGEIF($P$2:$P$601,P31,$M$2:$M$601) -> 0.97272727 | X31: =AVERAGEIF($O$2:$O$601,O31,$M$2:$M$601) -> 0.58992806 | Y31: =AVERAGEIF($I$2:$I$601,I31,$M$2:$M$601) -> 0.65217391 | Z31: =AVERAGEIF($N$2:$N$601,N31,$M$2:$M$601) -> 0.22368421 | AA31: =ROUND(AVERAGE(V31:Z31),10) -> 0.6756545 | AB31: =IF(AA31>=Como_Avaliar!$B$15,"Alta",IF(AA31>=Como_Avaliar!$B$16,"Média","Baixa")) -> Alta
A32: CTD00031 | B32: DF | C32: Centro-Oeste | D32: Médio Escritório | E32: Agronegócio | F32: 12 | G32: 194 | H32: 22 | I32: Totvs | J32: Não | K32: Não | L32: Churned | M32: 1 | N32: =IF(F32<8,"1. < 8 anos",IF(F32<16,"2. 8 a 15 anos","3. 16+ anos")) -> 2. 8 a 15 anos | O32: =IF(G32<20,"1. < 20",IF(G32<50,"2. 20 a 49",IF(G32<150,"3. 50 a 149","4. 150+"))) -> 4. 150+ | P32: =IF(H32<=2,"1. 1 a 2",IF(H32<=5,"2. 3 a 5",IF(H32<=15,"3. 6 a 15","4. 16+"))) -> 4. 16+ | Q32: =IF(OR(I32="Nenhum",I32="Planilha",I32="ContaAzul"),1,0) -> 0 | R32: =IF(AND(G32>=50,H32>=6,Q32=0),1,0) -> 1 | S32: =IF(AND(L32<>"Cliente Ativo",M32=0),1,0) -> 0 | V32: =AVERAGEIF($D$2:$D$601,D32,$M$2:$M$601) -> 0.93975904 | W32: =AVERAGEIF($P$2:$P$601,P32,$M$2:$M$601) -> 0.97272727 | X32: =AVERAGEIF($O$2:$O$601,O32,$M$2:$M$601) -> 0.97938144 | Y32: =AVERAGEIF($I$2:$I$601,I32,$M$2:$M$601) -> 0.58333333 | Z32: =AVERAGEIF($N$2:$N$601,N32,$M$2:$M$601) -> 0.22302158 | AA32: =ROUND(AVERAGE(V32:Z32),10) -> 0.73964453 | AB32: =IF(AA32>=Como_Avaliar!$B$15,"Alta",IF(AA32>=Como_Avaliar!$B$16,"Média","Baixa")) -> Alta
A33: CTD00032 | B33: MT | C33: Centro-Oeste | D33: Autônomo | E33: Agronegócio | F33: 26 | G33: 23 | H33: 2 | I33: Questor | J33: Não | K33: Não | L33: Lead Quente | M33: 0 | N33: =IF(F33<8,"1. < 8 anos",IF(F33<16,"2. 8 a 15 anos","3. 16+ anos")) -> 3. 16+ anos | O33: =IF(G33<20,"1. < 20",IF(G33<50,"2. 20 a 49",IF(G33<150,"3. 50 a 149","4. 150+"))) -> 2. 20 a 49 | P33: =IF(H33<=2,"1. 1 a 2",IF(H33<=5,"2. 3 a 5",IF(H33<=15,"3. 6 a 15","4. 16+"))) -> 1. 1 a 2 | Q33: =IF(OR(I33="Nenhum",I33="Planilha",I33="ContaAzul"),1,0) -> 0 | R33: =IF(AND(G33>=50,H33>=6,Q33=0),1,0) -> 0 | S33: =IF(AND(L33<>"Cliente Ativo",M33=0),1,0) -> 1 | T33: 2 | U33: Baixa | V33: =AVERAGEIF($D$2:$D$601,D33,$M$2:$M$601) -> 0.068273092 | W33: =AVERAGEIF($P$2:$P$601,P33,$M$2:$M$601) -> 0.086792453 | X33: =AVERAGEIF($O$2:$O$601,O33,$M$2:$M$601) -> 0.25294118 | Y33: =AVERAGEIF($I$2:$I$601,I33,$M$2:$M$601) -> 0.39751553 | Z33: =AVERAGEIF($N$2:$N$601,N33,$M$2:$M$601) -> 0.56634304 | AA33: =ROUND(AVERAGE(V33:Z33),10) -> 0.27437306 | AB33: =IF(AA33>=Como_Avaliar!$B$15,"Alta",IF(AA33>=Como_Avaliar!$B$16,"Média","Baixa")) -> Média
A34: CTD00033 | B34: PR | C34: Sul | D34: Autônomo | E34: Saúde | F34: 22 | G34: 22 | H34: 1 | I34: Planilha | J34: Não | K34: Sim | L34: Lead Quente | M34: 0 | N34: =IF(F34<8,"1. < 8 anos",IF(F34<16,"2. 8 a 15 anos","3. 16+ anos")) -> 3. 16+ anos | O34: =IF(G34<20,"1. < 20",IF(G34<50,"2. 20 a 49",IF(G34<150,"3. 50 a 149","4. 150+"))) -> 2. 20 a 49 | P34: =IF(H34<=2,"1. 1 a 2",IF(H34<=5,"2. 3 a 5",IF(H34<=15,"3. 6 a 15","4. 16+"))) -> 1. 1 a 2 | Q34: =IF(OR(I34="Nenhum",I34="Planilha",I34="ContaAzul"),1,0) -> 1 | R34: =IF(AND(G34>=50,H34>=6,Q34=0),1,0) -> 0 | S34: =IF(AND(L34<>"Cliente Ativo",M34=0),1,0) -> 1 | T34: 2 | U34: Baixa | V34: =AVERAGEIF($D$2:$D$601,D34,$M$2:$M$601) -> 0.068273092 | W34: =AVERAGEIF($P$2:$P$601,P34,$M$2:$M$601) -> 0.086792453 | X34: =AVERAGEIF($O$2:$O$601,O34,$M$2:$M$601) -> 0.25294118 | Y34: =AVERAGEIF($I$2:$I$601,I34,$M$2:$M$601) -> 0.15625 | Z34: =AVERAGEIF($N$2:$N$601,N34,$M$2:$M$601) -> 0.56634304 | AA34: =ROUND(AVERAGE(V34:Z34),10) -> 0.22611995 | AB34: =IF(AA34>=Como_Avaliar!$B$15,"Alta",IF(AA34>=Como_Avaliar!$B$16,"Média","Baixa")) -> Baixa
A35: CTD00034 | B35: AM | C35: Norte | D35: Autônomo | E35: Serviços | F35: 29 | G35: 15 | H35: 1 | I35: Domínio | J35: Não | K35: Sim | L35: Prospect | M35: 0 | N35: =IF(F35<8,"1. < 8 anos",IF(F35<16,"2. 8 a 15 anos","3. 16+ anos")) -> 3. 16+ anos | O35: =IF(G35<20,"1. < 20",IF(G35<50,"2. 20 a 49",IF(G35<150,"3. 50 a 149","4. 150+"))) -> 1. < 20 | P35: =IF(H35<=2,"1. 1 a 2",IF(H35<=5,"2. 3 a 5",IF(H35<=15,"3. 6 a 15","4. 16+"))) -> 1. 1 a 2 | Q35: =IF(OR(I35="Nenhum",I35="Planilha",I35="ContaAzul"),1,0) -> 0 | R35: =IF(AND(G35>=50,H35>=6,Q35=0),1,0) -> 0 | S35: =IF(AND(L35<>"Cliente Ativo",M35=0),1,0) -> 1 | T35: 2 | U35: Baixa | V35: =AVERAGEIF($D$2:$D$601,D35,$M$2:$M$601) -> 0.068273092 | W35: =AVERAGEIF($P$2:$P$601,P35,$M$2:$M$601) -> 0.086792453 | X35: =AVERAGEIF($O$2:$O$601,O35,$M$2:$M$601) -> 0.10309278 | Y35: =AVERAGEIF($I$2:$I$601,I35,$M$2:$M$601) -> 0.37662338 | Z35: =AVERAGEIF($N$2:$N$601,N35,$M$2:$M$601) -> 0.56634304 | AA35: =ROUND(AVERAGE(V35:Z35),10) -> 0.24022495 | AB35: =IF(AA35>=Como_Avaliar!$B$15,"Alta",IF(AA35>=Como_Avaliar!$B$16,"Média","Baixa")) -> Média
A36: CTD00035 | B36: MG | C36: Sudeste | D36: Pequeno Escritório | E36: Construção Civil | F36: 12 | G36: 33 | H36: 3 | I36: Questor | J36: Não | K36: Não | L36: Lead Frio | M36: 0 | N36: =IF(F36<8,"1. < 8 anos",IF(F36<16,"2. 8 a 15 anos","3. 16+ anos")) -> 2. 8 a 15 anos | O36: =IF(G36<20,"1. < 20",IF(G36<50,"2. 20 a 49",IF(G36<150,"3. 50 a 149","4. 150+"))) -> 2. 20 a 49 | P36: =IF(H36<=2,"1. 1 a 2",IF(H36<=5,"2. 3 a 5",IF(H36<=15,"3. 6 a 15","4. 16+"))) -> 2. 3 a 5 | Q36: =IF(OR(I36="Nenhum",I36="Planilha",I36="ContaAzul"),1,0) -> 0 | R36: =IF(AND(G36>=50,H36>=6,Q36=0),1,0) -> 0 | S36: =IF(AND(L36<>"Cliente Ativo",M36=0),1,0) -> 1 | T36: 3 | U36: Média | V36: =AVERAGEIF($D$2:$D$601,D36,$M$2:$M$601) -> 0.43835616 | W36: =AVERAGEIF($P$2:$P$601,P36,$M$2:$M$601) -> 0.38095238 | X36: =AVERAGEIF($O$2:$O$601,O36,$M$2:$M$601) -> 0.25294118 | Y36: =AVERAGEIF($I$2:$I$601,I36,$M$2:$M$601) -> 0.39751553 | Z36: =AVERAGEIF($N$2:$N$601,N36,$M$2:$M$601) -> 0.22302158 | AA36: =ROUND(AVERAGE(V36:Z36),10) -> 0.33855737 | AB36: =IF(AA36>=Como_Avaliar!$B$15,"Alta",IF(AA36>=Como_Avaliar!$B$16,"Média","Baixa")) -> Média
A37: CTD00036 | B37: SC | C37: Sul | D37: Autônomo | E37: Saúde | F37: 25 | G37: 24 | H37: 2 | I37: Domínio | J37: Não | K37: Não | L37: Lead Frio | M37: 0 | N37: =IF(F37<8,"1. < 8 anos",IF(F37<16,"2. 8 a 15 anos","3. 16+ anos")) -> 3. 16+ anos | O37: =IF(G37<20,"1. < 20",IF(G37<50,"2. 20 a 49",IF(G37<150,"3. 50 a 149","4. 150+"))) -> 2. 20 a 49 | P37: =IF(H37<=2,"1. 1 a 2",IF(H37<=5,"2. 3 a 5",IF(H37<=15,"3. 6 a 15","4. 16+"))) -> 1. 1 a 2 | Q37: =IF(OR(I37="Nenhum",I37="Planilha",I37="ContaAzul"),1,0) -> 0 | R37: =IF(AND(G37>=50,H37>=6,Q37=0),1,0) -> 0 | S37: =IF(AND(L37<>"Cliente Ativo",M37=0),1,0) -> 1 | T37: 2 | U37: Baixa | V37: =AVERAGEIF($D$2:$D$601,D37,$M$2:$M$601) -> 0.068273092 | W37: =AVERAGEIF($P$2:$P$601,P37,$M$2:$M$601) -> 0.086792453 | X37: =AVERAGEIF($O$2:$O$601,O37,$M$2:$M$601) -> 0.25294118 | Y37: =AVERAGEIF($I$2:$I$601,I37,$M$2:$M$601) -> 0.37662338 | Z37: =AVERAGEIF($N$2:$N$601,N37,$M$2:$M$601) -> 0.56634304 | AA37: =ROUND(AVERAGE(V37:Z37),10) -> 0.27019463 | AB37: =IF(AA37>=Como_Avaliar!$B$15,"Alta",IF(AA37>=Como_Avaliar!$B$16,"Média","Baixa")) -> Média
A38: CTD00037 | B38: BA | C38: Nordeste | D38: Pequeno Escritório | E38: Varejo/Comércio | F38: 17 | G38: 46 | H38: 10 | I38: Totvs | J38: Não | K38: Sim | L38: Cliente Ativo | M38: 1 | N38: =IF(F38<8,"1. < 8 anos",IF(F38<16,"2. 8 a 15 anos","3. 16+ anos")) -> 3. 16+ anos | O38: =IF(G38<20,"1. < 20",IF(G38<50,"2. 20 a 49",IF(G38<150,"3. 50 a 149","4. 150+"))) -> 2. 20 a 49 | P38: =IF(H38<=2,"1. 1 a 2",IF(H38<=5,"2. 3 a 5",IF(H38<=15,"3. 6 a 15","4. 16+"))) -> 3. 6 a 15 | Q38: =IF(OR(I38="Nenhum",I38="Planilha",I38="ContaAzul"),1,0) -> 0 | R38: =IF(AND(G38>=50,H38>=6,Q38=0),1,0) -> 0 | S38: =IF(AND(L38<>"Cliente Ativo",M38=0),1,0) -> 0 | V38: =AVERAGEIF($D$2:$D$601,D38,$M$2:$M$601) -> 0.43835616 | W38: =AVERAGEIF($P$2:$P$601,P38,$M$2:$M$601) -> 0.55319149 | X38: =AVERAGEIF($O$2:$O$601,O38,$M$2:$M$601) -> 0.25294118 | Y38: =AVERAGEIF($I$2:$I$601,I38,$M$2:$M$601) -> 0.58333333 | Z38: =AVERAGEIF($N$2:$N$601,N38,$M$2:$M$601) -> 0.56634304 | AA38: =ROUND(AVERAGE(V38:Z38),10) -> 0.47883304 | AB38: =IF(AA38>=Como_Avaliar!$B$15,"Alta",IF(AA38>=Como_Avaliar!$B$16,"Média","Baixa")) -> Alta
A39: CTD00038 | B39: RS | C39: Sul | D39: Grande Escritório | E39: Construção Civil | F39: 27 | G39: 232 | H39: 36 | I39: Alterdata | J39: Sim | K39: Sim | L39: Prospect | M39: 1 | N39: =IF(F39<8,"1. < 8 anos",IF(F39<16,"2. 8 a 15 anos","3. 16+ anos")) -> 3. 16+ anos | O39: =IF(G39<20,"1. < 20",IF(G39<50,"2. 20 a 49",IF(G39<150,"3. 50 a 149","4. 150+"))) -> 4. 150+ | P39: =IF(H39<=2,"1. 1 a 2",IF(H39<=5,"2. 3 a 5",IF(H39<=15,"3. 6 a 15","4. 16+"))) -> 4. 16+ | Q39: =IF(OR(I39="Nenhum",I39="Planilha",I39="ContaAzul"),1,0) -> 0 | R39: =IF(AND(G39>=50,H39>=6,Q39=0),1,0) -> 1 | S39: =IF(AND(L39<>"Cliente Ativo",M39=0),1,0) -> 0 | V39: =AVERAGEIF($D$2:$D$601,D39,$M$2:$M$601) -> 1 | W39: =AVERAGEIF($P$2:$P$601,P39,$M$2:$M$601) -> 0.97272727 | X39: =AVERAGEIF($O$2:$O$601,O39,$M$2:$M$601) -> 0.97938144 | Y39: =AVERAGEIF($I$2:$I$601,I39,$M$2:$M$601) -> 0.65217391 | Z39: =AVERAGEIF($N$2:$N$601,N39,$M$2:$M$601) -> 0.56634304 | AA39: =ROUND(AVERAGE(V39:Z39),10) -> 0.83412513 | AB39: =IF(AA39>=Como_Avaliar!$B$15,"Alta",IF(AA39>=Como_Avaliar!$B$16,"Média","Baixa")) -> Alta
A40: CTD00039 | B40: BA | C40: Nordeste | D40: Autônomo | E40: Serviços | F40: 27 | G40: 21 | H40: 2 | I40: Questor | J40: Não | K40: Sim | L40: Lead Frio | M40: 0 | N40: =IF(F40<8,"1. < 8 anos",IF(F40<16,"2. 8 a 15 anos","3. 16+ anos")) -> 3. 16+ anos | O40: =IF(G40<20,"1. < 20",IF(G40<50,"2. 20 a 49",IF(G40<150,"3. 50 a 149","4. 150+"))) -> 2. 20 a 49 | P40: =IF(H40<=2,"1. 1 a 2",IF(H40<=5,"2. 3 a 5",IF(H40<=15,"3. 6 a 15","4. 16+"))) -> 1. 1 a 2 | Q40: =IF(OR(I40="Nenhum",I40="Planilha",I40="ContaAzul"),1,0) -> 0 | R40: =IF(AND(G40>=50,H40>=6,Q40=0),1,0) -> 0 | S40: =IF(AND(L40<>"Cliente Ativo",M40=0),1,0) -> 1 | T40: 2 | U40: Baixa | V40: =AVERAGEIF($D$2:$D$601,D40,$M$2:$M$601) -> 0.068273092 | W40: =AVERAGEIF($P$2:$P$601,P40,$M$2:$M$601) -> 0.086792453 | X40: =AVERAGEIF($O$2:$O$601,O40,$M$2:$M$601) -> 0.25294118 | Y40: =AVERAGEIF($I$2:$I$601,I40,$M$2:$M$601) -> 0.39751553 | Z40: =AVERAGEIF($N$2:$N$601,N40,$M$2:$M$601) -> 0.56634304 | AA40: =ROUND(AVERAGE(V40:Z40),10) -> 0.27437306 | AB40: =IF(AA40>=Como_Avaliar!$B$15,"Alta",IF(AA40>=Como_Avaliar!$B$16,"Média","Baixa")) -> Média
A41: CTD00040 | B41: SC | C41: Sul | D41: Pequeno Escritório | E41: Serviços | F41: 10 | G41: 29 | H41: 8 | I41: Totvs | J41: Sim | K41: Não | L41: Lead Frio | M41: 0 | N41: =IF(F41<8,"1. < 8 anos",IF(F41<16,"2. 8 a 15 anos","3. 16+ anos")) -> 2. 8 a 15 anos | O41: =IF(G41<20,"1. < 20",IF(G41<50,"2. 20 a 49",IF(G41<150,"3. 50 a 149","4. 150+"))) -> 2. 20 a 49 | P41: =IF(H41<=2,"1. 1 a 2",IF(H41<=5,"2. 3 a 5",IF(H41<=15,"3. 6 a 15","4. 16+"))) -> 3. 6 a 15 | Q41: =IF(OR(I41="Nenhum",I41="Planilha",I41="ContaAzul"),1,0) -> 0 | R41: =IF(AND(G41>=50,H41>=6,Q41=0),1,0) -> 0 | S41: =IF(AND(L41<>"Cliente Ativo",M41=0),1,0) -> 1 | T41: 3 | U41: Média | V41: =AVERAGEIF($D$2:$D$601,D41,$M$2:$M$601) -> 0.43835616 | W41: =AVERAGEIF($P$2:$P$601,P41,$M$2:$M$601) -> 0.55319149 | X41: =AVERAGEIF($O$2:$O$601,O41,$M$2:$M$601) -> 0.25294118 | Y41: =AVERAGEIF($I$2:$I$601,I41,$M$2:$M$601) -> 0.58333333 | Z41: =AVERAGEIF($N$2:$N$601,N41,$M$2:$M$601) -> 0.22302158 | AA41: =ROUND(AVERAGE(V41:Z41),10) -> 0.41016875 | AB41: =IF(AA41>=Como_Avaliar!$B$15,"Alta",IF(AA41>=Como_Avaliar!$B$16,"Média","Baixa")) -> Média
A42: CTD00041 | B42: GO | C42: Centro-Oeste | D42: Autônomo | E42: Serviços | F42: 28 | G42: 9 | H42: 1 | I42: Questor | J42: Sim | K42: Não | L42: Prospect | M42: 0 | N42: =IF(F42<8,"1. < 8 anos",IF(F42<16,"2. 8 a 15 anos","3. 16+ anos")) -> 3. 16+ anos | O42: =IF(G42<20,"1. < 20",IF(G42<50,"2. 20 a 49",IF(G42<150,"3. 50 a 149","4. 150+"))) -> 1. < 20 | P42: =IF(H42<=2,"1. 1 a 2",IF(H42<=5,"2. 3 a 5",IF(H42<=15,"3. 6 a 15","4. 16+"))) -> 1. 1 a 2 | Q42: =IF(OR(I42="Nenhum",I42="Planilha",I42="ContaAzul"),1,0) -> 0 | R42: =IF(AND(G42>=50,H42>=6,Q42=0),1,0) -> 0 | S42: =IF(AND(L42<>"Cliente Ativo",M42=0),1,0) -> 1 | T42: 1 | U42: Baixa | V42: =AVERAGEIF($D$2:$D$601,D42,$M$2:$M$601) -> 0.068273092 | W42: =AVERAGEIF($P$2:$P$601,P42,$M$2:$M$601) -> 0.086792453 | X42: =AVERAGEIF($O$2:$O$601,O42,$M$2:$M$601) -> 0.10309278 | Y42: =AVERAGEIF($I$2:$I$601,I42,$M$2:$M$601) -> 0.39751553 | Z42: =AVERAGEIF($N$2:$N$601,N42,$M$2:$M$601) -> 0.56634304 | AA42: =ROUND(AVERAGE(V42:Z42),10) -> 0.24440338 | AB42: =IF(AA42>=Como_Avaliar!$B$15,"Alta",IF(AA42>=Como_Avaliar!$B$16,"Média","Baixa")) -> Média
A43: CTD00042 | B43: SP | C43: Sudeste | D43: Pequeno Escritório | E43: Tecnologia | F43: 28 | G43: 17 | H43: 6 | I43: Domínio | J43: Não | K43: Sim | L43: Lead Frio | M43: 1 | N43: =IF(F43<8,"1. < 8 anos",IF(F43<16,"2. 8 a 15 anos","3. 16+ anos")) -> 3. 16+ anos | O43: =IF(G43<20,"1. < 20",IF(G43<50,"2. 20 a 49",IF(G43<150,"3. 50 a 149","4. 150+"))) -> 1. < 20 | P43: =IF(H43<=2,"1. 1 a 2",IF(H43<=5,"2. 3 a 5",IF(H43<=15,"3. 6 a 15","4. 16+"))) -> 3. 6 a 15 | Q43: =IF(OR(I43="Nenhum",I43="Planilha",I43="ContaAzul"),1,0) -> 0 | R43: =IF(AND(G43>=50,H43>=6,Q43=0),1,0) -> 0 | S43: =IF(AND(L43<>"Cliente Ativo",M43=0),1,0) -> 0 | V43: =AVERAGEIF($D$2:$D$601,D43,$M$2:$M$601) -> 0.43835616 | W43: =AVERAGEIF($P$2:$P$601,P43,$M$2:$M$601) -> 0.55319149 | X43: =AVERAGEIF($O$2:$O$601,O43,$M$2:$M$601) -> 0.10309278 | Y43: =AVERAGEIF($I$2:$I$601,I43,$M$2:$M$601) -> 0.37662338 | Z43: =AVERAGEIF($N$2:$N$601,N43,$M$2:$M$601) -> 0.56634304 | AA43: =ROUND(AVERAGE(V43:Z43),10) -> 0.40752137 | AB43: =IF(AA43>=Como_Avaliar!$B$15,"Alta",IF(AA43>=Como_Avaliar!$B$16,"Média","Baixa")) -> Média
A44: CTD00043 | B44: RJ | C44: Sudeste | D44: Autônomo | E44: Agronegócio | F44: 16 | G44: 17 | H44: 2 | I44: Questor | J44: Não | K44: Não | L44: Cliente Ativo | M44: 0 | N44: =IF(F44<8,"1. < 8 anos",IF(F44<16,"2. 8 a 15 anos","3. 16+ anos")) -> 3. 16+ anos | O44: =IF(G44<20,"1. < 20",IF(G44<50,"2. 20 a 49",IF(G44<150,"3. 50 a 149","4. 150+"))) -> 1. < 20 | P44: =IF(H44<=2,"1. 1 a 2",IF(H44<=5,"2. 3 a 5",IF(H44<=15,"3. 6 a 15","4. 16+"))) -> 1. 1 a 2 | Q44: =IF(OR(I44="Nenhum",I44="Planilha",I44="ContaAzul"),1,0) -> 0 | R44: =IF(AND(G44>=50,H44>=6,Q44=0),1,0) -> 0 | S44: =IF(AND(L44<>"Cliente Ativo",M44=0),1,0) -> 0 | V44: =AVERAGEIF($D$2:$D$601,D44,$M$2:$M$601) -> 0.068273092 | W44: =AVERAGEIF($P$2:$P$601,P44,$M$2:$M$601) -> 0.086792453 | X44: =AVERAGEIF($O$2:$O$601,O44,$M$2:$M$601) -> 0.10309278 | Y44: =AVERAGEIF($I$2:$I$601,I44,$M$2:$M$601) -> 0.39751553 | Z44: =AVERAGEIF($N$2:$N$601,N44,$M$2:$M$601) -> 0.56634304 | AA44: =ROUND(AVERAGE(V44:Z44),10) -> 0.24440338 | AB44: =IF(AA44>=Como_Avaliar!$B$15,"Alta",IF(AA44>=Como_Avaliar!$B$16,"Média","Baixa")) -> Média
A45: CTD00044 | B45: RJ | C45: Sudeste | D45: Autônomo | E45: Construção Civil | F45: 15 | G45: 13 | H45: 2 | I45: Domínio | J45: Sim | K45: Sim | L45: Prospect | M45: 0 | N45: =IF(F45<8,"1. < 8 anos",IF(F45<16,"2. 8 a 15 anos","3. 16+ anos")) -> 2. 8 a 15 anos | O45: =IF(G45<20,"1. < 20",IF(G45<50,"2. 20 a 49",IF(G45<150,"3. 50 a 149","4. 150+"))) -> 1. < 20 | P45: =IF(H45<=2,"1. 1 a 2",IF(H45<=5,"2. 3 a 5",IF(H45<=15,"3. 6 a 15","4. 16+"))) -> 1. 1 a 2 | Q45: =IF(OR(I45="Nenhum",I45="Planilha",I45="ContaAzul"),1,0) -> 0 | R45: =IF(AND(G45>=50,H45>=6,Q45=0),1,0) -> 0 | S45: =IF(AND(L45<>"Cliente Ativo",M45=0),1,0) -> 1 | T45: 1 | U45: Baixa | V45: =AVERAGEIF($D$2:$D$601,D45,$M$2:$M$601) -> 0.068273092 | W45: =AVERAGEIF($P$2:$P$601,P45,$M$2:$M$601) -> 0.086792453 | X45: =AVERAGEIF($O$2:$O$601,O45,$M$2:$M$601) -> 0.10309278 | Y45: =AVERAGEIF($I$2:$I$601,I45,$M$2:$M$601) -> 0.37662338 | Z45: =AVERAGEIF($N$2:$N$601,N45,$M$2:$M$601) -> 0.22302158 | AA45: =ROUND(AVERAGE(V45:Z45),10) -> 0.17156066 | AB45: =IF(AA45>=Como_Avaliar!$B$15,"Alta",IF(AA45>=Como_Avaliar!$B$16,"Média","Baixa")) -> Baixa
A46: CTD00045 | B46: SP | C46: Sudeste | D46: Autônomo | E46: Indústria | F46: 15 | G46: 16 | H46: 1 | I46: Questor | J46: Não | K46: Não | L46: Lead Frio | M46: 0 | N46: =IF(F46<8,"1. < 8 anos",IF(F46<16,"2. 8 a 15 anos","3. 16+ anos")) -> 2. 8 a 15 anos | O46: =IF(G46<20,"1. < 20",IF(G46<50,"2. 20 a 49",IF(G46<150,"3. 50 a 149","4. 150+"))) -> 1. < 20 | P46: =IF(H46<=2,"1. 1 a 2",IF(H46<=5,"2. 3 a 5",IF(H46<=15,"3. 6 a 15","4. 16+"))) -> 1. 1 a 2 | Q46: =IF(OR(I46="Nenhum",I46="Planilha",I46="ContaAzul"),1,0) -> 0 | R46: =IF(AND(G46>=50,H46>=6,Q46=0),1,0) -> 0 | S46: =IF(AND(L46<>"Cliente Ativo",M46=0),1,0) -> 1 | T46: 2 | U46: Baixa | V46: =AVERAGEIF($D$2:$D$601,D46,$M$2:$M$601) -> 0.068273092 | W46: =AVERAGEIF($P$2:$P$601,P46,$M$2:$M$601) -> 0.086792453 | X46: =AVERAGEIF($O$2:$O$601,O46,$M$2:$M$601) -> 0.10309278 | Y46: =AVERAGEIF($I$2:$I$601,I46,$M$2:$M$601) -> 0.39751553 | Z46: =AVERAGEIF($N$2:$N$601,N46,$M$2:$M$601) -> 0.22302158 | AA46: =ROUND(AVERAGE(V46:Z46),10) -> 0.17573909 | AB46: =IF(AA46>=Como_Avaliar!$B$15,"Alta",IF(AA46>=Como_Avaliar!$B$16,"Média","Baixa")) -> Baixa
A47: CTD00046 | B47: RJ | C47: Sudeste | D47: Grande Escritório | E47: Saúde | F47: 19 | G47: 355 | H47: 96 | I47: Alterdata | J47: Não | K47: Não | L47: Prospect | M47: 1 | N47: =IF(F47<8,"1. < 8 anos",IF(F47<16,"2. 8 a 15 anos","3. 16+ anos")) -> 3. 16+ anos | O47: =IF(G47<20,"1. < 20",IF(G47<50,"2. 20 a 49",IF(G47<150,"3. 50 a 149","4. 150+"))) -> 4. 150+ | P47: =IF(H47<=2,"1. 1 a 2",IF(H47<=5,"2. 3 a 5",IF(H47<=15,"3. 6 a 15","4. 16+"))) -> 4. 16+ | Q47: =IF(OR(I47="Nenhum",I47="Planilha",I47="ContaAzul"),1,0) -> 0 | R47: =IF(AND(G47>=50,H47>=6,Q47=0),1,0) -> 1 | S47: =IF(AND(L47<>"Cliente Ativo",M47=0),1,0) -> 0 | V47: =AVERAGEIF($D$2:$D$601,D47,$M$2:$M$601) -> 1 | W47: =AVERAGEIF($P$2:$P$601,P47,$M$2:$M$601) -> 0.97272727 | X47: =AVERAGEIF($O$2:$O$601,O47,$M$2:$M$601) -> 0.97938144 | Y47: =AVERAGEIF($I$2:$I$601,I47,$M$2:$M$601) -> 0.65217391 | Z47: =AVERAGEIF($N$2:$N$601,N47,$M$2:$M$601) -> 0.56634304 | AA47: =ROUND(AVERAGE(V47:Z47),10) -> 0.83412513 | AB47: =IF(AA47>=Como_Avaliar!$B$15,"Alta",IF(AA47>=Como_Avaliar!$B$16,"Média","Baixa")) -> Alta
A48: CTD00047 | B48: SP | C48: Sudeste | D48: Pequeno Escritório | E48: Saúde | F48: 12 | G48: 67 | H48: 5 | I48: Questor | J48: Sim | K48: Sim | L48: Churned | M48: 1 | N48: =IF(F48<8,"1. < 8 anos",IF(F48<16,"2. 8 a 15 anos","3. 16+ anos")) -> 2. 8 a 15 anos | O48: =IF(G48<20,"1. < 20",IF(G48<50,"2. 20 a 49",IF(G48<150,"3. 50 a 149","4. 150+"))) -> 3. 50 a 149 | P48: =IF(H48<=2,"1. 1 a 2",IF(H48<=5,"2. 3 a 5",IF(H48<=15,"3. 6 a 15","4. 16+"))) -> 2. 3 a 5 | Q48: =IF(OR(I48="Nenhum",I48="Planilha",I48="ContaAzul"),1,0) -> 0 | R48: =IF(AND(G48>=50,H48>=6,Q48=0),1,0) -> 0 | S48: =IF(AND(L48<>"Cliente Ativo",M48=0),1,0) -> 0 | V48: =AVERAGEIF($D$2:$D$601,D48,$M$2:$M$601) -> 0.43835616 | W48: =AVERAGEIF($P$2:$P$601,P48,$M$2:$M$601) -> 0.38095238 | X48: =AVERAGEIF($O$2:$O$601,O48,$M$2:$M$601) -> 0.58992806 | Y48: =AVERAGEIF($I$2:$I$601,I48,$M$2:$M$601) -> 0.39751553 | Z48: =AVERAGEIF($N$2:$N$601,N48,$M$2:$M$601) -> 0.22302158 | AA48: =ROUND(AVERAGE(V48:Z48),10) -> 0.40595474 | AB48: =IF(AA48>=Como_Avaliar!$B$15,"Alta",IF(AA48>=Como_Avaliar!$B$16,"Média","Baixa")) -> Média
A49: CTD00048 | B49: RJ | C49: Sudeste | D49: Médio Escritório | E49: Varejo/Comércio | F49: 23 | G49: 236 | H49: 26 | I49: Totvs | J49: Sim | K49: Não | L49: Sem Contato | M49: 1 | N49: =IF(F49<8,"1. < 8 anos",IF(F49<16,"2. 8 a 15 anos","3. 16+ anos")) -> 3. 16+ anos | O49: =IF(G49<20,"1. < 20",IF(G49<50,"2. 20 a 49",IF(G49<150,"3. 50 a 149","4. 150+"))) -> 4. 150+ | P49: =IF(H49<=2,"1. 1 a 2",IF(H49<=5,"2. 3 a 5",IF(H49<=15,"3. 6 a 15","4. 16+"))) -> 4. 16+ | Q49: =IF(OR(I49="Nenhum",I49="Planilha",I49="ContaAzul"),1,0) -> 0 | R49: =IF(AND(G49>=50,H49>=6,Q49=0),1,0) -> 1 | S49: =IF(AND(L49<>"Cliente Ativo",M49=0),1,0) -> 0 | V49: =AVERAGEIF($D$2:$D$601,D49,$M$2:$M$601) -> 0.93975904 | W49: =AVERAGEIF($P$2:$P$601,P49,$M$2:$M$601) -> 0.97272727 | X49: =AVERAGEIF($O$2:$O$601,O49,$M$2:$M$601) -> 0.97938144 | Y49: =AVERAGEIF($I$2:$I$601,I49,$M$2:$M$601) -> 0.58333333 | Z49: =AVERAGEIF($N$2:$N$601,N49,$M$2:$M$601) -> 0.56634304 | AA49: =ROUND(AVERAGE(V49:Z49),10) -> 0.80830883 | AB49: =IF(AA49>=Como_Avaliar!$B$15,"Alta",IF(AA49>=Como_Avaliar!$B$16,"Média","Baixa")) -> Alta
A50: CTD00049 | B50: RS | C50: Sul | D50: Autônomo | E50: Tecnologia | F50: 20 | G50: 9 | H50: 1 | I50: Domínio | J50: Sim | K50: Não | L50: Churned | M50: 0 | N50: =IF(F50<8,"1. < 8 anos",IF(F50<16,"2. 8 a 15 anos","3. 16+ anos")) -> 3. 16+ anos | O50: =IF(G50<20,"1. < 20",IF(G50<50,"2. 20 a 49",IF(G50<150,"3. 50 a 149","4. 150+"))) -> 1. < 20 | P50: =IF(H50<=2,"1. 1 a 2",IF(H50<=5,"2. 3 a 5",IF(H50<=15,"3. 6 a 15","4. 16+"))) -> 1. 1 a 2 | Q50: =IF(OR(I50="Nenhum",I50="Planilha",I50="ContaAzul"),1,0) -> 0 | R50: =IF(AND(G50>=50,H50>=6,Q50=0),1,0) -> 0 | S50: =IF(AND(L50<>"Cliente Ativo",M50=0),1,0) -> 1 | T50: 1 | U50: Baixa | V50: =AVERAGEIF($D$2:$D$601,D50,$M$2:$M$601) -> 0.068273092 | W50: =AVERAGEIF($P$2:$P$601,P50,$M$2:$M$601) -> 0.086792453 | X50: =AVERAGEIF($O$2:$O$601,O50,$M$2:$M$601) -> 0.10309278 | Y50: =AVERAGEIF($I$2:$I$601,I50,$M$2:$M$601) -> 0.37662338 | Z50: =AVERAGEIF($N$2:$N$601,N50,$M$2:$M$601) -> 0.56634304 | AA50: =ROUND(AVERAGE(V50:Z50),10) -> 0.24022495 | AB50: =IF(AA50>=Como_Avaliar!$B$15,"Alta",IF(AA50>=Como_Avaliar!$B$16,"Média","Baixa")) -> Média
A51: CTD00050 | B51: MG | C51: Sudeste | D51: Médio Escritório | E51: Varejo/Comércio | F51: 25 | G51: 165 | H51: 29 | I51: Totvs | J51: Sim | K51: Sim | L51: Churned | M51: 1 | N51: =IF(F51<8,"1. < 8 anos",IF(F51<16,"2. 8 a 15 anos","3. 16+ anos")) -> 3. 16+ anos | O51: =IF(G51<20,"1. < 20",IF(G51<50,"2. 20 a 49",IF(G51<150,"3. 50 a 149","4. 150+"))) -> 4. 150+ | P51: =IF(H51<=2,"1. 1 a 2",IF(H51<=5,"2. 3 a 5",IF(H51<=15,"3. 6 a 15","4. 16+"))) -> 4. 16+ | Q51: =IF(OR(I51="Nenhum",I51="Planilha",I51="ContaAzul"),1,0) -> 0 | R51: =IF(AND(G51>=50,H51>=6,Q51=0),1,0) -> 1 | S51: =IF(AND(L51<>"Cliente Ativo",M51=0),1,0) -> 0 | V51: =AVERAGEIF($D$2:$D$601,D51,$M$2:$M$601) -> 0.93975904 | W51: =AVERAGEIF($P$2:$P$601,P51,$M$2:$M$601) -> 0.97272727 | X51: =AVERAGEIF($O$2:$O$601,O51,$M$2:$M$601) -> 0.97938144 | Y51: =AVERAGEIF($I$2:$I$601,I51,$M$2:$M$601) -> 0.58333333 | Z51: =AVERAGEIF($N$2:$N$601,N51,$M$2:$M$601) -> 0.56634304 | AA51: =ROUND(AVERAGE(V51:Z51),10) -> 0.80830883 | AB51: =IF(AA51>=Como_Avaliar!$B$15,"Alta",IF(AA51>=Como_Avaliar!$B$16,"Média","Baixa")) -> Alta
A52: CTD00051 | B52: MG | C52: Sudeste | D52: Autônomo | E52: Saúde | F52: 3 | G52: 19 | H52: 2 | I52: Domínio | J52: Sim | K52: Sim | L52: Lead Frio | M52: 0 | N52: =IF(F52<8,"1. < 8 anos",IF(F52<16,"2. 8 a 15 anos","3. 16+ anos")) -> 1. < 8 anos | O52: =IF(G52<20,"1. < 20",IF(G52<50,"2. 20 a 49",IF(G52<150,"3. 50 a 149","4. 150+"))) -> 1. < 20 | P52: =IF(H52<=2,"1. 1 a 2",IF(H52<=5,"2. 3 a 5",IF(H52<=15,"3. 6 a 15","4. 16+"))) -> 1. 1 a 2 | Q52: =IF(OR(I52="Nenhum",I52="Planilha",I52="ContaAzul"),1,0) -> 0 | R52: =IF(AND(G52>=50,H52>=6,Q52=0),1,0) -> 0 | S52: =IF(AND(L52<>"Cliente Ativo",M52=0),1,0) -> 1 | T52: 2 | U52: Baixa | V52: =AVERAGEIF($D$2:$D$601,D52,$M$2:$M$601) -> 0.068273092 | W52: =AVERAGEIF($P$2:$P$601,P52,$M$2:$M$601) -> 0.086792453 | X52: =AVERAGEIF($O$2:$O$601,O52,$M$2:$M$601) -> 0.10309278 | Y52: =AVERAGEIF($I$2:$I$601,I52,$M$2:$M$601) -> 0.37662338 | Z52: =AVERAGEIF($N$2:$N$601,N52,$M$2:$M$601) -> 0.22368421 | AA52: =ROUND(AVERAGE(V52:Z52),10) -> 0.17169318 | AB52: =IF(AA52>=Como_Avaliar!$B$15,"Alta",IF(AA52>=Como_Avaliar!$B$16,"Média","Baixa")) -> Baixa
A53: CTD00052 | B53: SP | C53: Sudeste | D53: Autônomo | E53: Tecnologia | F53: 5 | G53: 22 | H53: 1 | I53: Questor | J53: Não | K53: Sim | L53: Prospect | M53: 0 | N53: =IF(F53<8,"1. < 8 anos",IF(F53<16,"2. 8 a 15 anos","3. 16+ anos")) -> 1. < 8 anos | O53: =IF(G53<20,"1. < 20",IF(G53<50,"2. 20 a 49",IF(G53<150,"3. 50 a 149","4. 150+"))) -> 2. 20 a 49 | P53: =IF(H53<=2,"1. 1 a 2",IF(H53<=5,"2. 3 a 5",IF(H53<=15,"3. 6 a 15","4. 16+"))) -> 1. 1 a 2 | Q53: =IF(OR(I53="Nenhum",I53="Planilha",I53="ContaAzul"),1,0) -> 0 | R53: =IF(AND(G53>=50,H53>=6,Q53=0),1,0) -> 0 | S53: =IF(AND(L53<>"Cliente Ativo",M53=0),1,0) -> 1 | T53: 2 | U53: Baixa | V53: =AVERAGEIF($D$2:$D$601,D53,$M$2:$M$601) -> 0.068273092 | W53: =AVERAGEIF($P$2:$P$601,P53,$M$2:$M$601) -> 0.086792453 | X53: =AVERAGEIF($O$2:$O$601,O53,$M$2:$M$601) -> 0.25294118 | Y53: =AVERAGEIF($I$2:$I$601,I53,$M$2:$M$601) -> 0.39751553 | Z53: =AVERAGEIF($N$2:$N$601,N53,$M$2:$M$601) -> 0.22368421 | AA53: =ROUND(AVERAGE(V53:Z53),10) -> 0.20584129 | AB53: =IF(AA53>=Como_Avaliar!$B$15,"Alta",IF(AA53>=Como_Avaliar!$B$16,"Média","Baixa")) -> Baixa
A54: CTD00053 | B54: RJ | C54: Sudeste | D54: Pequeno Escritório | E54: Serviços | F54: 19 | G54: 75 | H54: 4 | I54: Totvs | J54: Sim | K54: Não | L54: Sem Contato | M54: 0 | N54: =IF(F54<8,"1. < 8 anos",IF(F54<16,"2. 8 a 15 anos","3. 16+ anos")) -> 3. 16+ anos | O54: =IF(G54<20,"1. < 20",IF(G54<50,"2. 20 a 49",IF(G54<150,"3. 50 a 149","4. 150+"))) -> 3. 50 a 149 | P54: =IF(H54<=2,"1. 1 a 2",IF(H54<=5,"2. 3 a 5",IF(H54<=15,"3. 6 a 15","4. 16+"))) -> 2. 3 a 5 | Q54: =IF(OR(I54="Nenhum",I54="Planilha",I54="ContaAzul"),1,0) -> 0 | R54: =IF(AND(G54>=50,H54>=6,Q54=0),1,0) -> 0 | S54: =IF(AND(L54<>"Cliente Ativo",M54=0),1,0) -> 1 | T54: 3 | U54: Média | V54: =AVERAGEIF($D$2:$D$601,D54,$M$2:$M$601) -> 0.43835616 | W54: =AVERAGEIF($P$2:$P$601,P54,$M$2:$M$601) -> 0.38095238 | X54: =AVERAGEIF($O$2:$O$601,O54,$M$2:$M$601) -> 0.58992806 | Y54: =AVERAGEIF($I$2:$I$601,I54,$M$2:$M$601) -> 0.58333333 | Z54: =AVERAGEIF($N$2:$N$601,N54,$M$2:$M$601) -> 0.56634304 | AA54: =ROUND(AVERAGE(V54:Z54),10) -> 0.5117826 | AB54: =IF(AA54>=Como_Avaliar!$B$15,"Alta",IF(AA54>=Como_Avaliar!$B$16,"Média","Baixa")) -> Alta
A55: CTD00054 | B55: CE | C55: Nordeste | D55: Pequeno Escritório | E55: Construção Civil | F55: 7 | G55: 22 | H55: 6 | I55: Domínio | J55: Não | K55: Não | L55: Cliente Ativo | M55: 0 | N55: =IF(F55<8,"1. < 8 anos",IF(F55<16,"2. 8 a 15 anos","3. 16+ anos")) -> 1. < 8 anos | O55: =IF(G55<20,"1. < 20",IF(G55<50,"2. 20 a 49",IF(G55<150,"3. 50 a 149","4. 150+"))) -> 2. 20 a 49 | P55: =IF(H55<=2,"1. 1 a 2",IF(H55<=5,"2. 3 a 5",IF(H55<=15,"3. 6 a 15","4. 16+"))) -> 3. 6 a 15 | Q55: =IF(OR(I55="Nenhum",I55="Planilha",I55="ContaAzul"),1,0) -> 0 | R55: =IF(AND(G55>=50,H55>=6,Q55=0),1,0) -> 0 | S55: =IF(AND(L55<>"Cliente Ativo",M55=0),1,0) -> 0 | V55: =AVERAGEIF($D$2:$D$601,D55,$M$2:$M$601) -> 0.43835616 | W55: =AVERAGEIF($P$2:$P$601,P55,$M$2:$M$601) -> 0.55319149 | X55: =AVERAGEIF($O$2:$O$601,O55,$M$2:$M$601) -> 0.25294118 | Y55: =AVERAGEIF($I$2:$I$601,I55,$M$2:$M$601) -> 0.37662338 | Z55: =AVERAGEIF($N$2:$N$601,N55,$M$2:$M$601) -> 0.22368421 | AA55: =ROUND(AVERAGE(V55:Z55),10) -> 0.36895928 | AB55: =IF(AA55>=Como_Avaliar!$B$15,"Alta",IF(AA55>=Como_Avaliar!$B$16,"Média","Baixa")) -> Média
A56: CTD00055 | B56: RS | C56: Sul | D56: Pequeno Escritório | E56: Tecnologia | F56: 21 | G56: 32 | H56: 6 | I56: Alterdata | J56: Sim | K56: Não | L56: Lead Frio | M56: 1 | N56: =IF(F56<8,"1. < 8 anos",IF(F56<16,"2. 8 a 15 anos","3. 16+ anos")) -> 3. 16+ anos | O56: =IF(G56<20,"1. < 20",IF(G56<50,"2. 20 a 49",IF(G56<150,"3. 50 a 149","4. 150+"))) -> 2. 20 a 49 | P56: =IF(H56<=2,"1. 1 a 2",IF(H56<=5,"2. 3 a 5",IF(H56<=15,"3. 6 a 15","4. 16+"))) -> 3. 6 a 15 | Q56: =IF(OR(I56="Nenhum",I56="Planilha",I56="ContaAzul"),1,0) -> 0 | R56: =IF(AND(G56>=50,H56>=6,Q56=0),1,0) -> 0 | S56: =IF(AND(L56<>"Cliente Ativo",M56=0),1,0) -> 0 | V56: =AVERAGEIF($D$2:$D$601,D56,$M$2:$M$601) -> 0.43835616 | W56: =AVERAGEIF($P$2:$P$601,P56,$M$2:$M$601) -> 0.55319149 | X56: =AVERAGEIF($O$2:$O$601,O56,$M$2:$M$601) -> 0.25294118 | Y56: =AVERAGEIF($I$2:$I$601,I56,$M$2:$M$601) -> 0.65217391 | Z56: =AVERAGEIF($N$2:$N$601,N56,$M$2:$M$601) -> 0.56634304 | AA56: =ROUND(AVERAGE(V56:Z56),10) -> 0.49260116 | AB56: =IF(AA56>=Como_Avaliar!$B$15,"Alta",IF(AA56>=Como_Avaliar!$B$16,"Média","Baixa")) -> Alta
A57: CTD00056 | B57: RS | C57: Sul | D57: Pequeno Escritório | E57: Agronegócio | F57: 9 | G57: 41 | H57: 6 | I57: Domínio | J57: Sim | K57: Sim | L57: Lead Frio | M57: 1 | N57: =IF(F57<8,"1. < 8 anos",IF(F57<16,"2. 8 a 15 anos","3. 16+ anos")) -> 2. 8 a 15 anos | O57: =IF(G57<20,"1. < 20",IF(G57<50,"2. 20 a 49",IF(G57<150,"3. 50 a 149","4. 150+"))) -> 2. 20 a 49 | P57: =IF(H57<=2,"1. 1 a 2",IF(H57<=5,"2. 3 a 5",IF(H57<=15,"3. 6 a 15","4. 16+"))) -> 3. 6 a 15 | Q57: =IF(OR(I57="Nenhum",I57="Planilha",I57="ContaAzul"),1,0) -> 0 | R57: =IF(AND(G57>=50,H57>=6,Q57=0),1,0) -> 0 | S57: =IF(AND(L57<>"Cliente Ativo",M57=0),1,0) -> 0 | V57: =AVERAGEIF($D$2:$D$601,D57,$M$2:$M$601) -> 0.43835616 | W57: =AVERAGEIF($P$2:$P$601,P57,$M$2:$M$601) -> 0.55319149 | X57: =AVERAGEIF($O$2:$O$601,O57,$M$2:$M$601) -> 0.25294118 | Y57: =AVERAGEIF($I$2:$I$601,I57,$M$2:$M$601) -> 0.37662338 | Z57: =AVERAGEIF($N$2:$N$601,N57,$M$2:$M$601) -> 0.22302158 | AA57: =ROUND(AVERAGE(V57:Z57),10) -> 0.36882676 | AB57: =IF(AA57>=Como_Avaliar!$B$15,"Alta",IF(AA57>=Como_Avaliar!$B$16,"Média","Baixa")) -> Média
A58: CTD00057 | B58: SP | C58: Sudeste | D58: Autônomo | E58: Indústria | F58: 7 | G58: 20 | H58: 2 | I58: Domínio | J58: Sim | K58: Sim | L58: Lead Frio | M58: 0 | N58: =IF(F58<8,"1. < 8 anos",IF(F58<16,"2. 8 a 15 anos","3. 16+ anos")) -> 1. < 8 anos | O58: =IF(G58<20,"1. < 20",IF(G58<50,"2. 20 a 49",IF(G58<150,"3. 50 a 149","4. 150+"))) -> 2. 20 a 49 | P58: =IF(H58<=2,"1. 1 a 2",IF(H58<=5,"2. 3 a 5",IF(H58<=15,"3. 6 a 15","4. 16+"))) -> 1. 1 a 2 | Q58: =IF(OR(I58="Nenhum",I58="Planilha",I58="ContaAzul"),1,0) -> 0 | R58: =IF(AND(G58>=50,H58>=6,Q58=0),1,0) -> 0 | S58: =IF(AND(L58<>"Cliente Ativo",M58=0),1,0) -> 1 | T58: 2 | U58: Baixa | V58: =AVERAGEIF($D$2:$D$601,D58,$M$2:$M$601) -> 0.068273092 | W58: =AVERAGEIF($P$2:$P$601,P58,$M$2:$M$601) -> 0.086792453 | X58: =AVERAGEIF($O$2:$O$601,O58,$M$2:$M$601) -> 0.25294118 | Y58: =AVERAGEIF($I$2:$I$601,I58,$M$2:$M$601) -> 0.37662338 | Z58: =AVERAGEIF($N$2:$N$601,N58,$M$2:$M$601) -> 0.22368421 | AA58: =ROUND(AVERAGE(V58:Z58),10) -> 0.20166286 | AB58: =IF(AA58>=Como_Avaliar!$B$15,"Alta",IF(AA58>=Como_Avaliar!$B$16,"Média","Baixa")) -> Baixa
A59: CTD00058 | B59: MT | C59: Centro-Oeste | D59: Pequeno Escritório | E59: Indústria | F59: 18 | G59: 56 | H59: 4 | I59: Totvs | J59: Sim | K59: Sim | L59: Cliente Ativo | M59: 1 | N59: =IF(F59<8,"1. < 8 anos",IF(F59<16,"2. 8 a 15 anos","3. 16+ anos")) -> 3. 16+ anos | O59: =IF(G59<20,"1. < 20",IF(G59<50,"2. 20 a 49",IF(G59<150,"3. 50 a 149","4. 150+"))) -> 3. 50 a 149 | P59: =IF(H59<=2,"1. 1 a 2",IF(H59<=5,"2. 3 a 5",IF(H59<=15,"3. 6 a 15","4. 16+"))) -> 2. 3 a 5 | Q59: =IF(OR(I59="Nenhum",I59="Planilha",I59="ContaAzul"),1,0) -> 0 | R59: =IF(AND(G59>=50,H59>=6,Q59=0),1,0) -> 0 | S59: =IF(AND(L59<>"Cliente Ativo",M59=0),1,0) -> 0 | V59: =AVERAGEIF($D$2:$D$601,D59,$M$2:$M$601) -> 0.43835616 | W59: =AVERAGEIF($P$2:$P$601,P59,$M$2:$M$601) -> 0.38095238 | X59: =AVERAGEIF($O$2:$O$601,O59,$M$2:$M$601) -> 0.58992806 | Y59: =AVERAGEIF($I$2:$I$601,I59,$M$2:$M$601) -> 0.58333333 | Z59: =AVERAGEIF($N$2:$N$601,N59,$M$2:$M$601) -> 0.56634304 | AA59: =ROUND(AVERAGE(V59:Z59),10) -> 0.5117826 | AB59: =IF(AA59>=Como_Avaliar!$B$15,"Alta",IF(AA59>=Como_Avaliar!$B$16,"Média","Baixa")) -> Alta
A60: CTD00059 | B60: SP | C60: Sudeste | D60: Autônomo | E60: Tecnologia | F60: 4 | G60: 24 | H60: 1 | I60: Domínio | J60: Sim | K60: Não | L60: Lead Quente | M60: 0 | N60: =IF(F60<8,"1. < 8 anos",IF(F60<16,"2. 8 a 15 anos","3. 16+ anos")) -> 1. < 8 anos | O60: =IF(G60<20,"1. < 20",IF(G60<50,"2. 20 a 49",IF(G60<150,"3. 50 a 149","4. 150+"))) -> 2. 20 a 49 | P60: =IF(H60<=2,"1. 1 a 2",IF(H60<=5,"2. 3 a 5",IF(H60<=15,"3. 6 a 15","4. 16+"))) -> 1. 1 a 2 | Q60: =IF(OR(I60="Nenhum",I60="Planilha",I60="ContaAzul"),1,0) -> 0 | R60: =IF(AND(G60>=50,H60>=6,Q60=0),1,0) -> 0 | S60: =IF(AND(L60<>"Cliente Ativo",M60=0),1,0) -> 1 | T60: 2 | U60: Baixa | V60: =AVERAGEIF($D$2:$D$601,D60,$M$2:$M$601) -> 0.068273092 | W60: =AVERAGEIF($P$2:$P$601,P60,$M$2:$M$601) -> 0.086792453 | X60: =AVERAGEIF($O$2:$O$601,O60,$M$2:$M$601) -> 0.25294118 | Y60: =AVERAGEIF($I$2:$I$601,I60,$M$2:$M$601) -> 0.37662338 | Z60: =AVERAGEIF($N$2:$N$601,N60,$M$2:$M$601) -> 0.22368421 | AA60: =ROUND(AVERAGE(V60:Z60),10) -> 0.20166286 | AB60: =IF(AA60>=Como_Avaliar!$B$15,"Alta",IF(AA60>=Como_Avaliar!$B$16,"Média","Baixa")) -> Baixa
A61: CTD00060 | B61: MG | C61: Sudeste | D61: Autônomo | E61: Saúde | F61: 25 | G61: 18 | H61: 1 | I61: Questor | J61: Não | K61: Não | L61: Prospect | M61: 0 | N61: =IF(F61<8,"1. < 8 anos",IF(F61<16,"2. 8 a 15 anos","3. 16+ anos")) -> 3. 16+ anos | O61: =IF(G61<20,"1. < 20",IF(G61<50,"2. 20 a 49",IF(G61<150,"3. 50 a 149","4. 150+"))) -> 1. < 20 | P61: =IF(H61<=2,"1. 1 a 2",IF(H61<=5,"2. 3 a 5",IF(H61<=15,"3. 6 a 15","4. 16+"))) -> 1. 1 a 2 | Q61: =IF(OR(I61="Nenhum",I61="Planilha",I61="ContaAzul"),1,0) -> 0 | R61: =IF(AND(G61>=50,H61>=6,Q61=0),1,0) -> 0 | S61: =IF(AND(L61<>"Cliente Ativo",M61=0),1,0) -> 1 | T61: 2 | U61: Baixa | V61: =AVERAGEIF($D$2:$D$601,D61,$M$2:$M$601) -> 0.068273092 | W61: =AVERAGEIF($P$2:$P$601,P61,$M$2:$M$601) -> 0.086792453 | X61: =AVERAGEIF($O$2:$O$601,O61,$M$2:$M$601) -> 0.10309278 | Y61: =AVERAGEIF($I$2:$I$601,I61,$M$2:$M$601) -> 0.39751553 | Z61: =AVERAGEIF($N$2:$N$601,N61,$M$2:$M$601) -> 0.56634304 | AA61: =ROUND(AVERAGE(V61:Z61),10) -> 0.24440338 | AB61: =IF(AA61>=Como_Avaliar!$B$15,"Alta",IF(AA61>=Como_Avaliar!$B$16,"Média","Baixa")) -> Média
A62: CTD00061 | B62: PA | C62: Norte | D62: Pequeno Escritório | E62: Varejo/Comércio | F62: 28 | G62: 63 | H62: 8 | I62: Questor | J62: Sim | K62: Sim | L62: Lead Frio | M62: 1 | N62: =IF(F62<8,"1. < 8 anos",IF(F62<16,"2. 8 a 15 anos","3. 16+ anos")) -> 3. 16+ anos | O62: =IF(G62<20,"1. < 20",IF(G62<50,"2. 20 a 49",IF(G62<150,"3. 50 a 149","4. 150+"))) -> 3. 50 a 149 | P62: =IF(H62<=2,"1. 1 a 2",IF(H62<=5,"2. 3 a 5",IF(H62<=15,"3. 6 a 15","4. 16+"))) -> 3. 6 a 15 | Q62: =IF(OR(I62="Nenhum",I62="Planilha",I62="ContaAzul"),1,0) -> 0 | R62: =IF(AND(G62>=50,H62>=6,Q62=0),1,0) -> 1 | S62: =IF(AND(L62<>"Cliente Ativo",M62=0),1,0) -> 0 | V62: =AVERAGEIF($D$2:$D$601,D62,$M$2:$M$601) -> 0.43835616 | W62: =AVERAGEIF($P$2:$P$601,P62,$M$2:$M$601) -> 0.55319149 | X62: =AVERAGEIF($O$2:$O$601,O62,$M$2:$M$601) -> 0.58992806 | Y62: =AVERAGEIF($I$2:$I$601,I62,$M$2:$M$601) -> 0.39751553 | Z62: =AVERAGEIF($N$2:$N$601,N62,$M$2:$M$601) -> 0.56634304 | AA62: =ROUND(AVERAGE(V62:Z62),10) -> 0.50906686 | AB62: =IF(AA62>=Como_Avaliar!$B$15,"Alta",IF(AA62>=Como_Avaliar!$B$16,"Média","Baixa")) -> Alta
A63: CTD00062 | B63: RS | C63: Sul | D63: Pequeno Escritório | E63: Serviços | F63: 14 | G63: 55 | H63: 6 | I63: Totvs | J63: Não | K63: Não | L63: Prospect | M63: 1 | N63: =IF(F63<8,"1. < 8 anos",IF(F63<16,"2. 8 a 15 anos","3. 16+ anos")) -> 2. 8 a 15 anos | O63: =IF(G63<20,"1. < 20",IF(G63<50,"2. 20 a 49",IF(G63<150,"3. 50 a 149","4. 150+"))) -> 3. 50 a 149 | P63: =IF(H63<=2,"1. 1 a 2",IF(H63<=5,"2. 3 a 5",IF(H63<=15,"3. 6 a 15","4. 16+"))) -> 3. 6 a 15 | Q63: =IF(OR(I63="Nenhum",I63="Planilha",I63="ContaAzul"),1,0) -> 0 | R63: =IF(AND(G63>=50,H63>=6,Q63=0),1,0) -> 1 | S63: =IF(AND(L63<>"Cliente Ativo",M63=0),1,0) -> 0 | V63: =AVERAGEIF($D$2:$D$601,D63,$M$2:$M$601) -> 0.43835616 | W63: =AVERAGEIF($P$2:$P$601,P63,$M$2:$M$601) -> 0.55319149 | X63: =AVERAGEIF($O$2:$O$601,O63,$M$2:$M$601) -> 0.58992806 | Y63: =AVERAGEIF($I$2:$I$601,I63,$M$2:$M$601) -> 0.58333333 | Z63: =AVERAGEIF($N$2:$N$601,N63,$M$2:$M$601) -> 0.22302158 | AA63: =ROUND(AVERAGE(V63:Z63),10) -> 0.47756613 | AB63: =IF(AA63>=Como_Avaliar!$B$15,"Alta",IF(AA63>=Como_Avaliar!$B$16,"Média","Baixa")) -> Média
A64: CTD00063 | B64: SC | C64: Sul | D64: Pequeno Escritório | E64: Saúde | F64: 18 | G64: 37 | H64: 8 | I64: Totvs | J64: Não | K64: Não | L64: Cliente Ativo | M64: 1 | N64: =IF(F64<8,"1. < 8 anos",IF(F64<16,"2. 8 a 15 anos","3. 16+ anos")) -> 3. 16+ anos | O64: =IF(G64<20,"1. < 20",IF(G64<50,"2. 20 a 49",IF(G64<150,"3. 50 a 149","4. 150+"))) -> 2. 20 a 49 | P64: =IF(H64<=2,"1. 1 a 2",IF(H64<=5,"2. 3 a 5",IF(H64<=15,"3. 6 a 15","4. 16+"))) -> 3. 6 a 15 | Q64: =IF(OR(I64="Nenhum",I64="Planilha",I64="ContaAzul"),1,0) -> 0 | R64: =IF(AND(G64>=50,H64>=6,Q64=0),1,0) -> 0 | S64: =IF(AND(L64<>"Cliente Ativo",M64=0),1,0) -> 0 | V64: =AVERAGEIF($D$2:$D$601,D64,$M$2:$M$601) -> 0.43835616 | W64: =AVERAGEIF($P$2:$P$601,P64,$M$2:$M$601) -> 0.55319149 | X64: =AVERAGEIF($O$2:$O$601,O64,$M$2:$M$601) -> 0.25294118 | Y64: =AVERAGEIF($I$2:$I$601,I64,$M$2:$M$601) -> 0.58333333 | Z64: =AVERAGEIF($N$2:$N$601,N64,$M$2:$M$601) -> 0.56634304 | AA64: =ROUND(AVERAGE(V64:Z64),10) -> 0.47883304 | AB64: =IF(AA64>=Como_Avaliar!$B$15,"Alta",IF(AA64>=Como_Avaliar!$B$16,"Média","Baixa")) -> Alta
A65: CTD00064 | B65: GO | C65: Centro-Oeste | D65: Autônomo | E65: Serviços | F65: 26 | G65: 17 | H65: 2 | I65: Planilha | J65: Não | K65: Sim | L65: Lead Quente | M65: 0 | N65: =IF(F65<8,"1. < 8 anos",IF(F65<16,"2. 8 a 15 anos","3. 16+ anos")) -> 3. 16+ anos | O65: =IF(G65<20,"1. < 20",IF(G65<50,"2. 20 a 49",IF(G65<150,"3. 50 a 149","4. 150+"))) -> 1. < 20 | P65: =IF(H65<=2,"1. 1 a 2",IF(H65<=5,"2. 3 a 5",IF(H65<=15,"3. 6 a 15","4. 16+"))) -> 1. 1 a 2 | Q65: =IF(OR(I65="Nenhum",I65="Planilha",I65="ContaAzul"),1,0) -> 1 | R65: =IF(AND(G65>=50,H65>=6,Q65=0),1,0) -> 0 | S65: =IF(AND(L65<>"Cliente Ativo",M65=0),1,0) -> 1 | T65: 2 | U65: Baixa | V65: =AVERAGEIF($D$2:$D$601,D65,$M$2:$M$601) -> 0.068273092 | W65: =AVERAGEIF($P$2:$P$601,P65,$M$2:$M$601) -> 0.086792453 | X65: =AVERAGEIF($O$2:$O$601,O65,$M$2:$M$601) -> 0.10309278 | Y65: =AVERAGEIF($I$2:$I$601,I65,$M$2:$M$601) -> 0.15625 | Z65: =AVERAGEIF($N$2:$N$601,N65,$M$2:$M$601) -> 0.56634304 | AA65: =ROUND(AVERAGE(V65:Z65),10) -> 0.19615027 | AB65: =IF(AA65>=Como_Avaliar!$B$15,"Alta",IF(AA65>=Como_Avaliar!$B$16,"Média","Baixa")) -> Baixa
A66: CTD00065 | B66: BA | C66: Nordeste | D66: Autônomo | E66: Indústria | F66: 9 | G66: 20 | H66: 2 | I66: Nenhum | J66: Sim | K66: Não | L66: Lead Frio | M66: 0 | N66: =IF(F66<8,"1. < 8 anos",IF(F66<16,"2. 8 a 15 anos","3. 16+ anos")) -> 2. 8 a 15 anos | O66: =IF(G66<20,"1. < 20",IF(G66<50,"2. 20 a 49",IF(G66<150,"3. 50 a 149","4. 150+"))) -> 2. 20 a 49 | P66: =IF(H66<=2,"1. 1 a 2",IF(H66<=5,"2. 3 a 5",IF(H66<=15,"3. 6 a 15","4. 16+"))) -> 1. 1 a 2 | Q66: =IF(OR(I66="Nenhum",I66="Planilha",I66="ContaAzul"),1,0) -> 1 | R66: =IF(AND(G66>=50,H66>=6,Q66=0),1,0) -> 0 | S66: =IF(AND(L66<>"Cliente Ativo",M66=0),1,0) -> 1 | T66: 2 | U66: Baixa | V66: =AVERAGEIF($D$2:$D$601,D66,$M$2:$M$601) -> 0.068273092 | W66: =AVERAGEIF($P$2:$P$601,P66,$M$2:$M$601) -> 0.086792453 | X66: =AVERAGEIF($O$2:$O$601,O66,$M$2:$M$601) -> 0.25294118 | Y66: =AVERAGEIF($I$2:$I$601,I66,$M$2:$M$601) -> 0.065217391 | Z66: =AVERAGEIF($N$2:$N$601,N66,$M$2:$M$601) -> 0.22302158 | AA66: =ROUND(AVERAGE(V66:Z66),10) -> 0.13924914 | AB66: =IF(AA66>=Como_Avaliar!$B$15,"Alta",IF(AA66>=Como_Avaliar!$B$16,"Média","Baixa")) -> Baixa
A67: CTD00066 | B67: DF | C67: Centro-Oeste | D67: Grande Escritório | E67: Construção Civil | F67: 26 | G67: 550 | H67: 34 | I67: SAP | J67: Sim | K67: Não | L67: Prospect | M67: 1 | N67: =IF(F67<8,"1. < 8 anos",IF(F67<16,"2. 8 a 15 anos","3. 16+ anos")) -> 3. 16+ anos | O67: =IF(G67<20,"1. < 20",IF(G67<50,"2. 20 a 49",IF(G67<150,"3. 50 a 149","4. 150+"))) -> 4. 150+ | P67: =IF(H67<=2,"1. 1 a 2",IF(H67<=5,"2. 3 a 5",IF(H67<=15,"3. 6 a 15","4. 16+"))) -> 4. 16+ | Q67: =IF(OR(I67="Nenhum",I67="Planilha",I67="ContaAzul"),1,0) -> 0 | R67: =IF(AND(G67>=50,H67>=6,Q67=0),1,0) -> 1 | S67: =IF(AND(L67<>"Cliente Ativo",M67=0),1,0) -> 0 | V67: =AVERAGEIF($D$2:$D$601,D67,$M$2:$M$601) -> 1 | W67: =AVERAGEIF($P$2:$P$601,P67,$M$2:$M$601) -> 0.97272727 | X67: =AVERAGEIF($O$2:$O$601,O67,$M$2:$M$601) -> 0.97938144 | Y67: =AVERAGEIF($I$2:$I$601,I67,$M$2:$M$601) -> 1 | Z67: =AVERAGEIF($N$2:$N$601,N67,$M$2:$M$601) -> 0.56634304 | AA67: =ROUND(AVERAGE(V67:Z67),10) -> 0.90369035 | AB67: =IF(AA67>=Como_Avaliar!$B$15,"Alta",IF(AA67>=Como_Avaliar!$B$16,"Média","Baixa")) -> Alta
A68: CTD00067 | B68: RJ | C68: Sudeste | D68: Autônomo | E68: Indústria | F68: 21 | G68: 20 | H68: 2 | I68: Questor | J68: Não | K68: Não | L68: Lead Frio | M68: 0 | N68: =IF(F68<8,"1. < 8 anos",IF(F68<16,"2. 8 a 15 anos","3. 16+ anos")) -> 3. 16+ anos | O68: =IF(G68<20,"1. < 20",IF(G68<50,"2. 20 a 49",IF(G68<150,"3. 50 a 149","4. 150+"))) -> 2. 20 a 49 | P68: =IF(H68<=2,"1. 1 a 2",IF(H68<=5,"2. 3 a 5",IF(H68<=15,"3. 6 a 15","4. 16+"))) -> 1. 1 a 2 | Q68: =IF(OR(I68="Nenhum",I68="Planilha",I68="ContaAzul"),1,0) -> 0 | R68: =IF(AND(G68>=50,H68>=6,Q68=0),1,0) -> 0 | S68: =IF(AND(L68<>"Cliente Ativo",M68=0),1,0) -> 1 | T68: 2 | U68: Baixa | V68: =AVERAGEIF($D$2:$D$601,D68,$M$2:$M$601) -> 0.068273092 | W68: =AVERAGEIF($P$2:$P$601,P68,$M$2:$M$601) -> 0.086792453 | X68: =AVERAGEIF($O$2:$O$601,O68,$M$2:$M$601) -> 0.25294118 | Y68: =AVERAGEIF($I$2:$I$601,I68,$M$2:$M$601) -> 0.39751553 | Z68: =AVERAGEIF($N$2:$N$601,N68,$M$2:$M$601) -> 0.56634304 | AA68: =ROUND(AVERAGE(V68:Z68),10) -> 0.27437306 | AB68: =IF(AA68>=Como_Avaliar!$B$15,"Alta",IF(AA68>=Como_Avaliar!$B$16,"Média","Baixa")) -> Média
A69: CTD00068 | B69: SP | C69: Sudeste | D69: Autônomo | E69: Construção Civil | F69: 2 | G69: 14 | H69: 2 | I69: Domínio | J69: Sim | K69: Sim | L69: Prospect | M69: 0 | N69: =IF(F69<8,"1. < 8 anos",IF(F69<16,"2. 8 a 15 anos","3. 16+ anos")) -> 1. < 8 anos | O69: =IF(G69<20,"1. < 20",IF(G69<50,"2. 20 a 49",IF(G69<150,"3. 50 a 149","4. 150+"))) -> 1. < 20 | P69: =IF(H69<=2,"1. 1 a 2",IF(H69<=5,"2. 3 a 5",IF(H69<=15,"3. 6 a 15","4. 16+"))) -> 1. 1 a 2 | Q69: =IF(OR(I69="Nenhum",I69="Planilha",I69="ContaAzul"),1,0) -> 0 | R69: =IF(AND(G69>=50,H69>=6,Q69=0),1,0) -> 0 | S69: =IF(AND(L69<>"Cliente Ativo",M69=0),1,0) -> 1 | T69: 2 | U69: Baixa | V69: =AVERAGEIF($D$2:$D$601,D69,$M$2:$M$601) -> 0.068273092 | W69: =AVERAGEIF($P$2:$P$601,P69,$M$2:$M$601) -> 0.086792453 | X69: =AVERAGEIF($O$2:$O$601,O69,$M$2:$M$601) -> 0.10309278 | Y69: =AVERAGEIF($I$2:$I$601,I69,$M$2:$M$601) -> 0.37662338 | Z69: =AVERAGEIF($N$2:$N$601,N69,$M$2:$M$601) -> 0.22368421 | AA69: =ROUND(AVERAGE(V69:Z69),10) -> 0.17169318 | AB69: =IF(AA69>=Como_Avaliar!$B$15,"Alta",IF(AA69>=Como_Avaliar!$B$16,"Média","Baixa")) -> Baixa
A70: CTD00069 | B70: RJ | C70: Sudeste | D70: Grande Escritório | E70: Saúde | F70: 20 | G70: 470 | H70: 56 | I70: Alterdata | J70: Não | K70: Sim | L70: Sem Contato | M70: 1 | N70: =IF(F70<8,"1. < 8 anos",IF(F70<16,"2. 8 a 15 anos","3. 16+ anos")) -> 3. 16+ anos | O70: =IF(G70<20,"1. < 20",IF(G70<50,"2. 20 a 49",IF(G70<150,"3. 50 a 149","4. 150+"))) -> 4. 150+ | P70: =IF(H70<=2,"1. 1 a 2",IF(H70<=5,"2. 3 a 5",IF(H70<=15,"3. 6 a 15","4. 16+"))) -> 4. 16+ | Q70: =IF(OR(I70="Nenhum",I70="Planilha",I70="ContaAzul"),1,0) -> 0 | R70: =IF(AND(G70>=50,H70>=6,Q70=0),1,0) -> 1 | S70: =IF(AND(L70<>"Cliente Ativo",M70=0),1,0) -> 0 | V70: =AVERAGEIF($D$2:$D$601,D70,$M$2:$M$601) -> 1 | W70: =AVERAGEIF($P$2:$P$601,P70,$M$2:$M$601) -> 0.97272727 | X70: =AVERAGEIF($O$2:$O$601,O70,$M$2:$M$601) -> 0.97938144 | Y70: =AVERAGEIF($I$2:$I$601,I70,$M$2:$M$601) -> 0.65217391 | Z70: =AVERAGEIF($N$2:$N$601,N70,$M$2:$M$601) -> 0.56634304 | AA70: =ROUND(AVERAGE(V70:Z70),10) -> 0.83412513 | AB70: =IF(AA70>=Como_Avaliar!$B$15,"Alta",IF(AA70>=Como_Avaliar!$B$16,"Média","Baixa")) -> Alta
A71: CTD00070 | B71: RJ | C71: Sudeste | D71: Médio Escritório | E71: Varejo/Comércio | F71: 28 | G71: 216 | H71: 28 | I71: Questor | J71: Não | K71: Não | L71: Prospect | M71: 1 | N71: =IF(F71<8,"1. < 8 anos",IF(F71<16,"2. 8 a 15 anos","3. 16+ anos")) -> 3. 16+ anos | O71: =IF(G71<20,"1. < 20",IF(G71<50,"2. 20 a 49",IF(G71<150,"3. 50 a 149","4. 150+"))) -> 4. 150+ | P71: =IF(H71<=2,"1. 1 a 2",IF(H71<=5,"2. 3 a 5",IF(H71<=15,"3. 6 a 15","4. 16+"))) -> 4. 16+ | Q71: =IF(OR(I71="Nenhum",I71="Planilha",I71="ContaAzul"),1,0) -> 0 | R71: =IF(AND(G71>=50,H71>=6,Q71=0),1,0) -> 1 | S71: =IF(AND(L71<>"Cliente Ativo",M71=0),1,0) -> 0 | V71: =AVERAGEIF($D$2:$D$601,D71,$M$2:$M$601) -> 0.93975904 | W71: =AVERAGEIF($P$2:$P$601,P71,$M$2:$M$601) -> 0.97272727 | X71: =AVERAGEIF($O$2:$O$601,O71,$M$2:$M$601) -> 0.97938144 | Y71: =AVERAGEIF($I$2:$I$601,I71,$M$2:$M$601) -> 0.39751553 | Z71: =AVERAGEIF($N$2:$N$601,N71,$M$2:$M$601) -> 0.56634304 | AA71: =ROUND(AVERAGE(V71:Z71),10) -> 0.77114526 | AB71: =IF(AA71>=Como_Avaliar!$B$15,"Alta",IF(AA71>=Como_Avaliar!$B$16,"Média","Baixa")) -> Alta
A72: CTD00071 | B72: SP | C72: Sudeste | D72: Médio Escritório | E72: Saúde | F72: 15 | G72: 183 | H72: 23 | I72: Alterdata | J72: Não | K72: Não | L72: Lead Quente | M72: 1 | N72: =IF(F72<8,"1. < 8 anos",IF(F72<16,"2. 8 a 15 anos","3. 16+ anos")) -> 2. 8 a 15 anos | O72: =IF(G72<20,"1. < 20",IF(G72<50,"2. 20 a 49",IF(G72<150,"3. 50 a 149","4. 150+"))) -> 4. 150+ | P72: =IF(H72<=2,"1. 1 a 2",IF(H72<=5,"2. 3 a 5",IF(H72<=15,"3. 6 a 15","4. 16+"))) -> 4. 16+ | Q72: =IF(OR(I72="Nenhum",I72="Planilha",I72="ContaAzul"),1,0) -> 0 | R72: =IF(AND(G72>=50,H72>=6,Q72=0),1,0) -> 1 | S72: =IF(AND(L72<>"Cliente Ativo",M72=0),1,0) -> 0 | V72: =AVERAGEIF($D$2:$D$601,D72,$M$2:$M$601) -> 0.93975904 | W72: =AVERAGEIF($P$2:$P$601,P72,$M$2:$M$601) -> 0.97272727 | X72: =AVERAGEIF($O$2:$O$601,O72,$M$2:$M$601) -> 0.97938144 | Y72: =AVERAGEIF($I$2:$I$601,I72,$M$2:$M$601) -> 0.65217391 | Z72: =AVERAGEIF($N$2:$N$601,N72,$M$2:$M$601) -> 0.22302158 | AA72: =ROUND(AVERAGE(V72:Z72),10) -> 0.75341265 | AB72: =IF(AA72>=Como_Avaliar!$B$15,"Alta",IF(AA72>=Como_Avaliar!$B$16,"Média","Baixa")) -> Alta
A73: CTD00072 | B73: MA | C73: Nordeste | D73: Autônomo | E73: Agronegócio | F73: 28 | G73: 9 | H73: 1 | I73: Planilha | J73: Não | K73: Sim | L73: Prospect | M73: 0 | N73: =IF(F73<8,"1. < 8 anos",IF(F73<16,"2. 8 a 15 anos","3. 16+ anos")) -> 3. 16+ anos | O73: =IF(G73<20,"1. < 20",IF(G73<50,"2. 20 a 49",IF(G73<150,"3. 50 a 149","4. 150+"))) -> 1. < 20 | P73: =IF(H73<=2,"1. 1 a 2",IF(H73<=5,"2. 3 a 5",IF(H73<=15,"3. 6 a 15","4. 16+"))) -> 1. 1 a 2 | Q73: =IF(OR(I73="Nenhum",I73="Planilha",I73="ContaAzul"),1,0) -> 1 | R73: =IF(AND(G73>=50,H73>=6,Q73=0),1,0) -> 0 | S73: =IF(AND(L73<>"Cliente Ativo",M73=0),1,0) -> 1 | T73: 1 | U73: Baixa | V73: =AVERAGEIF($D$2:$D$601,D73,$M$2:$M$601) -> 0.068273092 | W73: =AVERAGEIF($P$2:$P$601,P73,$M$2:$M$601) -> 0.086792453 | X73: =AVERAGEIF($O$2:$O$601,O73,$M$2:$M$601) -> 0.10309278 | Y73: =AVERAGEIF($I$2:$I$601,I73,$M$2:$M$601) -> 0.15625 | Z73: =AVERAGEIF($N$2:$N$601,N73,$M$2:$M$601) -> 0.56634304 | AA73: =ROUND(AVERAGE(V73:Z73),10) -> 0.19615027 | AB73: =IF(AA73>=Como_Avaliar!$B$15,"Alta",IF(AA73>=Como_Avaliar!$B$16,"Média","Baixa")) -> Baixa
A74: CTD00073 | B74: PE | C74: Nordeste | D74: Autônomo | E74: Serviços | F74: 7 | G74: 10 | H74: 2 | I74: Domínio | J74: Não | K74: Sim | L74: Lead Frio | M74: 0 | N74: =IF(F74<8,"1. < 8 anos",IF(F74<16,"2. 8 a 15 anos","3. 16+ anos")) -> 1. < 8 anos | O74: =IF(G74<20,"1. < 20",IF(G74<50,"2. 20 a 49",IF(G74<150,"3. 50 a 149","4. 150+"))) -> 1. < 20 | P74: =IF(H74<=2,"1. 1 a 2",IF(H74<=5,"2. 3 a 5",IF(H74<=15,"3. 6 a 15","4. 16+"))) -> 1. 1 a 2 | Q74: =IF(OR(I74="Nenhum",I74="Planilha",I74="ContaAzul"),1,0) -> 0 | R74: =IF(AND(G74>=50,H74>=6,Q74=0),1,0) -> 0 | S74: =IF(AND(L74<>"Cliente Ativo",M74=0),1,0) -> 1 | T74: 1 | U74: Baixa | V74: =AVERAGEIF($D$2:$D$601,D74,$M$2:$M$601) -> 0.068273092 | W74: =AVERAGEIF($P$2:$P$601,P74,$M$2:$M$601) -> 0.086792453 | X74: =AVERAGEIF($O$2:$O$601,O74,$M$2:$M$601) -> 0.10309278 | Y74: =AVERAGEIF($I$2:$I$601,I74,$M$2:$M$601) -> 0.37662338 | Z74: =AVERAGEIF($N$2:$N$601,N74,$M$2:$M$601) -> 0.22368421 | AA74: =ROUND(AVERAGE(V74:Z74),10) -> 0.17169318 | AB74: =IF(AA74>=Como_Avaliar!$B$15,"Alta",IF(AA74>=Como_Avaliar!$B$16,"Média","Baixa")) -> Baixa
A75: CTD00074 | B75: RJ | C75: Sudeste | D75: Pequeno Escritório | E75: Agronegócio | F75: 12 | G75: 50 | H75: 3 | I75: Totvs | J75: Não | K75: Não | L75: Lead Quente | M75: 0 | N75: =IF(F75<8,"1. < 8 anos",IF(F75<16,"2. 8 a 15 anos","3. 16+ anos")) -> 2. 8 a 15 anos | O75: =IF(G75<20,"1. < 20",IF(G75<50,"2. 20 a 49",IF(G75<150,"3. 50 a 149","4. 150+"))) -> 3. 50 a 149 | P75: =IF(H75<=2,"1. 1 a 2",IF(H75<=5,"2. 3 a 5",IF(H75<=15,"3. 6 a 15","4. 16+"))) -> 2. 3 a 5 | Q75: =IF(OR(I75="Nenhum",I75="Planilha",I75="ContaAzul"),1,0) -> 0 | R75: =IF(AND(G75>=50,H75>=6,Q75=0),1,0) -> 0 | S75: =IF(AND(L75<>"Cliente Ativo",M75=0),1,0) -> 1 | T75: 5 | U75: Alta | V75: =AVERAGEIF($D$2:$D$601,D75,$M$2:$M$601) -> 0.43835616 | W75: =AVERAGEIF($P$2:$P$601,P75,$M$2:$M$601) -> 0.38095238 | X75: =AVERAGEIF($O$2:$O$601,O75,$M$2:$M$601) -> 0.58992806 | Y75: =AVERAGEIF($I$2:$I$601,I75,$M$2:$M$601) -> 0.58333333 | Z75: =AVERAGEIF($N$2:$N$601,N75,$M$2:$M$601) -> 0.22302158 | AA75: =ROUND(AVERAGE(V75:Z75),10) -> 0.4431183 | AB75: =IF(AA75>=Como_Avaliar!$B$15,"Alta",IF(AA75>=Como_Avaliar!$B$16,"Média","Baixa")) -> Média
A76: CTD00075 | B76: RS | C76: Sul | D76: Pequeno Escritório | E76: Serviços | F76: 29 | G76: 53 | H76: 4 | I76: Questor | J76: Sim | K76: Sim | L76: Lead Quente | M76: 1 | N76: =IF(F76<8,"1. < 8 anos",IF(F76<16,"2. 8 a 15 anos","3. 16+ anos")) -> 3. 16+ anos | O76: =IF(G76<20,"1. < 20",IF(G76<50,"2. 20 a 49",IF(G76<150,"3. 50 a 149","4. 150+"))) -> 3. 50 a 149 | P76: =IF(H76<=2,"1. 1 a 2",IF(H76<=5,"2. 3 a 5",IF(H76<=15,"3. 6 a 15","4. 16+"))) -> 2. 3 a 5 | Q76: =IF(OR(I76="Nenhum",I76="Planilha",I76="ContaAzul"),1,0) -> 0 | R76: =IF(AND(G76>=50,H76>=6,Q76=0),1,0) -> 0 | S76: =IF(AND(L76<>"Cliente Ativo",M76=0),1,0) -> 0 | V76: =AVERAGEIF($D$2:$D$601,D76,$M$2:$M$601) -> 0.43835616 | W76: =AVERAGEIF($P$2:$P$601,P76,$M$2:$M$601) -> 0.38095238 | X76: =AVERAGEIF($O$2:$O$601,O76,$M$2:$M$601) -> 0.58992806 | Y76: =AVERAGEIF($I$2:$I$601,I76,$M$2:$M$601) -> 0.39751553 | Z76: =AVERAGEIF($N$2:$N$601,N76,$M$2:$M$601) -> 0.56634304 | AA76: =ROUND(AVERAGE(V76:Z76),10) -> 0.47461903 | AB76: =IF(AA76>=Como_Avaliar!$B$15,"Alta",IF(AA76>=Como_Avaliar!$B$16,"Média","Baixa")) -> Média
A77: CTD00076 | B77: MG | C77: Sudeste | D77: Autônomo | E77: Serviços | F77: 8 | G77: 10 | H77: 2 | I77: Planilha | J77: Não | K77: Não | L77: Sem Contato | M77: 0 | N77: =IF(F77<8,"1. < 8 anos",IF(F77<16,"2. 8 a 15 anos","3. 16+ anos")) -> 2. 8 a 15 anos | O77: =IF(G77<20,"1. < 20",IF(G77<50,"2. 20 a 49",IF(G77<150,"3. 50 a 149","4. 150+"))) -> 1. < 20 | P77: =IF(H77<=2,"1. 1 a 2",IF(H77<=5,"2. 3 a 5",IF(H77<=15,"3. 6 a 15","4. 16+"))) -> 1. 1 a 2 | Q77: =IF(OR(I77="Nenhum",I77="Planilha",I77="ContaAzul"),1,0) -> 1 | R77: =IF(AND(G77>=50,H77>=6,Q77=0),1,0) -> 0 | S77: =IF(AND(L77<>"Cliente Ativo",M77=0),1,0) -> 1 | T77: 1 | U77: Baixa | V77: =AVERAGEIF($D$2:$D$601,D77,$M$2:$M$601) -> 0.068273092 | W77: =AVERAGEIF($P$2:$P$601,P77,$M$2:$M$601) -> 0.086792453 | X77: =AVERAGEIF($O$2:$O$601,O77,$M$2:$M$601) -> 0.10309278 | Y77: =AVERAGEIF($I$2:$I$601,I77,$M$2:$M$601) -> 0.15625 | Z77: =AVERAGEIF($N$2:$N$601,N77,$M$2:$M$601) -> 0.22302158 | AA77: =ROUND(AVERAGE(V77:Z77),10) -> 0.12748598 | AB77: =IF(AA77>=Como_Avaliar!$B$15,"Alta",IF(AA77>=Como_Avaliar!$B$16,"Média","Baixa")) -> Baixa
A78: CTD00077 | B78: CE | C78: Nordeste | D78: Pequeno Escritório | E78: Serviços | F78: 15 | G78: 53 | H78: 2 | I78: Alterdata | J78: Não | K78: Sim | L78: Lead Frio | M78: 0 | N78: =IF(F78<8,"1. < 8 anos",IF(F78<16,"2. 8 a 15 anos","3. 16+ anos")) -> 2. 8 a 15 anos | O78: =IF(G78<20,"1. < 20",IF(G78<50,"2. 20 a 49",IF(G78<150,"3. 50 a 149","4. 150+"))) -> 3. 50 a 149 | P78: =IF(H78<=2,"1. 1 a 2",IF(H78<=5,"2. 3 a 5",IF(H78<=15,"3. 6 a 15","4. 16+"))) -> 1. 1 a 2 | Q78: =IF(OR(I78="Nenhum",I78="Planilha",I78="ContaAzul"),1,0) -> 0 | R78: =IF(AND(G78>=50,H78>=6,Q78=0),1,0) -> 0 | S78: =IF(AND(L78<>"Cliente Ativo",M78=0),1,0) -> 1 | T78: 3 | U78: Média | V78: =AVERAGEIF($D$2:$D$601,D78,$M$2:$M$601) -> 0.43835616 | W78: =AVERAGEIF($P$2:$P$601,P78,$M$2:$M$601) -> 0.086792453 | X78: =AVERAGEIF($O$2:$O$601,O78,$M$2:$M$601) -> 0.58992806 | Y78: =AVERAGEIF($I$2:$I$601,I78,$M$2:$M$601) -> 0.65217391 | Z78: =AVERAGEIF($N$2:$N$601,N78,$M$2:$M$601) -> 0.22302158 | AA78: =ROUND(AVERAGE(V78:Z78),10) -> 0.39805443 | AB78: =IF(AA78>=Como_Avaliar!$B$15,"Alta",IF(AA78>=Como_Avaliar!$B$16,"Média","Baixa")) -> Média
A79: CTD00078 | B79: ES | C79: Sudeste | D79: Autônomo | E79: Tecnologia | F79: 3 | G79: 12 | H79: 2 | I79: Nenhum | J79: Não | K79: Não | L79: Prospect | M79: 0 | N79: =IF(F79<8,"1. < 8 anos",IF(F79<16,"2. 8 a 15 anos","3. 16+ anos")) -> 1. < 8 anos | O79: =IF(G79<20,"1. < 20",IF(G79<50,"2. 20 a 49",IF(G79<150,"3. 50 a 149","4. 150+"))) -> 1. < 20 | P79: =IF(H79<=2,"1. 1 a 2",IF(H79<=5,"2. 3 a 5",IF(H79<=15,"3. 6 a 15","4. 16+"))) -> 1. 1 a 2 | Q79: =IF(OR(I79="Nenhum",I79="Planilha",I79="ContaAzul"),1,0) -> 1 | R79: =IF(AND(G79>=50,H79>=6,Q79=0),1,0) -> 0 | S79: =IF(AND(L79<>"Cliente Ativo",M79=0),1,0) -> 1 | T79: 1 | U79: Baixa | V79: =AVERAGEIF($D$2:$D$601,D79,$M$2:$M$601) -> 0.068273092 | W79: =AVERAGEIF($P$2:$P$601,P79,$M$2:$M$601) -> 0.086792453 | X79: =AVERAGEIF($O$2:$O$601,O79,$M$2:$M$601) -> 0.10309278 | Y79: =AVERAGEIF($I$2:$I$601,I79,$M$2:$M$601) -> 0.065217391 | Z79: =AVERAGEIF($N$2:$N$601,N79,$M$2:$M$601) -> 0.22368421 | AA79: =ROUND(AVERAGE(V79:Z79),10) -> 0.10941199 | AB79: =IF(AA79>=Como_Avaliar!$B$15,"Alta",IF(AA79>=Como_Avaliar!$B$16,"Média","Baixa")) -> Baixa
A80: CTD00079 | B80: RJ | C80: Sudeste | D80: Pequeno Escritório | E80: Construção Civil | F80: 14 | G80: 41 | H80: 7 | I80: Totvs | J80: Não | K80: Não | L80: Cliente Ativo | M80: 0 | N80: =IF(F80<8,"1. < 8 anos",IF(F80<16,"2. 8 a 15 anos","3. 16+ anos")) -> 2. 8 a 15 anos | O80: =IF(G80<20,"1. < 20",IF(G80<50,"2. 20 a 49",IF(G80<150,"3. 50 a 149","4. 150+"))) -> 2. 20 a 49 | P80: =IF(H80<=2,"1. 1 a 2",IF(H80<=5,"2. 3 a 5",IF(H80<=15,"3. 6 a 15","4. 16+"))) -> 3. 6 a 15 | Q80: =IF(OR(I80="Nenhum",I80="Planilha",I80="ContaAzul"),1,0) -> 0 | R80: =IF(AND(G80>=50,H80>=6,Q80=0),1,0) -> 0 | S80: =IF(AND(L80<>"Cliente Ativo",M80=0),1,0) -> 0 | V80: =AVERAGEIF($D$2:$D$601,D80,$M$2:$M$601) -> 0.43835616 | W80: =AVERAGEIF($P$2:$P$601,P80,$M$2:$M$601) -> 0.55319149 | X80: =AVERAGEIF($O$2:$O$601,O80,$M$2:$M$601) -> 0.25294118 | Y80: =AVERAGEIF($I$2:$I$601,I80,$M$2:$M$601) -> 0.58333333 | Z80: =AVERAGEIF($N$2:$N$601,N80,$M$2:$M$601) -> 0.22302158 | AA80: =ROUND(AVERAGE(V80:Z80),10) -> 0.41016875 | AB80: =IF(AA80>=Como_Avaliar!$B$15,"Alta",IF(AA80>=Como_Avaliar!$B$16,"Média","Baixa")) -> Média
A81: CTD00080 | B81: RJ | C81: Sudeste | D81: Pequeno Escritório | E81: Tecnologia | F81: 17 | G81: 77 | H81: 8 | I81: Questor | J81: Sim | K81: Não | L81: Prospect | M81: 1 | N81: =IF(F81<8,"1. < 8 anos",IF(F81<16,"2. 8 a 15 anos","3. 16+ anos")) -> 3. 16+ anos | O81: =IF(G81<20,"1. < 20",IF(G81<50,"2. 20 a 49",IF(G81<150,"3. 50 a 149","4. 150+"))) -> 3. 50 a 149 | P81: =IF(H81<=2,"1. 1 a 2",IF(H81<=5,"2. 3 a 5",IF(H81<=15,"3. 6 a 15","4. 16+"))) -> 3. 6 a 15 | Q81: =IF(OR(I81="Nenhum",I81="Planilha",I81="ContaAzul"),1,0) -> 0 | R81: =IF(AND(G81>=50,H81>=6,Q81=0),1,0) -> 1 | S81: =IF(AND(L81<>"Cliente Ativo",M81=0),1,0) -> 0 | V81: =AVERAGEIF($D$2:$D$601,D81,$M$2:$M$601) -> 0.43835616 | W81: =AVERAGEIF($P$2:$P$601,P81,$M$2:$M$601) -> 0.55319149 | X81: =AVERAGEIF($O$2:$O$601,O81,$M$2:$M$601) -> 0.58992806 | Y81: =AVERAGEIF($I$2:$I$601,I81,$M$2:$M$601) -> 0.39751553 | Z81: =AVERAGEIF($N$2:$N$601,N81,$M$2:$M$601) -> 0.56634304 | AA81: =ROUND(AVERAGE(V81:Z81),10) -> 0.50906686 | AB81: =IF(AA81>=Como_Avaliar!$B$15,"Alta",IF(AA81>=Como_Avaliar!$B$16,"Média","Baixa")) -> Alta
A82: CTD00081 | B82: SC | C82: Sul | D82: Autônomo | E82: Indústria | F82: 4 | G82: 13 | H82: 2 | I82: Domínio | J82: Não | K82: Não | L82: Cliente Ativo | M82: 0 | N82: =IF(F82<8,"1. < 8 anos",IF(F82<16,"2. 8 a 15 anos","3. 16+ anos")) -> 1. < 8 anos | O82: =IF(G82<20,"1. < 20",IF(G82<50,"2. 20 a 49",IF(G82<150,"3. 50 a 149","4. 150+"))) -> 1. < 20 | P82: =IF(H82<=2,"1. 1 a 2",IF(H82<=5,"2. 3 a 5",IF(H82<=15,"3. 6 a 15","4. 16+"))) -> 1. 1 a 2 | Q82: =IF(OR(I82="Nenhum",I82="Planilha",I82="ContaAzul"),1,0) -> 0 | R82: =IF(AND(G82>=50,H82>=6,Q82=0),1,0) -> 0 | S82: =IF(AND(L82<>"Cliente Ativo",M82=0),1,0) -> 0 | V82: =AVERAGEIF($D$2:$D$601,D82,$M$2:$M$601) -> 0.068273092 | W82: =AVERAGEIF($P$2:$P$601,P82,$M$2:$M$601) -> 0.086792453 | X82: =AVERAGEIF($O$2:$O$601,O82,$M$2:$M$601) -> 0.10309278 | Y82: =AVERAGEIF($I$2:$I$601,I82,$M$2:$M$601) -> 0.37662338 | Z82: =AVERAGEIF($N$2:$N$601,N82,$M$2:$M$601) -> 0.22368421 | AA82: =ROUND(AVERAGE(V82:Z82),10) -> 0.17169318 | AB82: =IF(AA82>=Como_Avaliar!$B$15,"Alta",IF(AA82>=Como_Avaliar!$B$16,"Média","Baixa")) -> Baixa
A83: CTD00082 | B83: RJ | C83: Sudeste | D83: Autônomo | E83: Indústria | F83: 18 | G83: 18 | H83: 2 | I83: Domínio | J83: Não | K83: Não | L83: Lead Quente | M83: 0 | N83: =IF(F83<8,"1. < 8 anos",IF(F83<16,"2. 8 a 15 anos","3. 16+ anos")) -> 3. 16+ anos | O83: =IF(G83<20,"1. < 20",IF(G83<50,"2. 20 a 49",IF(G83<150,"3. 50 a 149","4. 150+"))) -> 1. < 20 | P83: =IF(H83<=2,"1. 1 a 2",IF(H83<=5,"2. 3 a 5",IF(H83<=15,"3. 6 a 15","4. 16+"))) -> 1. 1 a 2 | Q83: =IF(OR(I83="Nenhum",I83="Planilha",I83="ContaAzul"),1,0) -> 0 | R83: =IF(AND(G83>=50,H83>=6,Q83=0),1,0) -> 0 | S83: =IF(AND(L83<>"Cliente Ativo",M83=0),1,0) -> 1 | T83: 2 | U83: Baixa | V83: =AVERAGEIF($D$2:$D$601,D83,$M$2:$M$601) -> 0.068273092 | W83: =AVERAGEIF($P$2:$P$601,P83,$M$2:$M$601) -> 0.086792453 | X83: =AVERAGEIF($O$2:$O$601,O83,$M$2:$M$601) -> 0.10309278 | Y83: =AVERAGEIF($I$2:$I$601,I83,$M$2:$M$601) -> 0.37662338 | Z83: =AVERAGEIF($N$2:$N$601,N83,$M$2:$M$601) -> 0.56634304 | AA83: =ROUND(AVERAGE(V83:Z83),10) -> 0.24022495 | AB83: =IF(AA83>=Como_Avaliar!$B$15,"Alta",IF(AA83>=Como_Avaliar!$B$16,"Média","Baixa")) -> Média
A84: CTD00083 | B84: SC | C84: Sul | D84: Pequeno Escritório | E84: Varejo/Comércio | F84: 8 | G84: 59 | H84: 7 | I84: Questor | J84: Não | K84: Não | L84: Cliente Ativo | M84: 1 | N84: =IF(F84<8,"1. < 8 anos",IF(F84<16,"2. 8 a 15 anos","3. 16+ anos")) -> 2. 8 a 15 anos | O84: =IF(G84<20,"1. < 20",IF(G84<50,"2. 20 a 49",IF(G84<150,"3. 50 a 149","4. 150+"))) -> 3. 50 a 149 | P84: =IF(H84<=2,"1. 1 a 2",IF(H84<=5,"2. 3 a 5",IF(H84<=15,"3. 6 a 15","4. 16+"))) -> 3. 6 a 15 | Q84: =IF(OR(I84="Nenhum",I84="Planilha",I84="ContaAzul"),1,0) -> 0 | R84: =IF(AND(G84>=50,H84>=6,Q84=0),1,0) -> 1 | S84: =IF(AND(L84<>"Cliente Ativo",M84=0),1,0) -> 0 | V84: =AVERAGEIF($D$2:$D$601,D84,$M$2:$M$601) -> 0.43835616 | W84: =AVERAGEIF($P$2:$P$601,P84,$M$2:$M$601) -> 0.55319149 | X84: =AVERAGEIF($O$2:$O$601,O84,$M$2:$M$601) -> 0.58992806 | Y84: =AVERAGEIF($I$2:$I$601,I84,$M$2:$M$601) -> 0.39751553 | Z84: =AVERAGEIF($N$2:$N$601,N84,$M$2:$M$601) -> 0.22302158 | AA84: =ROUND(AVERAGE(V84:Z84),10) -> 0.44040256 | AB84: =IF(AA84>=Como_Avaliar!$B$15,"Alta",IF(AA84>=Como_Avaliar!$B$16,"Média","Baixa")) -> Média
A85: CTD00084 | B85: PE | C85: Nordeste | D85: Pequeno Escritório | E85: Tecnologia | F85: 4 | G85: 50 | H85: 8 | I85: Questor | J85: Não | K85: Não | L85: Prospect | M85: 0 | N85: =IF(F85<8,"1. < 8 anos",IF(F85<16,"2. 8 a 15 anos","3. 16+ anos")) -> 1. < 8 anos | O85: =IF(G85<20,"1. < 20",IF(G85<50,"2. 20 a 49",IF(G85<150,"3. 50 a 149","4. 150+"))) -> 3. 50 a 149 | P85: =IF(H85<=2,"1. 1 a 2",IF(H85<=5,"2. 3 a 5",IF(H85<=15,"3. 6 a 15","4. 16+"))) -> 3. 6 a 15 | Q85: =IF(OR(I85="Nenhum",I85="Planilha",I85="ContaAzul"),1,0) -> 0 | R85: =IF(AND(G85>=50,H85>=6,Q85=0),1,0) -> 1 | S85: =IF(AND(L85<>"Cliente Ativo",M85=0),1,0) -> 1 | T85: 3 | U85: Média | V85: =AVERAGEIF($D$2:$D$601,D85,$M$2:$M$601) -> 0.43835616 | W85: =AVERAGEIF($P$2:$P$601,P85,$M$2:$M$601) -> 0.55319149 | X85: =AVERAGEIF($O$2:$O$601,O85,$M$2:$M$601) -> 0.58992806 | Y85: =AVERAGEIF($I$2:$I$601,I85,$M$2:$M$601) -> 0.39751553 | Z85: =AVERAGEIF($N$2:$N$601,N85,$M$2:$M$601) -> 0.22368421 | AA85: =ROUND(AVERAGE(V85:Z85),10) -> 0.44053509 | AB85: =IF(AA85>=Como_Avaliar!$B$15,"Alta",IF(AA85>=Como_Avaliar!$B$16,"Média","Baixa")) -> Média
A86: CTD00085 | B86: MG | C86: Sudeste | D86: Pequeno Escritório | E86: Agronegócio | F86: 2 | G86: 51 | H86: 4 | I86: Totvs | J86: Sim | K86: Sim | L86: Lead Quente | M86: 0 | N86: =IF(F86<8,"1. < 8 anos",IF(F86<16,"2. 8 a 15 anos","3. 16+ anos")) -> 1. < 8 anos | O86: =IF(G86<20,"1. < 20",IF(G86<50,"2. 20 a 49",IF(G86<150,"3. 50 a 149","4. 150+"))) -> 3. 50 a 149 | P86: =IF(H86<=2,"1. 1 a 2",IF(H86<=5,"2. 3 a 5",IF(H86<=15,"3. 6 a 15","4. 16+"))) -> 2. 3 a 5 | Q86: =IF(OR(I86="Nenhum",I86="Planilha",I86="ContaAzul"),1,0) -> 0 | R86: =IF(AND(G86>=50,H86>=6,Q86=0),1,0) -> 0 | S86: =IF(AND(L86<>"Cliente Ativo",M86=0),1,0) -> 1 | T86: 3 | U86: Média | V86: =AVERAGEIF($D$2:$D$601,D86,$M$2:$M$601) -> 0.43835616 | W86: =AVERAGEIF($P$2:$P$601,P86,$M$2:$M$601) -> 0.38095238 | X86: =AVERAGEIF($O$2:$O$601,O86,$M$2:$M$601) -> 0.58992806 | Y86: =AVERAGEIF($I$2:$I$601,I86,$M$2:$M$601) -> 0.58333333 | Z86: =AVERAGEIF($N$2:$N$601,N86,$M$2:$M$601) -> 0.22368421 | AA86: =ROUND(AVERAGE(V86:Z86),10) -> 0.44325083 | AB86: =IF(AA86>=Como_Avaliar!$B$15,"Alta",IF(AA86>=Como_Avaliar!$B$16,"Média","Baixa")) -> Média
A87: CTD00086 | B87: SP | C87: Sudeste | D87: Autônomo | E87: Tecnologia | F87: 6 | G87: 6 | H87: 2 | I87: Domínio | J87: Sim | K87: Sim | L87: Lead Frio | M87: 0 | N87: =IF(F87<8,"1. < 8 anos",IF(F87<16,"2. 8 a 15 anos","3. 16+ anos")) -> 1. < 8 anos | O87: =IF(G87<20,"1. < 20",IF(G87<50,"2. 20 a 49",IF(G87<150,"3. 50 a 149","4. 150+"))) -> 1. < 20 | P87: =IF(H87<=2,"1. 1 a 2",IF(H87<=5,"2. 3 a 5",IF(H87<=15,"3. 6 a 15","4. 16+"))) -> 1. 1 a 2 | Q87: =IF(OR(I87="Nenhum",I87="Planilha",I87="ContaAzul"),1,0) -> 0 | R87: =IF(AND(G87>=50,H87>=6,Q87=0),1,0) -> 0 | S87: =IF(AND(L87<>"Cliente Ativo",M87=0),1,0) -> 1 | T87: 1 | U87: Baixa | V87: =AVERAGEIF($D$2:$D$601,D87,$M$2:$M$601) -> 0.068273092 | W87: =AVERAGEIF($P$2:$P$601,P87,$M$2:$M$601) -> 0.086792453 | X87: =AVERAGEIF($O$2:$O$601,O87,$M$2:$M$601) -> 0.10309278 | Y87: =AVERAGEIF($I$2:$I$601,I87,$M$2:$M$601) -> 0.37662338 | Z87: =AVERAGEIF($N$2:$N$601,N87,$M$2:$M$601) -> 0.22368421 | AA87: =ROUND(AVERAGE(V87:Z87),10) -> 0.17169318 | AB87: =IF(AA87>=Como_Avaliar!$B$15,"Alta",IF(AA87>=Como_Avaliar!$B$16,"Média","Baixa")) -> Baixa
A88: CTD00087 | B88: RO | C88: Norte | D88: Autônomo | E88: Tecnologia | F88: 22 | G88: 21 | H88: 2 | I88: ContaAzul | J88: Não | K88: Não | L88: Lead Quente | M88: 0 | N88: =IF(F88<8,"1. < 8 anos",IF(F88<16,"2. 8 a 15 anos","3. 16+ anos")) -> 3. 16+ anos | O88: =IF(G88<20,"1. < 20",IF(G88<50,"2. 20 a 49",IF(G88<150,"3. 50 a 149","4. 150+"))) -> 2. 20 a 49 | P88: =IF(H88<=2,"1. 1 a 2",IF(H88<=5,"2. 3 a 5",IF(H88<=15,"3. 6 a 15","4. 16+"))) -> 1. 1 a 2 | Q88: =IF(OR(I88="Nenhum",I88="Planilha",I88="ContaAzul"),1,0) -> 1 | R88: =IF(AND(G88>=50,H88>=6,Q88=0),1,0) -> 0 | S88: =IF(AND(L88<>"Cliente Ativo",M88=0),1,0) -> 1 | T88: 2 | U88: Baixa | V88: =AVERAGEIF($D$2:$D$601,D88,$M$2:$M$601) -> 0.068273092 | W88: =AVERAGEIF($P$2:$P$601,P88,$M$2:$M$601) -> 0.086792453 | X88: =AVERAGEIF($O$2:$O$601,O88,$M$2:$M$601) -> 0.25294118 | Y88: =AVERAGEIF($I$2:$I$601,I88,$M$2:$M$601) -> 0 | Z88: =AVERAGEIF($N$2:$N$601,N88,$M$2:$M$601) -> 0.56634304 | AA88: =ROUND(AVERAGE(V88:Z88),10) -> 0.19486995 | AB88: =IF(AA88>=Como_Avaliar!$B$15,"Alta",IF(AA88>=Como_Avaliar!$B$16,"Média","Baixa")) -> Baixa
A89: CTD00088 | B89: PR | C89: Sul | D89: Pequeno Escritório | E89: Indústria | F89: 10 | G89: 63 | H89: 5 | I89: Totvs | J89: Sim | K89: Não | L89: Lead Frio | M89: 1 | N89: =IF(F89<8,"1. < 8 anos",IF(F89<16,"2. 8 a 15 anos","3. 16+ anos")) -> 2. 8 a 15 anos | O89: =IF(G89<20,"1. < 20",IF(G89<50,"2. 20 a 49",IF(G89<150,"3. 50 a 149","4. 150+"))) -> 3. 50 a 149 | P89: =IF(H89<=2,"1. 1 a 2",IF(H89<=5,"2. 3 a 5",IF(H89<=15,"3. 6 a 15","4. 16+"))) -> 2. 3 a 5 | Q89: =IF(OR(I89="Nenhum",I89="Planilha",I89="ContaAzul"),1,0) -> 0 | R89: =IF(AND(G89>=50,H89>=6,Q89=0),1,0) -> 0 | S89: =IF(AND(L89<>"Cliente Ativo",M89=0),1,0) -> 0 | V89: =AVERAGEIF($D$2:$D$601,D89,$M$2:$M$601) -> 0.43835616 | W89: =AVERAGEIF($P$2:$P$601,P89,$M$2:$M$601) -> 0.38095238 | X89: =AVERAGEIF($O$2:$O$601,O89,$M$2:$M$601) -> 0.58992806 | Y89: =AVERAGEIF($I$2:$I$601,I89,$M$2:$M$601) -> 0.58333333 | Z89: =AVERAGEIF($N$2:$N$601,N89,$M$2:$M$601) -> 0.22302158 | AA89: =ROUND(AVERAGE(V89:Z89),10) -> 0.4431183 | AB89: =IF(AA89>=Como_Avaliar!$B$15,"Alta",IF(AA89>=Como_Avaliar!$B$16,"Média","Baixa")) -> Média
A90: CTD00089 | B90: SP | C90: Sudeste | D90: Pequeno Escritório | E90: Serviços | F90: 4 | G90: 65 | H90: 9 | I90: Domínio | J90: Sim | K90: Sim | L90: Prospect | M90: 0 | N90: =IF(F90<8,"1. < 8 anos",IF(F90<16,"2. 8 a 15 anos","3. 16+ anos")) -> 1. < 8 anos | O90: =IF(G90<20,"1. < 20",IF(G90<50,"2. 20 a 49",IF(G90<150,"3. 50 a 149","4. 150+"))) -> 3. 50 a 149 | P90: =IF(H90<=2,"1. 1 a 2",IF(H90<=5,"2. 3 a 5",IF(H90<=15,"3. 6 a 15","4. 16+"))) -> 3. 6 a 15 | Q90: =IF(OR(I90="Nenhum",I90="Planilha",I90="ContaAzul"),1,0) -> 0 | R90: =IF(AND(G90>=50,H90>=6,Q90=0),1,0) -> 1 | S90: =IF(AND(L90<>"Cliente Ativo",M90=0),1,0) -> 1 | T90: 3 | U90: Média | V90: =AVERAGEIF($D$2:$D$601,D90,$M$2:$M$601) -> 0.43835616 | W90: =AVERAGEIF($P$2:$P$601,P90,$M$2:$M$601) -> 0.55319149 | X90: =AVERAGEIF($O$2:$O$601,O90,$M$2:$M$601) -> 0.58992806 | Y90: =AVERAGEIF($I$2:$I$601,I90,$M$2:$M$601) -> 0.37662338 | Z90: =AVERAGEIF($N$2:$N$601,N90,$M$2:$M$601) -> 0.22368421 | AA90: =ROUND(AVERAGE(V90:Z90),10) -> 0.43635666 | AB90: =IF(AA90>=Como_Avaliar!$B$15,"Alta",IF(AA90>=Como_Avaliar!$B$16,"Média","Baixa")) -> Média
A91: CTD00090 | B91: SP | C91: Sudeste | D91: Pequeno Escritório | E91: Varejo/Comércio | F91: 22 | G91: 59 | H91: 7 | I91: Questor | J91: Sim | K91: Não | L91: Cliente Ativo | M91: 1 | N91: =IF(F91<8,"1. < 8 anos",IF(F91<16,"2. 8 a 15 anos","3. 16+ anos")) -> 3. 16+ anos | O91: =IF(G91<20,"1. < 20",IF(G91<50,"2. 20 a 49",IF(G91<150,"3. 50 a 149","4. 150+"))) -> 3. 50 a 149 | P91: =IF(H91<=2,"1. 1 a 2",IF(H91<=5,"2. 3 a 5",IF(H91<=15,"3. 6 a 15","4. 16+"))) -> 3. 6 a 15 | Q91: =IF(OR(I91="Nenhum",I91="Planilha",I91="ContaAzul"),1,0) -> 0 | R91: =IF(AND(G91>=50,H91>=6,Q91=0),1,0) -> 1 | S91: =IF(AND(L91<>"Cliente Ativo",M91=0),1,0) -> 0 | V91: =AVERAGEIF($D$2:$D$601,D91,$M$2:$M$601) -> 0.43835616 | W91: =AVERAGEIF($P$2:$P$601,P91,$M$2:$M$601) -> 0.55319149 | X91: =AVERAGEIF($O$2:$O$601,O91,$M$2:$M$601) -> 0.58992806 | Y91: =AVERAGEIF($I$2:$I$601,I91,$M$2:$M$601) -> 0.39751553 | Z91: =AVERAGEIF($N$2:$N$601,N91,$M$2:$M$601) -> 0.56634304 | AA91: =ROUND(AVERAGE(V91:Z91),10) -> 0.50906686 | AB91: =IF(AA91>=Como_Avaliar!$B$15,"Alta",IF(AA91>=Como_Avaliar!$B$16,"Média","Baixa")) -> Alta
A92: CTD00091 | B92: SP | C92: Sudeste | D92: Autônomo | E92: Tecnologia | F92: 29 | G92: 7 | H92: 1 | I92: Nenhum | J92: Sim | K92: Não | L92: Lead Quente | M92: 1 | N92: =IF(F92<8,"1. < 8 anos",IF(F92<16,"2. 8 a 15 anos","3. 16+ anos")) -> 3. 16+ anos | O92: =IF(G92<20,"1. < 20",IF(G92<50,"2. 20 a 49",IF(G92<150,"3. 50 a 149","4. 150+"))) -> 1. < 20 | P92: =IF(H92<=2,"1. 1 a 2",IF(H92<=5,"2. 3 a 5",IF(H92<=15,"3. 6 a 15","4. 16+"))) -> 1. 1 a 2 | Q92: =IF(OR(I92="Nenhum",I92="Planilha",I92="ContaAzul"),1,0) -> 1 | R92: =IF(AND(G92>=50,H92>=6,Q92=0),1,0) -> 0 | S92: =IF(AND(L92<>"Cliente Ativo",M92=0),1,0) -> 0 | V92: =AVERAGEIF($D$2:$D$601,D92,$M$2:$M$601) -> 0.068273092 | W92: =AVERAGEIF($P$2:$P$601,P92,$M$2:$M$601) -> 0.086792453 | X92: =AVERAGEIF($O$2:$O$601,O92,$M$2:$M$601) -> 0.10309278 | Y92: =AVERAGEIF($I$2:$I$601,I92,$M$2:$M$601) -> 0.065217391 | Z92: =AVERAGEIF($N$2:$N$601,N92,$M$2:$M$601) -> 0.56634304 | AA92: =ROUND(AVERAGE(V92:Z92),10) -> 0.17794375 | AB92: =IF(AA92>=Como_Avaliar!$B$15,"Alta",IF(AA92>=Como_Avaliar!$B$16,"Média","Baixa")) -> Baixa
A93: CTD00092 | B93: RS | C93: Sul | D93: Pequeno Escritório | E93: Varejo/Comércio | F93: 18 | G93: 52 | H93: 8 | I93: Domínio | J93: Não | K93: Não | L93: Lead Quente | M93: 1 | N93: =IF(F93<8,"1. < 8 anos",IF(F93<16,"2. 8 a 15 anos","3. 16+ anos")) -> 3. 16+ anos | O93: =IF(G93<20,"1. < 20",IF(G93<50,"2. 20 a 49",IF(G93<150,"3. 50 a 149","4. 150+"))) -> 3. 50 a 149 | P93: =IF(H93<=2,"1. 1 a 2",IF(H93<=5,"2. 3 a 5",IF(H93<=15,"3. 6 a 15","4. 16+"))) -> 3. 6 a 15 | Q93: =IF(OR(I93="Nenhum",I93="Planilha",I93="ContaAzul"),1,0) -> 0 | R93: =IF(AND(G93>=50,H93>=6,Q93=0),1,0) -> 1 | S93: =IF(AND(L93<>"Cliente Ativo",M93=0),1,0) -> 0 | V93: =AVERAGEIF($D$2:$D$601,D93,$M$2:$M$601) -> 0.43835616 | W93: =AVERAGEIF($P$2:$P$601,P93,$M$2:$M$601) -> 0.55319149 | X93: =AVERAGEIF($O$2:$O$601,O93,$M$2:$M$601) -> 0.58992806 | Y93: =AVERAGEIF($I$2:$I$601,I93,$M$2:$M$601) -> 0.37662338 | Z93: =AVERAGEIF($N$2:$N$601,N93,$M$2:$M$601) -> 0.56634304 | AA93: =ROUND(AVERAGE(V93:Z93),10) -> 0.50488843 | AB93: =IF(AA93>=Como_Avaliar!$B$15,"Alta",IF(AA93>=Como_Avaliar!$B$16,"Média","Baixa")) -> Alta
A94: CTD00093 | B94: DF | C94: Centro-Oeste | D94: Grande Escritório | E94: Agronegócio | F94: 26 | G94: 243 | H94: 65 | I94: Alterdata | J94: Não | K94: Sim | L94: Lead Quente | M94: 1 | N94: =IF(F94<8,"1. < 8 anos",IF(F94<16,"2. 8 a 15 anos","3. 16+ anos")) -> 3. 16+ anos | O94: =IF(G94<20,"1. < 20",IF(G94<50,"2. 20 a 49",IF(G94<150,"3. 50 a 149","4. 150+"))) -> 4. 150+ | P94: =IF(H94<=2,"1. 1 a 2",IF(H94<=5,"2. 3 a 5",IF(H94<=15,"3. 6 a 15","4. 16+"))) -> 4. 16+ | Q94: =IF(OR(I94="Nenhum",I94="Planilha",I94="ContaAzul"),1,0) -> 0 | R94: =IF(AND(G94>=50,H94>=6,Q94=0),1,0) -> 1 | S94: =IF(AND(L94<>"Cliente Ativo",M94=0),1,0) -> 0 | V94: =AVERAGEIF($D$2:$D$601,D94,$M$2:$M$601) -> 1 | W94: =AVERAGEIF($P$2:$P$601,P94,$M$2:$M$601) -> 0.97272727 | X94: =AVERAGEIF($O$2:$O$601,O94,$M$2:$M$601) -> 0.97938144 | Y94: =AVERAGEIF($I$2:$I$601,I94,$M$2:$M$601) -> 0.65217391 | Z94: =AVERAGEIF($N$2:$N$601,N94,$M$2:$M$601) -> 0.56634304 | AA94: =ROUND(AVERAGE(V94:Z94),10) -> 0.83412513 | AB94: =IF(AA94>=Como_Avaliar!$B$15,"Alta",IF(AA94>=Como_Avaliar!$B$16,"Média","Baixa")) -> Alta
A95: CTD00094 | B95: MG | C95: Sudeste | D95: Autônomo | E95: Saúde | F95: 12 | G95: 12 | H95: 2 | I95: Questor | J95: Não | K95: Não | L95: Prospect | M95: 0 | N95: =IF(F95<8,"1. < 8 anos",IF(F95<16,"2. 8 a 15 anos","3. 16+ anos")) -> 2. 8 a 15 anos | O95: =IF(G95<20,"1. < 20",IF(G95<50,"2. 20 a 49",IF(G95<150,"3. 50 a 149","4. 150+"))) -> 1. < 20 | P95: =IF(H95<=2,"1. 1 a 2",IF(H95<=5,"2. 3 a 5",IF(H95<=15,"3. 6 a 15","4. 16+"))) -> 1. 1 a 2 | Q95: =IF(OR(I95="Nenhum",I95="Planilha",I95="ContaAzul"),1,0) -> 0 | R95: =IF(AND(G95>=50,H95>=6,Q95=0),1,0) -> 0 | S95: =IF(AND(L95<>"Cliente Ativo",M95=0),1,0) -> 1 | T95: 1 | U95: Baixa | V95: =AVERAGEIF($D$2:$D$601,D95,$M$2:$M$601) -> 0.068273092 | W95: =AVERAGEIF($P$2:$P$601,P95,$M$2:$M$601) -> 0.086792453 | X95: =AVERAGEIF($O$2:$O$601,O95,$M$2:$M$601) -> 0.10309278 | Y95: =AVERAGEIF($I$2:$I$601,I95,$M$2:$M$601) -> 0.39751553 | Z95: =AVERAGEIF($N$2:$N$601,N95,$M$2:$M$601) -> 0.22302158 | AA95: =ROUND(AVERAGE(V95:Z95),10) -> 0.17573909 | AB95: =IF(AA95>=Como_Avaliar!$B$15,"Alta",IF(AA95>=Como_Avaliar!$B$16,"Média","Baixa")) -> Baixa
A96: CTD00095 | B96: SP | C96: Sudeste | D96: Grande Escritório | E96: Serviços | F96: 2 | G96: 280 | H96: 87 | I96: Totvs | J96: Não | K96: Não | L96: Lead Quente | M96: 1 | N96: =IF(F96<8,"1. < 8 anos",IF(F96<16,"2. 8 a 15 anos","3. 16+ anos")) -> 1. < 8 anos | O96: =IF(G96<20,"1. < 20",IF(G96<50,"2. 20 a 49",IF(G96<150,"3. 50 a 149","4. 150+"))) -> 4. 150+ | P96: =IF(H96<=2,"1. 1 a 2",IF(H96<=5,"2. 3 a 5",IF(H96<=15,"3. 6 a 15","4. 16+"))) -> 4. 16+ | Q96: =IF(OR(I96="Nenhum",I96="Planilha",I96="ContaAzul"),1,0) -> 0 | R96: =IF(AND(G96>=50,H96>=6,Q96=0),1,0) -> 1 | S96: =IF(AND(L96<>"Cliente Ativo",M96=0),1,0) -> 0 | V96: =AVERAGEIF($D$2:$D$601,D96,$M$2:$M$601) -> 1 | W96: =AVERAGEIF($P$2:$P$601,P96,$M$2:$M$601) -> 0.97272727 | X96: =AVERAGEIF($O$2:$O$601,O96,$M$2:$M$601) -> 0.97938144 | Y96: =AVERAGEIF($I$2:$I$601,I96,$M$2:$M$601) -> 0.58333333 | Z96: =AVERAGEIF($N$2:$N$601,N96,$M$2:$M$601) -> 0.22368421 | AA96: =ROUND(AVERAGE(V96:Z96),10) -> 0.75182525 | AB96: =IF(AA96>=Como_Avaliar!$B$15,"Alta",IF(AA96>=Como_Avaliar!$B$16,"Média","Baixa")) -> Alta
A97: CTD00096 | B97: MG | C97: Sudeste | D97: Pequeno Escritório | E97: Serviços | F97: 10 | G97: 59 | H97: 5 | I97: Alterdata | J97: Não | K97: Sim | L97: Lead Quente | M97: 0 | N97: =IF(F97<8,"1. < 8 anos",IF(F97<16,"2. 8 a 15 anos","3. 16+ anos")) -> 2. 8 a 15 anos | O97: =IF(G97<20,"1. < 20",IF(G97<50,"2. 20 a 49",IF(G97<150,"3. 50 a 149","4. 150+"))) -> 3. 50 a 149 | P97: =IF(H97<=2,"1. 1 a 2",IF(H97<=5,"2. 3 a 5",IF(H97<=15,"3. 6 a 15","4. 16+"))) -> 2. 3 a 5 | Q97: =IF(OR(I97="Nenhum",I97="Planilha",I97="ContaAzul"),1,0) -> 0 | R97: =IF(AND(G97>=50,H97>=6,Q97=0),1,0) -> 0 | S97: =IF(AND(L97<>"Cliente Ativo",M97=0),1,0) -> 1 | T97: 3 | U97: Média | V97: =AVERAGEIF($D$2:$D$601,D97,$M$2:$M$601) -> 0.43835616 | W97: =AVERAGEIF($P$2:$P$601,P97,$M$2:$M$601) -> 0.38095238 | X97: =AVERAGEIF($O$2:$O$601,O97,$M$2:$M$601) -> 0.58992806 | Y97: =AVERAGEIF($I$2:$I$601,I97,$M$2:$M$601) -> 0.65217391 | Z97: =AVERAGEIF($N$2:$N$601,N97,$M$2:$M$601) -> 0.22302158 | AA97: =ROUND(AVERAGE(V97:Z97),10) -> 0.45688642 | AB97: =IF(AA97>=Como_Avaliar!$B$15,"Alta",IF(AA97>=Como_Avaliar!$B$16,"Média","Baixa")) -> Média
A98: CTD00097 | B98: RO | C98: Norte | D98: Pequeno Escritório | E98: Saúde | F98: 4 | G98: 71 | H98: 7 | I98: Questor | J98: Não | K98: Sim | L98: Prospect | M98: 0 | N98: =IF(F98<8,"1. < 8 anos",IF(F98<16,"2. 8 a 15 anos","3. 16+ anos")) -> 1. < 8 anos | O98: =IF(G98<20,"1. < 20",IF(G98<50,"2. 20 a 49",IF(G98<150,"3. 50 a 149","4. 150+"))) -> 3. 50 a 149 | P98: =IF(H98<=2,"1. 1 a 2",IF(H98<=5,"2. 3 a 5",IF(H98<=15,"3. 6 a 15","4. 16+"))) -> 3. 6 a 15 | Q98: =IF(OR(I98="Nenhum",I98="Planilha",I98="ContaAzul"),1,0) -> 0 | R98: =IF(AND(G98>=50,H98>=6,Q98=0),1,0) -> 1 | S98: =IF(AND(L98<>"Cliente Ativo",M98=0),1,0) -> 1 | T98: 4 | U98: Alta | V98: =AVERAGEIF($D$2:$D$601,D98,$M$2:$M$601) -> 0.43835616 | W98: =AVERAGEIF($P$2:$P$601,P98,$M$2:$M$601) -> 0.55319149 | X98: =AVERAGEIF($O$2:$O$601,O98,$M$2:$M$601) -> 0.58992806 | Y98: =AVERAGEIF($I$2:$I$601,I98,$M$2:$M$601) -> 0.39751553 | Z98: =AVERAGEIF($N$2:$N$601,N98,$M$2:$M$601) -> 0.22368421 | AA98: =ROUND(AVERAGE(V98:Z98),10) -> 0.44053509 | AB98: =IF(AA98>=Como_Avaliar!$B$15,"Alta",IF(AA98>=Como_Avaliar!$B$16,"Média","Baixa")) -> Média
A99: CTD00098 | B99: PR | C99: Sul | D99: Autônomo | E99: Agronegócio | F99: 14 | G99: 23 | H99: 2 | I99: Domínio | J99: Não | K99: Não | L99: Sem Contato | M99: 0 | N99: =IF(F99<8,"1. < 8 anos",IF(F99<16,"2. 8 a 15 anos","3. 16+ anos")) -> 2. 8 a 15 anos | O99: =IF(G99<20,"1. < 20",IF(G99<50,"2. 20 a 49",IF(G99<150,"3. 50 a 149","4. 150+"))) -> 2. 20 a 49 | P99: =IF(H99<=2,"1. 1 a 2",IF(H99<=5,"2. 3 a 5",IF(H99<=15,"3. 6 a 15","4. 16+"))) -> 1. 1 a 2 | Q99: =IF(OR(I99="Nenhum",I99="Planilha",I99="ContaAzul"),1,0) -> 0 | R99: =IF(AND(G99>=50,H99>=6,Q99=0),1,0) -> 0 | S99: =IF(AND(L99<>"Cliente Ativo",M99=0),1,0) -> 1 | T99: 2 | U99: Baixa | V99: =AVERAGEIF($D$2:$D$601,D99,$M$2:$M$601) -> 0.068273092 | W99: =AVERAGEIF($P$2:$P$601,P99,$M$2:$M$601) -> 0.086792453 | X99: =AVERAGEIF($O$2:$O$601,O99,$M$2:$M$601) -> 0.25294118 | Y99: =AVERAGEIF($I$2:$I$601,I99,$M$2:$M$601) -> 0.37662338 | Z99: =AVERAGEIF($N$2:$N$601,N99,$M$2:$M$601) -> 0.22302158 | AA99: =ROUND(AVERAGE(V99:Z99),10) -> 0.20153034 | AB99: =IF(AA99>=Como_Avaliar!$B$15,"Alta",IF(AA99>=Como_Avaliar!$B$16,"Média","Baixa")) -> Baixa
A100: CTD00099 | B100: AM | C100: Norte | D100: Pequeno Escritório | E100: Indústria | F100: 16 | G100: 47 | H100: 6 | I100: Planilha | J100: Não | K100: Não | L100: Lead Frio | M100: 0 | N100: =IF(F100<8,"1. < 8 anos",IF(F100<16,"2. 8 a 15 anos","3. 16+ anos")) -> 3. 16+ anos | O100: =IF(G100<20,"1. < 20",IF(G100<50,"2. 20 a 49",IF(G100<150,"3. 50 a 149","4. 150+"))) -> 2. 20 a 49 | P100: =IF(H100<=2,"1. 1 a 2",IF(H100<=5,"2. 3 a 5",IF(H100<=15,"3. 6 a 15","4. 16+"))) -> 3. 6 a 15 | Q100: =IF(OR(I100="Nenhum",I100="Planilha",I100="ContaAzul"),1,0) -> 1 | R100: =IF(AND(G100>=50,H100>=6,Q100=0),1,0) -> 0 | S100: =IF(AND(L100<>"Cliente Ativo",M100=0),1,0) -> 1 | T100: 3 | U100: Média | V100: =AVERAGEIF($D$2:$D$601,D100,$M$2:$M$601) -> 0.43835616 | W100: =AVERAGEIF($P$2:$P$601,P100,$M$2:$M$601) -> 0.55319149 | X100: =AVERAGEIF($O$2:$O$601,O100,$M$2:$M$601) -> 0.25294118 | Y100: =AVERAGEIF($I$2:$I$601,I100,$M$2:$M$601) -> 0.15625 | Z100: =AVERAGEIF($N$2:$N$601,N100,$M$2:$M$601) -> 0.56634304 | AA100: =ROUND(AVERAGE(V100:Z100),10) -> 0.39341637 | AB100: =IF(AA100>=Como_Avaliar!$B$15,"Alta",IF(AA100>=Como_Avaliar!$B$16,"Média","Baixa")) -> Média
...

Sheet Leads
A1: id_lead | B1: id_contador | C1: canal_origem | D1: status_lead | E1: mrr_inicial | F1: tentativas | G1: porte | H1: regiao | I1: converteu_omie | J1: com desfecho (Ganho/Perdido) | K1: ganho | L1: tier (1c) | M1: icp | N1: faixa de propensão (D2) | O1: tempo_ciclo_dias | P1: data_conversao
A2: LEAD00001 | B2: CTD00382 | C2: Franquia | D2: Perdido | F2: 1 | G2: =INDEX(Base!$D$2:$D$601,MATCH(B2,Base!$A$2:$A$601,0)) -> Autônomo | H2: =INDEX(Base!$C$2:$C$601,MATCH(B2,Base!$A$2:$A$601,0)) -> Sudeste | I2: =INDEX(Base!$M$2:$M$601,MATCH(B2,Base!$A$2:$A$601,0)) -> 0 | J2: =IF(OR(D2="Ganho",D2="Perdido"),1,0) -> 1 | K2: =IF(D2="Ganho",1,0) -> 0 | L2: =IF(INDEX(Base!$U$2:$U$601,MATCH(B2,Base!$A$2:$A$601,0))="","",INDEX(Base!$U$2:$U$601,MATCH(B2,Base!$A$2:$A$601,0))) -> Alta | M2: =INDEX(Base!$R$2:$R$601,MATCH(B2,Base!$A$2:$A$601,0)) -> 0 | N2: =INDEX(Base!$AB$2:$AB$601,MATCH(B2,Base!$A$2:$A$601,0)) -> Baixa | O2: 25
A3: LEAD00002 | B3: CTD00585 | C3: Inbound | D3: Ganho | E3: 1186.79 | F3: 5 | G3: =INDEX(Base!$D$2:$D$601,MATCH(B3,Base!$A$2:$A$601,0)) -> Autônomo | H3: =INDEX(Base!$C$2:$C$601,MATCH(B3,Base!$A$2:$A$601,0)) -> Nordeste | I3: =INDEX(Base!$M$2:$M$601,MATCH(B3,Base!$A$2:$A$601,0)) -> 0 | J3: =IF(OR(D3="Ganho",D3="Perdido"),1,0) -> 1 | K3: =IF(D3="Ganho",1,0) -> 1 | L3: =IF(INDEX(Base!$U$2:$U$601,MATCH(B3,Base!$A$2:$A$601,0))="","",INDEX(Base!$U$2:$U$601,MATCH(B3,Base!$A$2:$A$601,0))) -> Média | M3: =INDEX(Base!$R$2:$R$601,MATCH(B3,Base!$A$2:$A$601,0)) -> 0 | N3: =INDEX(Base!$AB$2:$AB$601,MATCH(B3,Base!$A$2:$A$601,0)) -> Média | O3: 58 | P3: 46074
A4: LEAD00003 | B4: CTD00046 | C4: Inbound | D4: Em Contato | F4: 1 | G4: =INDEX(Base!$D$2:$D$601,MATCH(B4,Base!$A$2:$A$601,0)) -> Grande Escritório | H4: =INDEX(Base!$C$2:$C$601,MATCH(B4,Base!$A$2:$A$601,0)) -> Sudeste | I4: =INDEX(Base!$M$2:$M$601,MATCH(B4,Base!$A$2:$A$601,0)) -> 1 | J4: =IF(OR(D4="Ganho",D4="Perdido"),1,0) -> 0 | K4: =IF(D4="Ganho",1,0) -> 0 | L4: =IF(INDEX(Base!$U$2:$U$601,MATCH(B4,Base!$A$2:$A$601,0))="","",INDEX(Base!$U$2:$U$601,MATCH(B4,Base!$A$2:$A$601,0))) | M4: =INDEX(Base!$R$2:$R$601,MATCH(B4,Base!$A$2:$A$601,0)) -> 1 | N4: =INDEX(Base!$AB$2:$AB$601,MATCH(B4,Base!$A$2:$A$601,0)) -> Alta | O4: 172
A5: LEAD00004 | B5: CTD00511 | C5: Inbound | D5: Em Contato | F5: 12 | G5: =INDEX(Base!$D$2:$D$601,MATCH(B5,Base!$A$2:$A$601,0)) -> Autônomo | H5: =INDEX(Base!$C$2:$C$601,MATCH(B5,Base!$A$2:$A$601,0)) -> Sudeste | I5: =INDEX(Base!$M$2:$M$601,MATCH(B5,Base!$A$2:$A$601,0)) -> 0 | J5: =IF(OR(D5="Ganho",D5="Perdido"),1,0) -> 0 | K5: =IF(D5="Ganho",1,0) -> 0 | L5: =IF(INDEX(Base!$U$2:$U$601,MATCH(B5,Base!$A$2:$A$601,0))="","",INDEX(Base!$U$2:$U$601,MATCH(B5,Base!$A$2:$A$601,0))) -> Baixa | M5: =INDEX(Base!$R$2:$R$601,MATCH(B5,Base!$A$2:$A$601,0)) -> 0 | N5: =INDEX(Base!$AB$2:$AB$601,MATCH(B5,Base!$A$2:$A$601,0)) -> Média | O5: 150
A6: LEAD00005 | B6: CTD00129 | C6: Franquia | D6: Perdido | F6: 6 | G6: =INDEX(Base!$D$2:$D$601,MATCH(B6,Base!$A$2:$A$601,0)) -> Médio Escritório | H6: =INDEX(Base!$C$2:$C$601,MATCH(B6,Base!$A$2:$A$601,0)) -> Nordeste | I6: =INDEX(Base!$M$2:$M$601,MATCH(B6,Base!$A$2:$A$601,0)) -> 1 | J6: =IF(OR(D6="Ganho",D6="Perdido"),1,0) -> 1 | K6: =IF(D6="Ganho",1,0) -> 0 | L6: =IF(INDEX(Base!$U$2:$U$601,MATCH(B6,Base!$A$2:$A$601,0))="","",INDEX(Base!$U$2:$U$601,MATCH(B6,Base!$A$2:$A$601,0))) | M6: =INDEX(Base!$R$2:$R$601,MATCH(B6,Base!$A$2:$A$601,0)) -> 1 | N6: =INDEX(Base!$AB$2:$AB$601,MATCH(B6,Base!$A$2:$A$601,0)) -> Alta | O6: 19
A7: LEAD00006 | B7: CTD00160 | C7: Outreach Ativo | D7: Sem Resposta | F7: 7 | G7: =INDEX(Base!$D$2:$D$601,MATCH(B7,Base!$A$2:$A$601,0)) -> Grande Escritório | H7: =INDEX(Base!$C$2:$C$601,MATCH(B7,Base!$A$2:$A$601,0)) -> Sudeste | I7: =INDEX(Base!$M$2:$M$601,MATCH(B7,Base!$A$2:$A$601,0)) -> 1 | J7: =IF(OR(D7="Ganho",D7="Perdido"),1,0) -> 0 | K7: =IF(D7="Ganho",1,0) -> 0 | L7: =IF(INDEX(Base!$U$2:$U$601,MATCH(B7,Base!$A$2:$A$601,0))="","",INDEX(Base!$U$2:$U$601,MATCH(B7,Base!$A$2:$A$601,0))) | M7: =INDEX(Base!$R$2:$R$601,MATCH(B7,Base!$A$2:$A$601,0)) -> 1 | N7: =INDEX(Base!$AB$2:$AB$601,MATCH(B7,Base!$A$2:$A$601,0)) -> Alta | O7: 28
A8: LEAD00007 | B8: CTD00179 | C8: Franquia | D8: Sem Resposta | F8: 7 | G8: =INDEX(Base!$D$2:$D$601,MATCH(B8,Base!$A$2:$A$601,0)) -> Autônomo | H8: =INDEX(Base!$C$2:$C$601,MATCH(B8,Base!$A$2:$A$601,0)) -> Sudeste | I8: =INDEX(Base!$M$2:$M$601,MATCH(B8,Base!$A$2:$A$601,0)) -> 0 | J8: =IF(OR(D8="Ganho",D8="Perdido"),1,0) -> 0 | K8: =IF(D8="Ganho",1,0) -> 0 | L8: =IF(INDEX(Base!$U$2:$U$601,MATCH(B8,Base!$A$2:$A$601,0))="","",INDEX(Base!$U$2:$U$601,MATCH(B8,Base!$A$2:$A$601,0))) -> Baixa | M8: =INDEX(Base!$R$2:$R$601,MATCH(B8,Base!$A$2:$A$601,0)) -> 0 | N8: =INDEX(Base!$AB$2:$AB$601,MATCH(B8,Base!$A$2:$A$601,0)) -> Baixa | O8: 27
A9: LEAD00008 | B9: CTD00345 | C9: Franquia | D9: Reunião Agendada | F9: 7 | G9: =INDEX(Base!$D$2:$D$601,MATCH(B9,Base!$A$2:$A$601,0)) -> Autônomo | H9: =INDEX(Base!$C$2:$C$601,MATCH(B9,Base!$A$2:$A$601,0)) -> Sudeste | I9: =INDEX(Base!$M$2:$M$601,MATCH(B9,Base!$A$2:$A$601,0)) -> 0 | J9: =IF(OR(D9="Ganho",D9="Perdido"),1,0) -> 0 | K9: =IF(D9="Ganho",1,0) -> 0 | L9: =IF(INDEX(Base!$U$2:$U$601,MATCH(B9,Base!$A$2:$A$601,0))="","",INDEX(Base!$U$2:$U$601,MATCH(B9,Base!$A$2:$A$601,0))) -> Média | M9: =INDEX(Base!$R$2:$R$601,MATCH(B9,Base!$A$2:$A$601,0)) -> 0 | N9: =INDEX(Base!$AB$2:$AB$601,MATCH(B9,Base!$A$2:$A$601,0)) -> Baixa | O9: 77
A10: LEAD00009 | B10: CTD00483 | C10: Inbound | D10: Em Contato | F10: 5 | G10: =INDEX(Base!$D$2:$D$601,MATCH(B10,Base!$A$2:$A$601,0)) -> Pequeno Escritório | H10: =INDEX(Base!$C$2:$C$601,MATCH(B10,Base!$A$2:$A$601,0)) -> Sudeste | I10: =INDEX(Base!$M$2:$M$601,MATCH(B10,Base!$A$2:$A$601,0)) -> 0 | J10: =IF(OR(D10="Ganho",D10="Perdido"),1,0) -> 0 | K10: =IF(D10="Ganho",1,0) -> 0 | L10: =IF(INDEX(Base!$U$2:$U$601,MATCH(B10,Base!$A$2:$A$601,0))="","",INDEX(Base!$U$2:$U$601,MATCH(B10,Base!$A$2:$A$601,0))) -> Média | M10: =INDEX(Base!$R$2:$R$601,MATCH(B10,Base!$A$2:$A$601,0)) -> 0 | N10: =INDEX(Base!$AB$2:$AB$601,MATCH(B10,Base!$A$2:$A$601,0)) -> Média | O10: 130
A11: LEAD00010 | B11: CTD00375 | C11: Outreach Ativo | D11: Perdido | F11: 3 | G11: =INDEX(Base!$D$2:$D$601,MATCH(B11,Base!$A$2:$A$601,0)) -> Autônomo | H11: =INDEX(Base!$C$2:$C$601,MATCH(B11,Base!$A$2:$A$601,0)) -> Sudeste | I11: =INDEX(Base!$M$2:$M$601,MATCH(B11,Base!$A$2:$A$601,0)) -> 0 | J11: =IF(OR(D11="Ganho",D11="Perdido"),1,0) -> 1 | K11: =IF(D11="Ganho",1,0) -> 0 | L11: =IF(INDEX(Base!$U$2:$U$601,MATCH(B11,Base!$A$2:$A$601,0))="","",INDEX(Base!$U$2:$U$601,MATCH(B11,Base!$A$2:$A$601,0))) -> Baixa | M11: =INDEX(Base!$R$2:$R$601,MATCH(B11,Base!$A$2:$A$601,0)) -> 0 | N11: =INDEX(Base!$AB$2:$AB$601,MATCH(B11,Base!$A$2:$A$601,0)) -> Baixa | O11: 96
A12: LEAD00011 | B12: CTD00575 | C12: Outreach Ativo | D12: Proposta Enviada | F12: 8 | G12: =INDEX(Base!$D$2:$D$601,MATCH(B12,Base!$A$2:$A$601,0)) -> Autônomo | H12: =INDEX(Base!$C$2:$C$601,MATCH(B12,Base!$A$2:$A$601,0)) -> Sudeste | I12: =INDEX(Base!$M$2:$M$601,MATCH(B12,Base!$A$2:$A$601,0)) -> 0 | J12: =IF(OR(D12="Ganho",D12="Perdido"),1,0) -> 0 | K12: =IF(D12="Ganho",1,0) -> 0 | L12: =IF(INDEX(Base!$U$2:$U$601,MATCH(B12,Base!$A$2:$A$601,0))="","",INDEX(Base!$U$2:$U$601,MATCH(B12,Base!$A$2:$A$601,0))) -> Baixa | M12: =INDEX(Base!$R$2:$R$601,MATCH(B12,Base!$A$2:$A$601,0)) -> 0 | N12: =INDEX(Base!$AB$2:$AB$601,MATCH(B12,Base!$A$2:$A$601,0)) -> Baixa | O12: 119
A13: LEAD00012 | B13: CTD00431 | C13: Indicação | D13: Em Contato | F13: 10 | G13: =INDEX(Base!$D$2:$D$601,MATCH(B13,Base!$A$2:$A$601,0)) -> Grande Escritório | H13: =INDEX(Base!$C$2:$C$601,MATCH(B13,Base!$A$2:$A$601,0)) -> Sudeste | I13: =INDEX(Base!$M$2:$M$601,MATCH(B13,Base!$A$2:$A$601,0)) -> 1 | J13: =IF(OR(D13="Ganho",D13="Perdido"),1,0) -> 0 | K13: =IF(D13="Ganho",1,0) -> 0 | L13: =IF(INDEX(Base!$U$2:$U$601,MATCH(B13,Base!$A$2:$A$601,0))="","",INDEX(Base!$U$2:$U$601,MATCH(B13,Base!$A$2:$A$601,0))) | M13: =INDEX(Base!$R$2:$R$601,MATCH(B13,Base!$A$2:$A$601,0)) -> 1 | N13: =INDEX(Base!$AB$2:$AB$601,MATCH(B13,Base!$A$2:$A$601,0)) -> Alta | O13: 113
A14: LEAD00013 | B14: CTD00347 | C14: Franquia | D14: Proposta Enviada | F14: 7 | G14: =INDEX(Base!$D$2:$D$601,MATCH(B14,Base!$A$2:$A$601,0)) -> Grande Escritório | H14: =INDEX(Base!$C$2:$C$601,MATCH(B14,Base!$A$2:$A$601,0)) -> Norte | I14: =INDEX(Base!$M$2:$M$601,MATCH(B14,Base!$A$2:$A$601,0)) -> 1 | J14: =IF(OR(D14="Ganho",D14="Perdido"),1,0) -> 0 | K14: =IF(D14="Ganho",1,0) -> 0 | L14: =IF(INDEX(Base!$U$2:$U$601,MATCH(B14,Base!$A$2:$A$601,0))="","",INDEX(Base!$U$2:$U$601,MATCH(B14,Base!$A$2:$A$601,0))) | M14: =INDEX(Base!$R$2:$R$601,MATCH(B14,Base!$A$2:$A$601,0)) -> 1 | N14: =INDEX(Base!$AB$2:$AB$601,MATCH(B14,Base!$A$2:$A$601,0)) -> Alta | O14: 166
A15: LEAD00014 | B15: CTD00356 | C15: Inbound | D15: Proposta Enviada | F15: 8 | G15: =INDEX(Base!$D$2:$D$601,MATCH(B15,Base!$A$2:$A$601,0)) -> Pequeno Escritório | H15: =INDEX(Base!$C$2:$C$601,MATCH(B15,Base!$A$2:$A$601,0)) -> Sudeste | I15: =INDEX(Base!$M$2:$M$601,MATCH(B15,Base!$A$2:$A$601,0)) -> 1 | J15: =IF(OR(D15="Ganho",D15="Perdido"),1,0) -> 0 | K15: =IF(D15="Ganho",1,0) -> 0 | L15: =IF(INDEX(Base!$U$2:$U$601,MATCH(B15,Base!$A$2:$A$601,0))="","",INDEX(Base!$U$2:$U$601,MATCH(B15,Base!$A$2:$A$601,0))) | M15: =INDEX(Base!$R$2:$R$601,MATCH(B15,Base!$A$2:$A$601,0)) -> 0 | N15: =INDEX(Base!$AB$2:$AB$601,MATCH(B15,Base!$A$2:$A$601,0)) -> Média | O15: 178
... A20: LEAD00019 | B20: CTD00209 | C20: Franquia | D20: Proposta Enviada | F20: 9 | G20: =INDEX(Base!$D$2:$D$601,MATCH(B20,Base!$A$2:$A$601,0)) -> Autônomo | H20: =INDEX(Base!$C$2:$C$601,MATCH(B20,Base!$A$2:$A$601,0)) -> Sudeste | I20: =INDEX(Base!$M$2:$M$601,MATCH(B20,Base!$A$2:$A$601,0)) -> 0 | J20: =IF(OR(D20="Ganho",D20="Perdido"),1,0) -> 0 | K20: =IF(D20="Ganho",1,0) -> 0 | L20: =IF(INDEX(Base!$U$2:$U$601,MATCH(B20,Base!$A$2:$A$601,0))="","",INDEX(Base!$U$2:$U$601,MATCH(B20,Base!$A$2:$A$601,0))) -> Baixa | M20: =INDEX(Base!$R$2:$R$601,MATCH(B20,Base!$A$2:$A$601,0)) -> 0 | N20: =INDEX(Base!$AB$2:$AB$601,MATCH(B20,Base!$A$2:$A$601,0)) -> Baixa | O20: 113
A21: LEAD00020 | B21: CTD00046 | C21: Inbound | D21: Ganho | E21: 1491.16 | F21: 6 | G21: =INDEX(Base!$D$2:$D$601,MATCH(B21,Base!$A$2:$A$601,0)) -> Grande Escritório | H21: =INDEX(Base!$C$2:$C$601,MATCH(B21,Base!$A$2:$A$601,0)) -> Sudeste | I21: =INDEX(Base!$M$2:$M$601,MATCH(B21,Base!$A$2:$A$601,0)) -> 1 | J21: =IF(OR(D21="Ganho",D21="Perdido"),1,0) -> 1 | K21: =IF(D21="Ganho",1,0) -> 1 | L21: =IF(INDEX(Base!$U$2:$U$601,MATCH(B21,Base!$A$2:$A$601,0))="","",INDEX(Base!$U$2:$U$601,MATCH(B21,Base!$A$2:$A$601,0))) | M21: =INDEX(Base!$R$2:$R$601,MATCH(B21,Base!$A$2:$A$601,0)) -> 1 | N21: =INDEX(Base!$AB$2:$AB$601,MATCH(B21,Base!$A$2:$A$601,0)) -> Alta | O21: 72 | P21: 45839
A22: LEAD00021 | B22: CTD00495 | C22: Franquia | D22: Novo | F22: 12 | G22: =INDEX(Base!$D$2:$D$601,MATCH(B22,Base!$A$2:$A$601,0)) -> Pequeno Escritório | H22: =INDEX(Base!$C$2:$C$601,MATCH(B22,Base!$A$2:$A$601,0)) -> Sudeste | I22: =INDEX(Base!$M$2:$M$601,MATCH(B22,Base!$A$2:$A$601,0)) -> 0 | J22: =IF(OR(D22="Ganho",D22="Perdido"),1,0) -> 0 | K22: =IF(D22="Ganho",1,0) -> 0 | L22: =IF(INDEX(Base!$U$2:$U$601,MATCH(B22,Base!$A$2:$A$601,0))="","",INDEX(Base!$U$2:$U$601,MATCH(B22,Base!$A$2:$A$601,0))) | M22: =INDEX(Base!$R$2:$R$601,MATCH(B22,Base!$A$2:$A$601,0)) -> 1 | N22: =INDEX(Base!$AB$2:$AB$601,MATCH(B22,Base!$A$2:$A$601,0)) -> Média | O22: 174
A23: LEAD00022 | B23: CTD00303 | C23: Inbound | D23: Perdido | F23: 2 | G23: =INDEX(Base!$D$2:$D$601,MATCH(B23,Base!$A$2:$A$601,0)) -> Pequeno Escritório | H23: =INDEX(Base!$C$2:$C$601,MATCH(B23,Base!$A$2:$A$601,0)) -> Nordeste | I23: =INDEX(Base!$M$2:$M$601,MATCH(B23,Base!$A$2:$A$601,0)) -> 0 | J23: =IF(OR(D23="Ganho",D23="Perdido"),1,0) -> 1 | K23: =IF(D23="Ganho",1,0) -> 0 | L23: =IF(INDEX(Base!$U$2:$U$601,MATCH(B23,Base!$A$2:$A$601,0))="","",INDEX(Base!$U$2:$U$601,MATCH(B23,Base!$A$2:$A$601,0))) -> Média | M23: =INDEX(Base!$R$2:$R$601,MATCH(B23,Base!$A$2:$A$601,0)) -> 0 | N23: =INDEX(Base!$AB$2:$AB$601,MATCH(B23,Base!$A$2:$A$601,0)) -> Alta | O23: 111
A24: LEAD00023 | B24: CTD00180 | C24: Indicação | D24: Em Contato | F24: 12 | G24: =INDEX(Base!$D$2:$D$601,MATCH(B24,Base!$A$2:$A$601,0)) -> Autônomo | H24: =INDEX(Base!$C$2:$C$601,MATCH(B24,Base!$A$2:$A$601,0)) -> Sudeste | I24: =INDEX(Base!$M$2:$M$601,MATCH(B24,Base!$A$2:$A$601,0)) -> 0 | J24: =IF(OR(D24="Ganho",D24="Perdido"),1,0) -> 0 | K24: =IF(D24="Ganho",1,0) -> 0 | L24: =IF(INDEX(Base!$U$2:$U$601,MATCH(B24,Base!$A$2:$A$601,0))="","",INDEX(Base!$U$2:$U$601,MATCH(B24,Base!$A$2:$A$601,0))) -> Baixa | M24: =INDEX(Base!$R$2:$R$601,MATCH(B24,Base!$A$2:$A$601,0)) -> 0 | N24: =INDEX(Base!$AB$2:$AB$601,MATCH(B24,Base!$A$2:$A$601,0)) -> Baixa | O24: 121
A25: LEAD00024 | B25: CTD00399 | C25: Outreach Ativo | D25: Ganho | E25: 713.2 | F25: 3 | G25: =INDEX(Base!$D$2:$D$601,MATCH(B25,Base!$A$2:$A$601,0)) -> Pequeno Escritório | H25: =INDEX(Base!$C$2:$C$601,MATCH(B25,Base!$A$2:$A$601,0)) -> Sul | I25: =INDEX(Base!$M$2:$M$601,MATCH(B25,Base!$A$2:$A$601,0)) -> 1 | J25: =IF(OR(D25="Ganho",D25="Perdido"),1,0) -> 1 | K25: =IF(D25="Ganho",1,0) -> 1 | L25: =IF(INDEX(Base!$U$2:$U$601,MATCH(B25,Base!$A$2:$A$601,0))="","",INDEX(Base!$U$2:$U$601,MATCH(B25,Base!$A$2:$A$601,0))) | M25: =INDEX(Base!$R$2:$R$601,MATCH(B25,Base!$A$2:$A$601,0)) -> 0 | N25: =INDEX(Base!$AB$2:$AB$601,MATCH(B25,Base!$A$2:$A$601,0)) -> Alta | O25: 33 | P25: 45785
A26: LEAD00025 | B26: CTD00189 | C26: Franquia | D26: Em Contato | F26: 11 | G26: =INDEX(Base!$D$2:$D$601,MATCH(B26,Base!$A$2:$A$601,0)) -> Pequeno Escritório | H26: =INDEX(Base!$C$2:$C$601,MATCH(B26,Base!$A$2:$A$601,0)) -> Sudeste | I26: =INDEX(Base!$M$2:$M$601,MATCH(B26,Base!$A$2:$A$601,0)) -> 0 | J26: =IF(OR(D26="Ganho",D26="Perdido"),1,0) -> 0 | K26: =IF(D26="Ganho",1,0) -> 0 | L26: =IF(INDEX(Base!$U$2:$U$601,MATCH(B26,Base!$A$2:$A$601,0))="","",INDEX(Base!$U$2:$U$601,MATCH(B26,Base!$A$2:$A$601,0))) -> Média | M26: =INDEX(Base!$R$2:$R$601,MATCH(B26,Base!$A$2:$A$601,0)) -> 0 | N26: =INDEX(Base!$AB$2:$AB$601,MATCH(B26,Base!$A$2:$A$601,0)) -> Média | O26: 32
A27: LEAD00026 | B27: CTD00249 | C27: Inbound | D27: Novo | F27: 2 | G27: =INDEX(Base!$D$2:$D$601,MATCH(B27,Base!$A$2:$A$601,0)) -> Médio Escritório | H27: =INDEX(Base!$C$2:$C$601,MATCH(B27,Base!$A$2:$A$601,0)) -> Centro-Oeste | I27: =INDEX(Base!$M$2:$M$601,MATCH(B27,Base!$A$2:$A$601,0)) -> 1 | J27: =IF(OR(D27="Ganho",D27="Perdido"),1,0) -> 0 | K27: =IF(D27="Ganho",1,0) -> 0 | L27: =IF(INDEX(Base!$U$2:$U$601,MATCH(B27,Base!$A$2:$A$601,0))="","",INDEX(Base!$U$2:$U$601,MATCH(B27,Base!$A$2:$A$601,0))) | M27: =INDEX(Base!$R$2:$R$601,MATCH(B27,Base!$A$2:$A$601,0)) -> 1 | N27: =INDEX(Base!$AB$2:$AB$601,MATCH(B27,Base!$A$2:$A$601,0)) -> Alta | O27: 8
A28: LEAD00027 | B28: CTD00151 | C28: Franquia | D28: Ganho | E28: 1743.58 | F28: 10 | G28: =INDEX(Base!$D$2:$D$601,MATCH(B28,Base!$A$2:$A$601,0)) -> Pequeno Escritório | H28: =INDEX(Base!$C$2:$C$601,MATCH(B28,Base!$A$2:$A$601,0)) -> Norte | I28: =INDEX(Base!$M$2:$M$601,MATCH(B28,Base!$A$2:$A$601,0)) -> 0 | J28: =IF(OR(D28="Ganho",D28="Perdido"),1,0) -> 1 | K28: =IF(D28="Ganho",1,0) -> 1 | L28: =IF(INDEX(Base!$U$2:$U$601,MATCH(B28,Base!$A$2:$A$601,0))="","",INDEX(Base!$U$2:$U$601,MATCH(B28,Base!$A$2:$A$601,0))) -> Média | M28: =INDEX(Base!$R$2:$R$601,MATCH(B28,Base!$A$2:$A$601,0)) -> 0 | N28: =INDEX(Base!$AB$2:$AB$601,MATCH(B28,Base!$A$2:$A$601,0)) -> Média | O28: 84 | P28: 45847
A29: LEAD00028 | B29: CTD00310 | C29: Outreach Ativo | D29: Proposta Enviada | F29: 10 | G29: =INDEX(Base!$D$2:$D$601,MATCH(B29,Base!$A$2:$A$601,0)) -> Pequeno Escritório | H29: =INDEX(Base!$C$2:$C$601,MATCH(B29,Base!$A$2:$A$601,0)) -> Nordeste | I29: =INDEX(Base!$M$2:$M$601,MATCH(B29,Base!$A$2:$A$601,0)) -> 0 | J29: =IF(OR(D29="Ganho",D29="Perdido"),1,0) -> 0 | K29: =IF(D29="Ganho",1,0) -> 0 | L29: =IF(INDEX(Base!$U$2:$U$601,MATCH(B29,Base!$A$2:$A$601,0))="","",INDEX(Base!$U$2:$U$601,MATCH(B29,Base!$A$2:$A$601,0))) -> Média | M29: =INDEX(Base!$R$2:$R$601,MATCH(B29,Base!$A$2:$A$601,0)) -> 0 | N29: =INDEX(Base!$AB$2:$AB$601,MATCH(B29,Base!$A$2:$A$601,0)) -> Média | O29: 97
A30: LEAD00029 | B30: CTD00403 | C30: Outreach Ativo | D30: Ganho | E30: 294.6 | F30: 3 | G30: =INDEX(Base!$D$2:$D$601,MATCH(B30,Base!$A$2:$A$601,0)) -> Pequeno Escritório | H30: =INDEX(Base!$C$2:$C$601,MATCH(B30,Base!$A$2:$A$601,0)) -> Sudeste | I30: =INDEX(Base!$M$2:$M$601,MATCH(B30,Base!$A$2:$A$601,0)) -> 0 | J30: =IF(OR(D30="Ganho",D30="Perdido"),1,0) -> 1 | K30: =IF(D30="Ganho",1,0) -> 1 | L30: =IF(INDEX(Base!$U$2:$U$601,MATCH(B30,Base!$A$2:$A$601,0))="","",INDEX(Base!$U$2:$U$601,MATCH(B30,Base!$A$2:$A$601,0))) -> Baixa | M30: =INDEX(Base!$R$2:$R$601,MATCH(B30,Base!$A$2:$A$601,0)) -> 0 | N30: =INDEX(Base!$AB$2:$AB$601,MATCH(B30,Base!$A$2:$A$601,0)) -> Média | O30: 38 | P30: 46036
A31: LEAD00030 | B31: CTD00329 | C31: Franquia | D31: Ganho | E31: 1567.37 | F31: 4 | G31: =INDEX(Base!$D$2:$D$601,MATCH(B31,Base!$A$2:$A$601,0)) -> Autônomo | H31: =INDEX(Base!$C$2:$C$601,MATCH(B31,Base!$A$2:$A$601,0)) -> Centro-Oeste | I31: =INDEX(Base!$M$2:$M$601,MATCH(B31,Base!$A$2:$A$601,0)) -> 0 | J31: =IF(OR(D31="Ganho",D31="Perdido"),1,0) -> 1 | K31: =IF(D31="Ganho",1,0) -> 1 | L31: =IF(INDEX(Base!$U$2:$U$601,MATCH(B31,Base!$A$2:$A$601,0))="","",INDEX(Base!$U$2:$U$601,MATCH(B31,Base!$A$2:$A$601,0))) -> Baixa | M31: =INDEX(Base!$R$2:$R$601,MATCH(B31,Base!$A$2:$A$601,0)) -> 0 | N31: =INDEX(Base!$AB$2:$AB$601,MATCH(B31,Base!$A$2:$A$601,0)) -> Média | O31: 24 | P31: 45332
A32: LEAD00031 | B32: CTD00529 | C32: Inbound | D32: Ganho | E32: 1539.45 | F32: 9 | G32: =INDEX(Base!$D$2:$D$601,MATCH(B32,Base!$A$2:$A$601,0)) -> Autônomo | H32: =INDEX(Base!$C$2:$C$601,MATCH(B32,Base!$A$2:$A$601,0)) -> Sudeste | I32: =INDEX(Base!$M$2:$M$601,MATCH(B32,Base!$A$2:$A$601,0)) -> 0 | J32: =IF(OR(D32="Ganho",D32="Perdido"),1,0) -> 1 | K32: =IF(D32="Ganho",1,0) -> 1 | L32: =IF(INDEX(Base!$U$2:$U$601,MATCH(B32,Base!$A$2:$A$601,0))="","",INDEX(Base!$U$2:$U$601,MATCH(B32,Base!$A$2:$A$601,0))) -> Baixa | M32: =INDEX(Base!$R$2:$R$601,MATCH(B32,Base!$A$2:$A$601,0)) -> 0 | N32: =INDEX(Base!$AB$2:$AB$601,MATCH(B32,Base!$A$2:$A$601,0)) -> Baixa | O32: 55 | P32: 45495
A33: LEAD00032 | B33: CTD00377 | C33: Franquia | D33: Novo | F33: 7 | G33: =INDEX(Base!$D$2:$D$601,MATCH(B33,Base!$A$2:$A$601,0)) -> Pequeno Escritório | H33: =INDEX(Base!$C$2:$C$601,MATCH(B33,Base!$A$2:$A$601,0)) -> Centro-Oeste | I33: =INDEX(Base!$M$2:$M$601,MATCH(B33,Base!$A$2:$A$601,0)) -> 1 | J33: =IF(OR(D33="Ganho",D33="Perdido"),1,0) -> 0 | K33: =IF(D33="Ganho",1,0) -> 0 | L33: =IF(INDEX(Base!$U$2:$U$601,MATCH(B33,Base!$A$2:$A$601,0))="","",INDEX(Base!$U$2:$U$601,MATCH(B33,Base!$A$2:$A$601,0))) | M33: =INDEX(Base!$R$2:$R$601,MATCH(B33,Base!$A$2:$A$601,0)) -> 0 | N33: =INDEX(Base!$AB$2:$AB$601,MATCH(B33,Base!$A$2:$A$601,0)) -> Média | O33: 10
A34: LEAD00033 | B34: CTD00310 | C34: Franquia | D34: Ganho | E34: 1740.38 | F34: 8 | G34: =INDEX(Base!$D$2:$D$601,MATCH(B34,Base!$A$2:$A$601,0)) -> Pequeno Escritório | H34: =INDEX(Base!$C$2:$C$601,MATCH(B34,Base!$A$2:$A$601,0)) -> Nordeste | I34: =INDEX(Base!$M$2:$M$601,MATCH(B34,Base!$A$2:$A$601,0)) -> 0 | J34: =IF(OR(D34="Ganho",D34="Perdido"),1,0) -> 1 | K34: =IF(D34="Ganho",1,0) -> 1 | L34: =IF(INDEX(Base!$U$2:$U$601,MATCH(B34,Base!$A$2:$A$601,0))="","",INDEX(Base!$U$2:$U$601,MATCH(B34,Base!$A$2:$A$601,0))) -> Média | M34: =INDEX(Base!$R$2:$R$601,MATCH(B34,Base!$A$2:$A$601,0)) -> 0 | N34: =INDEX(Base!$AB$2:$AB$601,MATCH(B34,Base!$A$2:$A$601,0)) -> Média | O34: 56 | P34: 45504
A35: LEAD00034 | B35: CTD00112 | C35: Franquia | D35: Em Contato | F35: 5 | G35: =INDEX(Base!$D$2:$D$601,MATCH(B35,Base!$A$2:$A$601,0)) -> Médio Escritório | H35: =INDEX(Base!$C$2:$C$601,MATCH(B35,Base!$A$2:$A$601,0)) -> Sudeste | I35: =INDEX(Base!$M$2:$M$601,MATCH(B35,Base!$A$2:$A$601,0)) -> 1 | J35: =IF(OR(D35="Ganho",D35="Perdido"),1,0) -> 0 | K35: =IF(D35="Ganho",1,0) -> 0 | L35: =IF(INDEX(Base!$U$2:$U$601,MATCH(B35,Base!$A$2:$A$601,0))="","",INDEX(Base!$U$2:$U$601,MATCH(B35,Base!$A$2:$A$601,0))) | M35: =INDEX(Base!$R$2:$R$601,MATCH(B35,Base!$A$2:$A$601,0)) -> 1 | N35: =INDEX(Base!$AB$2:$AB$601,MATCH(B35,Base!$A$2:$A$601,0)) -> Alta | O35: 150
A36: LEAD00035 | B36: CTD00300 | C36: Outreach Ativo | D36: Novo | F36: 1 | G36: =INDEX(Base!$D$2:$D$601,MATCH(B36,Base!$A$2:$A$601,0)) -> Autônomo | H36: =INDEX(Base!$C$2:$C$601,MATCH(B36,Base!$A$2:$A$601,0)) -> Nordeste | I36: =INDEX(Base!$M$2:$M$601,MATCH(B36,Base!$A$2:$A$601,0)) -> 0 | J36: =IF(OR(D36="Ganho",D36="Perdido"),1,0) -> 0 | K36: =IF(D36="Ganho",1,0) -> 0 | L36: =IF(INDEX(Base!$U$2:$U$601,MATCH(B36,Base!$A$2:$A$601,0))="","",INDEX(Base!$U$2:$U$601,MATCH(B36,Base!$A$2:$A$601,0))) | M36: =INDEX(Base!$R$2:$R$601,MATCH(B36,Base!$A$2:$A$601,0)) -> 0 | N36: =INDEX(Base!$AB$2:$AB$601,MATCH(B36,Base!$A$2:$A$601,0)) -> Baixa | O36: 31
A37: LEAD00036 | B37: CTD00397 | C37: Inbound | D37: Reunião Agendada | F37: 7 | G37: =INDEX(Base!$D$2:$D$601,MATCH(B37,Base!$A$2:$A$601,0)) -> Pequeno Escritório | H37: =INDEX(Base!$C$2:$C$601,MATCH(B37,Base!$A$2:$A$601,0)) -> Sudeste | I37: =INDEX(Base!$M$2:$M$601,MATCH(B37,Base!$A$2:$A$601,0)) -> 1 | J37: =IF(OR(D37="Ganho",D37="Perdido"),1,0) -> 0 | K37: =IF(D37="Ganho",1,0) -> 0 | L37: =IF(INDEX(Base!$U$2:$U$601,MATCH(B37,Base!$A$2:$A$601,0))="","",INDEX(Base!$U$2:$U$601,MATCH(B37,Base!$A$2:$A$601,0))) | M37: =INDEX(Base!$R$2:$R$601,MATCH(B37,Base!$A$2:$A$601,0)) -> 0 | N37: =INDEX(Base!$AB$2:$AB$601,MATCH(B37,Base!$A$2:$A$601,0)) -> Média | O37: 131
A38: LEAD00037 | B38: CTD00495 | C38: Outreach Ativo | D38: Ganho | E38: 211.08 | F38: 7 | G38: =INDEX(Base!$D$2:$D$601,MATCH(B38,Base!$A$2:$A$601,0)) -> Pequeno Escritório | H38: =INDEX(Base!$C$2:$C$601,MATCH(B38,Base!$A$2:$A$601,0)) -> Sudeste | I38: =INDEX(Base!$M$2:$M$601,MATCH(B38,Base!$A$2:$A$601,0)) -> 0 | J38: =IF(OR(D38="Ganho",D38="Perdido"),1,0) -> 1 | K38: =IF(D38="Ganho",1,0) -> 1 | L38: =IF(INDEX(Base!$U$2:$U$601,MATCH(B38,Base!$A$2:$A$601,0))="","",INDEX(Base!$U$2:$U$601,MATCH(B38,Base!$A$2:$A$601,0))) | M38: =INDEX(Base!$R$2:$R$601,MATCH(B38,Base!$A$2:$A$601,0)) -> 1 | N38: =INDEX(Base!$AB$2:$AB$601,MATCH(B38,Base!$A$2:$A$601,0)) -> Média | O38: 37 | P38: 45939
A39: LEAD00038 | B39: CTD00563 | C39: Inbound | D39: Ganho | E39: 1643.37 | F39: 8 | G39: =INDEX(Base!$D$2:$D$601,MATCH(B39,Base!$A$2:$A$601,0)) -> Autônomo | H39: =INDEX(Base!$C$2:$C$601,MATCH(B39,Base!$A$2:$A$601,0)) -> Sul | I39: =INDEX(Base!$M$2:$M$601,MATCH(B39,Base!$A$2:$A$601,0)) -> 0 | J39: =IF(OR(D39="Ganho",D39="Perdido"),1,0) -> 1 | K39: =IF(D39="Ganho",1,0) -> 1 | L39: =IF(INDEX(Base!$U$2:$U$601,MATCH(B39,Base!$A$2:$A$601,0))="","",INDEX(Base!$U$2:$U$601,MATCH(B39,Base!$A$2:$A$601,0))) | M39: =INDEX(Base!$R$2:$R$601,MATCH(B39,Base!$A$2:$A$601,0)) -> 0 | N39: =INDEX(Base!$AB$2:$AB$601,MATCH(B39,Base!$A$2:$A$601,0)) -> Baixa | O39: 86 | P39: 45983
A40: LEAD00039 | B40: CTD00161 | C40: Franquia | D40: Novo | F40: 10 | G40: =INDEX(Base!$D$2:$D$601,MATCH(B40,Base!$A$2:$A$601,0)) -> Pequeno Escritório | H40: =INDEX(Base!$C$2:$C$601,MATCH(B40,Base!$A$2:$A$601,0)) -> Sudeste | I40: =INDEX(Base!$M$2:$M$601,MATCH(B40,Base!$A$2:$A$601,0)) -> 1 | J40: =IF(OR(D40="Ganho",D40="Perdido"),1,0) -> 0 | K40: =IF(D40="Ganho",1,0) -> 0 | L40: =IF(INDEX(Base!$U$2:$U$601,MATCH(B40,Base!$A$2:$A$601,0))="","",INDEX(Base!$U$2:$U$601,MATCH(B40,Base!$A$2:$A$601,0))) | M40: =INDEX(Base!$R$2:$R$601,MATCH(B40,Base!$A$2:$A$601,0)) -> 0 | N40: =INDEX(Base!$AB$2:$AB$601,MATCH(B40,Base!$A$2:$A$601,0)) -> Média | O40: 85
A41: LEAD00040 | B41: CTD00383 | C41: Inbound | D41: Perdido | F41: 8 | G41: =INDEX(Base!$D$2:$D$601,MATCH(B41,Base!$A$2:$A$601,0)) -> Autônomo | H41: =INDEX(Base!$C$2:$C$601,MATCH(B41,Base!$A$2:$A$601,0)) -> Sudeste | I41: =INDEX(Base!$M$2:$M$601,MATCH(B41,Base!$A$2:$A$601,0)) -> 0 | J41: =IF(OR(D41="Ganho",D41="Perdido"),1,0) -> 1 | K41: =IF(D41="Ganho",1,0) -> 0 | L41: =IF(INDEX(Base!$U$2:$U$601,MATCH(B41,Base!$A$2:$A$601,0))="","",INDEX(Base!$U$2:$U$601,MATCH(B41,Base!$A$2:$A$601,0))) -> Baixa | M41: =INDEX(Base!$R$2:$R$601,MATCH(B41,Base!$A$2:$A$601,0)) -> 0 | N41: =INDEX(Base!$AB$2:$AB$601,MATCH(B41,Base!$A$2:$A$601,0)) -> Baixa | O41: 34
A42: LEAD00041 | B42: CTD00486 | C42: Inbound | D42: Em Contato | F42: 12 | G42: =INDEX(Base!$D$2:$D$601,MATCH(B42,Base!$A$2:$A$601,0)) -> Grande Escritório | H42: =INDEX(Base!$C$2:$C$601,MATCH(B42,Base!$A$2:$A$601,0)) -> Nordeste | I42: =INDEX(Base!$M$2:$M$601,MATCH(B42,Base!$A$2:$A$601,0)) -> 1 | J42: =IF(OR(D42="Ganho",D42="Perdido"),1,0) -> 0 | K42: =IF(D42="Ganho",1,0) -> 0 | L42: =IF(INDEX(Base!$U$2:$U$601,MATCH(B42,Base!$A$2:$A$601,0))="","",INDEX(Base!$U$2:$U$601,MATCH(B42,Base!$A$2:$A$601,0))) | M42: =INDEX(Base!$R$2:$R$601,MATCH(B42,Base!$A$2:$A$601,0)) -> 1 | N42: =INDEX(Base!$AB$2:$AB$601,MATCH(B42,Base!$A$2:$A$601,0)) -> Alta | O42: 116
A43: LEAD00042 | B43: CTD00512 | C43: Franquia | D43: Reunião Agendada | F43: 8 | G43: =INDEX(Base!$D$2:$D$601,MATCH(B43,Base!$A$2:$A$601,0)) -> Autônomo | H43: =INDEX(Base!$C$2:$C$601,MATCH(B43,Base!$A$2:$A$601,0)) -> Sudeste | I43: =INDEX(Base!$M$2:$M$601,MATCH(B43,Base!$A$2:$A$601,0)) -> 0 | J43: =IF(OR(D43="Ganho",D43="Perdido"),1,0) -> 0 | K43: =IF(D43="Ganho",1,0) -> 0 | L43: =IF(INDEX(Base!$U$2:$U$601,MATCH(B43,Base!$A$2:$A$601,0))="","",INDEX(Base!$U$2:$U$601,MATCH(B43,Base!$A$2:$A$601,0))) -> Média | M43: =INDEX(Base!$R$2:$R$601,MATCH(B43,Base!$A$2:$A$601,0)) -> 0 | N43: =INDEX(Base!$AB$2:$AB$601,MATCH(B43,Base!$A$2:$A$601,0)) -> Baixa | O43: 64
A44: LEAD00043 | B44: CTD00545 | C44: Inbound | D44: Perdido | F44: 10 | G44: =INDEX(Base!$D$2:$D$601,MATCH(B44,Base!$A$2:$A$601,0)) -> Pequeno Escritório | H44: =INDEX(Base!$C$2:$C$601,MATCH(B44,Base!$A$2:$A$601,0)) -> Sudeste | I44: =INDEX(Base!$M$2:$M$601,MATCH(B44,Base!$A$2:$A$601,0)) -> 0 | J44: =IF(OR(D44="Ganho",D44="Perdido"),1,0) -> 1 | K44: =IF(D44="Ganho",1,0) -> 0 | L44: =IF(INDEX(Base!$U$2:$U$601,MATCH(B44,Base!$A$2:$A$601,0))="","",INDEX(Base!$U$2:$U$601,MATCH(B44,Base!$A$2:$A$601,0))) -> Média | M44: =INDEX(Base!$R$2:$R$601,MATCH(B44,Base!$A$2:$A$601,0)) -> 0 | N44: =INDEX(Base!$AB$2:$AB$601,MATCH(B44,Base!$A$2:$A$601,0)) -> Média | O44: 173
A45: LEAD00044 | B45: CTD00561 | C45: Inbound | D45: Ganho | E45: 1733.68 | F45: 11 | G45: =INDEX(Base!$D$2:$D$601,MATCH(B45,Base!$A$2:$A$601,0)) -> Pequeno Escritório | H45: =INDEX(Base!$C$2:$C$601,MATCH(B45,Base!$A$2:$A$601,0)) -> Sudeste | I45: =INDEX(Base!$M$2:$M$601,MATCH(B45,Base!$A$2:$A$601,0)) -> 1 | J45: =IF(OR(D45="Ganho",D45="Perdido"),1,0) -> 1 | K45: =IF(D45="Ganho",1,0) -> 1 | L45: =IF(INDEX(Base!$U$2:$U$601,MATCH(B45,Base!$A$2:$A$601,0))="","",INDEX(Base!$U$2:$U$601,MATCH(B45,Base!$A$2:$A$601,0))) | M45: =INDEX(Base!$R$2:$R$601,MATCH(B45,Base!$A$2:$A$601,0)) -> 0 | N45: =INDEX(Base!$AB$2:$AB$601,MATCH(B45,Base!$A$2:$A$601,0)) -> Média | O45: 49 | P45: 45641
A46: LEAD00045 | B46: CTD00436 | C46: Outreach Ativo | D46: Ganho | E46: 1176.04 | F46: 5 | G46: =INDEX(Base!$D$2:$D$601,MATCH(B46,Base!$A$2:$A$601,0)) -> Pequeno Escritório | H46: =INDEX(Base!$C$2:$C$601,MATCH(B46,Base!$A$2:$A$601,0)) -> Sudeste | I46: =INDEX(Base!$M$2:$M$601,MATCH(B46,Base!$A$2:$A$601,0)) -> 1 | J46: =IF(OR(D46="Ganho",D46="Perdido"),1,0) -> 1 | K46: =IF(D46="Ganho",1,0) -> 1 | L46: =IF(INDEX(Base!$U$2:$U$601,MATCH(B46,Base!$A$2:$A$601,0))="","",INDEX(Base!$U$2:$U$601,MATCH(B46,Base!$A$2:$A$601,0))) | M46: =INDEX(Base!$R$2:$R$601,MATCH(B46,Base!$A$2:$A$601,0)) -> 0 | N46: =INDEX(Base!$AB$2:$AB$601,MATCH(B46,Base!$A$2:$A$601,0)) -> Alta | O46: 20 | P46: 45680
A47: LEAD00046 | B47: CTD00036 | C47: Outreach Ativo | D47: Ganho | E47: 435.93 | F47: 3 | G47: =INDEX(Base!$D$2:$D$601,MATCH(B47,Base!$A$2:$A$601,0)) -> Autônomo | H47: =INDEX(Base!$C$2:$C$601,MATCH(B47,Base!$A$2:$A$601,0)) -> Sul | I47: =INDEX(Base!$M$2:$M$601,MATCH(B47,Base!$A$2:$A$601,0)) -> 0 | J47: =IF(OR(D47="Ganho",D47="Perdido"),1,0) -> 1 | K47: =IF(D47="Ganho",1,0) -> 1 | L47: =IF(INDEX(Base!$U$2:$U$601,MATCH(B47,Base!$A$2:$A$601,0))="","",INDEX(Base!$U$2:$U$601,MATCH(B47,Base!$A$2:$A$601,0))) -> Baixa | M47: =INDEX(Base!$R$2:$R$601,MATCH(B47,Base!$A$2:$A$601,0)) -> 0 | N47: =INDEX(Base!$AB$2:$AB$601,MATCH(B47,Base!$A$2:$A$601,0)) -> Média | O47: 16 | P47: 45396
A48: LEAD00047 | B48: CTD00121 | C48: Inbound | D48: Ganho | E48: 651.03 | F48: 4 | G48: =INDEX(Base!$D$2:$D$601,MATCH(B48,Base!$A$2:$A$601,0)) -> Médio Escritório | H48: =INDEX(Base!$C$2:$C$601,MATCH(B48,Base!$A$2:$A$601,0)) -> Centro-Oeste | I48: =INDEX(Base!$M$2:$M$601,MATCH(B48,Base!$A$2:$A$601,0)) -> 1 | J48: =IF(OR(D48="Ganho",D48="Perdido"),1,0) -> 1 | K48: =IF(D48="Ganho",1,0) -> 1 | L48: =IF(INDEX(Base!$U$2:$U$601,MATCH(B48,Base!$A$2:$A$601,0))="","",INDEX(Base!$U$2:$U$601,MATCH(B48,Base!$A$2:$A$601,0))) | M48: =INDEX(Base!$R$2:$R$601,MATCH(B48,Base!$A$2:$A$601,0)) -> 1 | N48: =INDEX(Base!$AB$2:$AB$601,MATCH(B48,Base!$A$2:$A$601,0)) -> Alta | O48: 63 | P48: 45458
A49: LEAD00048 | B49: CTD00278 | C49: Inbound | D49: Reunião Agendada | F49: 5 | G49: =INDEX(Base!$D$2:$D$601,MATCH(B49,Base!$A$2:$A$601,0)) -> Autônomo | H49: =INDEX(Base!$C$2:$C$601,MATCH(B49,Base!$A$2:$A$601,0)) -> Sul | I49: =INDEX(Base!$M$2:$M$601,MATCH(B49,Base!$A$2:$A$601,0)) -> 1 | J49: =IF(OR(D49="Ganho",D49="Perdido"),1,0) -> 0 | K49: =IF(D49="Ganho",1,0) -> 0 | L49: =IF(INDEX(Base!$U$2:$U$601,MATCH(B49,Base!$A$2:$A$601,0))="","",INDEX(Base!$U$2:$U$601,MATCH(B49,Base!$A$2:$A$601,0))) | M49: =INDEX(Base!$R$2:$R$601,MATCH(B49,Base!$A$2:$A$601,0)) -> 0 | N49: =INDEX(Base!$AB$2:$AB$601,MATCH(B49,Base!$A$2:$A$601,0)) -> Média | O49: 96
A50: LEAD00049 | B50: CTD00145 | C50: Outreach Ativo | D50: Perdido | F50: 1 | G50: =INDEX(Base!$D$2:$D$601,MATCH(B50,Base!$A$2:$A$601,0)) -> Autônomo | H50: =INDEX(Base!$C$2:$C$601,MATCH(B50,Base!$A$2:$A$601,0)) -> Sudeste | I50: =INDEX(Base!$M$2:$M$601,MATCH(B50,Base!$A$2:$A$601,0)) -> 0 | J50: =IF(OR(D50="Ganho",D50="Perdido"),1,0) -> 1 | K50: =IF(D50="Ganho",1,0) -> 0 | L50: =IF(INDEX(Base!$U$2:$U$601,MATCH(B50,Base!$A$2:$A$601,0))="","",INDEX(Base!$U$2:$U$601,MATCH(B50,Base!$A$2:$A$601,0))) -> Baixa | M50: =INDEX(Base!$R$2:$R$601,MATCH(B50,Base!$A$2:$A$601,0)) -> 0 | N50: =INDEX(Base!$AB$2:$AB$601,MATCH(B50,Base!$A$2:$A$601,0)) -> Baixa | O50: 21
A51: LEAD00050 | B51: CTD00448 | C51: Franquia | D51: Em Contato | F51: 9 | G51: =INDEX(Base!$D$2:$D$601,MATCH(B51,Base!$A$2:$A$601,0)) -> Pequeno Escritório | H51: =INDEX(Base!$C$2:$C$601,MATCH(B51,Base!$A$2:$A$601,0)) -> Sul | I51: =INDEX(Base!$M$2:$M$601,MATCH(B51,Base!$A$2:$A$601,0)) -> 0 | J51: =IF(OR(D51="Ganho",D51="Perdido"),1,0) -> 0 | K51: =IF(D51="Ganho",1,0) -> 0 | L51: =IF(INDEX(Base!$U$2:$U$601,MATCH(B51,Base!$A$2:$A$601,0))="","",INDEX(Base!$U$2:$U$601,MATCH(B51,Base!$A$2:$A$601,0))) -> Alta | M51: =INDEX(Base!$R$2:$R$601,MATCH(B51,Base!$A$2:$A$601,0)) -> 1 | N51: =INDEX(Base!$AB$2:$AB$601,MATCH(B51,Base!$A$2:$A$601,0)) -> Média | O51: 62
A52: LEAD00051 | B52: CTD00460 | C52: Inbound | D52: Ganho | E52: 1420.66 | F52: 9 | G52: =INDEX(Base!$D$2:$D$601,MATCH(B52,Base!$A$2:$A$601,0)) -> Autônomo | H52: =INDEX(Base!$C$2:$C$601,MATCH(B52,Base!$A$2:$A$601,0)) -> Sudeste | I52: =INDEX(Base!$M$2:$M$601,MATCH(B52,Base!$A$2:$A$601,0)) -> 0 | J52: =IF(OR(D52="Ganho",D52="Perdido"),1,0) -> 1 | K52: =IF(D52="Ganho",1,0) -> 1 | L52: =IF(INDEX(Base!$U$2:$U$601,MATCH(B52,Base!$A$2:$A$601,0))="","",INDEX(Base!$U$2:$U$601,MATCH(B52,Base!$A$2:$A$601,0))) -> Baixa | M52: =INDEX(Base!$R$2:$R$601,MATCH(B52,Base!$A$2:$A$601,0)) -> 0 | N52: =INDEX(Base!$AB$2:$AB$601,MATCH(B52,Base!$A$2:$A$601,0)) -> Baixa | O52: 5 | P52: 45645
A53: LEAD00052 | B53: CTD00507 | C53: Franquia | D53: Perdido | F53: 11 | G53: =INDEX(Base!$D$2:$D$601,MATCH(B53,Base!$A$2:$A$601,0)) -> Médio Escritório | H53: =INDEX(Base!$C$2:$C$601,MATCH(B53,Base!$A$2:$A$601,0)) -> Sudeste | I53: =INDEX(Base!$M$2:$M$601,MATCH(B53,Base!$A$2:$A$601,0)) -> 1 | J53: =IF(OR(D53="Ganho",D53="Perdido"),1,0) -> 1 | K53: =IF(D53="Ganho",1,0) -> 0 | L53: =IF(INDEX(Base!$U$2:$U$601,MATCH(B53,Base!$A$2:$A$601,0))="","",INDEX(Base!$U$2:$U$601,MATCH(B53,Base!$A$2:$A$601,0))) | M53: =INDEX(Base!$R$2:$R$601,MATCH(B53,Base!$A$2:$A$601,0)) -> 1 | N53: =INDEX(Base!$AB$2:$AB$601,MATCH(B53,Base!$A$2:$A$601,0)) -> Alta | O53: 31
A54: LEAD00053 | B54: CTD00247 | C54: Outreach Ativo | D54: Ganho | E54: 1758.19 | F54: 10 | G54: =INDEX(Base!$D$2:$D$601,MATCH(B54,Base!$A$2:$A$601,0)) -> Pequeno Escritório | H54: =INDEX(Base!$C$2:$C$601,MATCH(B54,Base!$A$2:$A$601,0)) -> Sudeste | I54: =INDEX(Base!$M$2:$M$601,MATCH(B54,Base!$A$2:$A$601,0)) -> 0 | J54: =IF(OR(D54="Ganho",D54="Perdido"),1,0) -> 1 | K54: =IF(D54="Ganho",1,0) -> 1 | L54: =IF(INDEX(Base!$U$2:$U$601,MATCH(B54,Base!$A$2:$A$601,0))="","",INDEX(Base!$U$2:$U$601,MATCH(B54,Base!$A$2:$A$601,0))) -> Média | M54: =INDEX(Base!$R$2:$R$601,MATCH(B54,Base!$A$2:$A$601,0)) -> 0 | N54: =INDEX(Base!$AB$2:$AB$601,MATCH(B54,Base!$A$2:$A$601,0)) -> Média | O54: 14 | P54: 45754
A55: LEAD00054 | B55: CTD00517 | C55: Inbound | D55: Perdido | F55: 9 | G55: =INDEX(Base!$D$2:$D$601,MATCH(B55,Base!$A$2:$A$601,0)) -> Pequeno Escritório | H55: =INDEX(Base!$C$2:$C$601,MATCH(B55,Base!$A$2:$A$601,0)) -> Sudeste | I55: =INDEX(Base!$M$2:$M$601,MATCH(B55,Base!$A$2:$A$601,0)) -> 0 | J55: =IF(OR(D55="Ganho",D55="Perdido"),1,0) -> 1 | K55: =IF(D55="Ganho",1,0) -> 0 | L55: =IF(INDEX(Base!$U$2:$U$601,MATCH(B55,Base!$A$2:$A$601,0))="","",INDEX(Base!$U$2:$U$601,MATCH(B55,Base!$A$2:$A$601,0))) -> Média | M55: =INDEX(Base!$R$2:$R$601,MATCH(B55,Base!$A$2:$A$601,0)) -> 0 | N55: =INDEX(Base!$AB$2:$AB$601,MATCH(B55,Base!$A$2:$A$601,0)) -> Média | O55: 31
A56: LEAD00055 | B56: CTD00547 | C56: Franquia | D56: Perdido | F56: 12 | G56: =INDEX(Base!$D$2:$D$601,MATCH(B56,Base!$A$2:$A$601,0)) -> Médio Escritório | H56: =INDEX(Base!$C$2:$C$601,MATCH(B56,Base!$A$2:$A$601,0)) -> Nordeste | I56: =INDEX(Base!$M$2:$M$601,MATCH(B56,Base!$A$2:$A$601,0)) -> 1 | J56: =IF(OR(D56="Ganho",D56="Perdido"),1,0) -> 1 | K56: =IF(D56="Ganho",1,0) -> 0 | L56: =IF(INDEX(Base!$U$2:$U$601,MATCH(B56,Base!$A$2:$A$601,0))="","",INDEX(Base!$U$2:$U$601,MATCH(B56,Base!$A$2:$A$601,0))) | M56: =INDEX(Base!$R$2:$R$601,MATCH(B56,Base!$A$2:$A$601,0)) -> 1 | N56: =INDEX(Base!$AB$2:$AB$601,MATCH(B56,Base!$A$2:$A$601,0)) -> Alta | O56: 79
A57: LEAD00056 | B57: CTD00381 | C57: Outreach Ativo | D57: Proposta Enviada | F57: 2 | G57: =INDEX(Base!$D$2:$D$601,MATCH(B57,Base!$A$2:$A$601,0)) -> Autônomo | H57: =INDEX(Base!$C$2:$C$601,MATCH(B57,Base!$A$2:$A$601,0)) -> Centro-Oeste | I57: =INDEX(Base!$M$2:$M$601,MATCH(B57,Base!$A$2:$A$601,0)) -> 0 | J57: =IF(OR(D57="Ganho",D57="Perdido"),1,0) -> 0 | K57: =IF(D57="Ganho",1,0) -> 0 | L57: =IF(INDEX(Base!$U$2:$U$601,MATCH(B57,Base!$A$2:$A$601,0))="","",INDEX(Base!$U$2:$U$601,MATCH(B57,Base!$A$2:$A$601,0))) -> Alta | M57: =INDEX(Base!$R$2:$R$601,MATCH(B57,Base!$A$2:$A$601,0)) -> 0 | N57: =INDEX(Base!$AB$2:$AB$601,MATCH(B57,Base!$A$2:$A$601,0)) -> Baixa | O57: 44
A58: LEAD00057 | B58: CTD00508 | C58: Inbound | D58: Perdido | F58: 4 | G58: =INDEX(Base!$D$2:$D$601,MATCH(B58,Base!$A$2:$A$601,0)) -> Autônomo | H58: =INDEX(Base!$C$2:$C$601,MATCH(B58,Base!$A$2:$A$601,0)) -> Sudeste | I58: =INDEX(Base!$M$2:$M$601,MATCH(B58,Base!$A$2:$A$601,0)) -> 0 | J58: =IF(OR(D58="Ganho",D58="Perdido"),1,0) -> 1 | K58: =IF(D58="Ganho",1,0) -> 0 | L58: =IF(INDEX(Base!$U$2:$U$601,MATCH(B58,Base!$A$2:$A$601,0))="","",INDEX(Base!$U$2:$U$601,MATCH(B58,Base!$A$2:$A$601,0))) -> Baixa | M58: =INDEX(Base!$R$2:$R$601,MATCH(B58,Base!$A$2:$A$601,0)) -> 0 | N58: =INDEX(Base!$AB$2:$AB$601,MATCH(B58,Base!$A$2:$A$601,0)) -> Baixa | O58: 117
A59: LEAD00058 | B59: CTD00161 | C59: Evento | D59: Em Contato | F59: 8 | G59: =INDEX(Base!$D$2:$D$601,MATCH(B59,Base!$A$2:$A$601,0)) -> Pequeno Escritório | H59: =INDEX(Base!$C$2:$C$601,MATCH(B59,Base!$A$2:$A$601,0)) -> Sudeste | I59: =INDEX(Base!$M$2:$M$601,MATCH(B59,Base!$A$2:$A$601,0)) -> 1 | J59: =IF(OR(D59="Ganho",D59="Perdido"),1,0) -> 0 | K59: =IF(D59="Ganho",1,0) -> 0 | L59: =IF(INDEX(Base!$U$2:$U$601,MATCH(B59,Base!$A$2:$A$601,0))="","",INDEX(Base!$U$2:$U$601,MATCH(B59,Base!$A$2:$A$601,0))) | M59: =INDEX(Base!$R$2:$R$601,MATCH(B59,Base!$A$2:$A$601,0)) -> 0 | N59: =INDEX(Base!$AB$2:$AB$601,MATCH(B59,Base!$A$2:$A$601,0)) -> Média | O59: 92
A60: LEAD00059 | B60: CTD00173 | C60: Franquia | D60: Em Contato | F60: 12 | G60: =INDEX(Base!$D$2:$D$601,MATCH(B60,Base!$A$2:$A$601,0)) -> Médio Escritório | H60: =INDEX(Base!$C$2:$C$601,MATCH(B60,Base!$A$2:$A$601,0)) -> Sudeste | I60: =INDEX(Base!$M$2:$M$601,MATCH(B60,Base!$A$2:$A$601,0)) -> 1 | J60: =IF(OR(D60="Ganho",D60="Perdido"),1,0) -> 0 | K60: =IF(D60="Ganho",1,0) -> 0 | L60: =IF(INDEX(Base!$U$2:$U$601,MATCH(B60,Base!$A$2:$A$601,0))="","",INDEX(Base!$U$2:$U$601,MATCH(B60,Base!$A$2:$A$601,0))) | M60: =INDEX(Base!$R$2:$R$601,MATCH(B60,Base!$A$2:$A$601,0)) -> 1 | N60: =INDEX(Base!$AB$2:$AB$601,MATCH(B60,Base!$A$2:$A$601,0)) -> Alta | O60: 111
A61: LEAD00060 | B61: CTD00097 | C61: Franquia | D61: Em Contato | F61: 9 | G61: =INDEX(Base!$D$2:$D$601,MATCH(B61,Base!$A$2:$A$601,0)) -> Pequeno Escritório | H61: =INDEX(Base!$C$2:$C$601,MATCH(B61,Base!$A$2:$A$601,0)) -> Norte | I61: =INDEX(Base!$M$2:$M$601,MATCH(B61,Base!$A$2:$A$601,0)) -> 0 | J61: =IF(OR(D61="Ganho",D61="Perdido"),1,0) -> 0 | K61: =IF(D61="Ganho",1,0) -> 0 | L61: =IF(INDEX(Base!$U$2:$U$601,MATCH(B61,Base!$A$2:$A$601,0))="","",INDEX(Base!$U$2:$U$601,MATCH(B61,Base!$A$2:$A$601,0))) -> Alta | M61: =INDEX(Base!$R$2:$R$601,MATCH(B61,Base!$A$2:$A$601,0)) -> 1 | N61: =INDEX(Base!$AB$2:$AB$601,MATCH(B61,Base!$A$2:$A$601,0)) -> Média | O61: 112
A62: LEAD00061 | B62: CTD00413 | C62: Outreach Ativo | D62: Perdido | F62: 7 | G62: =INDEX(Base!$D$2:$D$601,MATCH(B62,Base!$A$2:$A$601,0)) -> Autônomo | H62: =INDEX(Base!$C$2:$C$601,MATCH(B62,Base!$A$2:$A$601,0)) -> Centro-Oeste | I62: =INDEX(Base!$M$2:$M$601,MATCH(B62,Base!$A$2:$A$601,0)) -> 0 | J62: =IF(OR(D62="Ganho",D62="Perdido"),1,0) -> 1 | K62: =IF(D62="Ganho",1,0) -> 0 | L62: =IF(INDEX(Base!$U$2:$U$601,MATCH(B62,Base!$A$2:$A$601,0))="","",INDEX(Base!$U$2:$U$601,MATCH(B62,Base!$A$2:$A$601,0))) -> Baixa | M62: =INDEX(Base!$R$2:$R$601,MATCH(B62,Base!$A$2:$A$601,0)) -> 0 | N62: =INDEX(Base!$AB$2:$AB$601,MATCH(B62,Base!$A$2:$A$601,0)) -> Média | O62: 122
A63: LEAD00062 | B63: CTD00142 | C63: Evento | D63: Ganho | E63: 1707.17 | F63: 8 | G63: =INDEX(Base!$D$2:$D$601,MATCH(B63,Base!$A$2:$A$601,0)) -> Pequeno Escritório | H63: =INDEX(Base!$C$2:$C$601,MATCH(B63,Base!$A$2:$A$601,0)) -> Sul | I63: =INDEX(Base!$M$2:$M$601,MATCH(B63,Base!$A$2:$A$601,0)) -> 0 | J63: =IF(OR(D63="Ganho",D63="Perdido"),1,0) -> 1 | K63: =IF(D63="Ganho",1,0) -> 1 | L63: =IF(INDEX(Base!$U$2:$U$601,MATCH(B63,Base!$A$2:$A$601,0))="","",INDEX(Base!$U$2:$U$601,MATCH(B63,Base!$A$2:$A$601,0))) -> Média | M63: =INDEX(Base!$R$2:$R$601,MATCH(B63,Base!$A$2:$A$601,0)) -> 0 | N63: =INDEX(Base!$AB$2:$AB$601,MATCH(B63,Base!$A$2:$A$601,0)) -> Média | O63: 46 | P63: 45866
A64: LEAD00063 | B64: CTD00144 | C64: Franquia | D64: Sem Resposta | F64: 2 | G64: =INDEX(Base!$D$2:$D$601,MATCH(B64,Base!$A$2:$A$601,0)) -> Autônomo | H64: =INDEX(Base!$C$2:$C$601,MATCH(B64,Base!$A$2:$A$601,0)) -> Nordeste | I64: =INDEX(Base!$M$2:$M$601,MATCH(B64,Base!$A$2:$A$601,0)) -> 0 | J64: =IF(OR(D64="Ganho",D64="Perdido"),1,0) -> 0 | K64: =IF(D64="Ganho",1,0) -> 0 | L64: =IF(INDEX(Base!$U$2:$U$601,MATCH(B64,Base!$A$2:$A$601,0))="","",INDEX(Base!$U$2:$U$601,MATCH(B64,Base!$A$2:$A$601,0))) -> Baixa | M64: =INDEX(Base!$R$2:$R$601,MATCH(B64,Base!$A$2:$A$601,0)) -> 0 | N64: =INDEX(Base!$AB$2:$AB$601,MATCH(B64,Base!$A$2:$A$601,0)) -> Baixa | O64: 91
A65: LEAD00064 | B65: CTD00090 | C65: Franquia | D65: Reunião Agendada | F65: 7 | G65: =INDEX(Base!$D$2:$D$601,MATCH(B65,Base!$A$2:$A$601,0)) -> Pequeno Escritório | H65: =INDEX(Base!$C$2:$C$601,MATCH(B65,Base!$A$2:$A$601,0)) -> Sudeste | I65: =INDEX(Base!$M$2:$M$601,MATCH(B65,Base!$A$2:$A$601,0)) -> 1 | J65: =IF(OR(D65="Ganho",D65="Perdido"),1,0) -> 0 | K65: =IF(D65="Ganho",1,0) -> 0 | L65: =IF(INDEX(Base!$U$2:$U$601,MATCH(B65,Base!$A$2:$A$601,0))="","",INDEX(Base!$U$2:$U$601,MATCH(B65,Base!$A$2:$A$601,0))) | M65: =INDEX(Base!$R$2:$R$601,MATCH(B65,Base!$A$2:$A$601,0)) -> 1 | N65: =INDEX(Base!$AB$2:$AB$601,MATCH(B65,Base!$A$2:$A$601,0)) -> Alta | O65: 14
A66: LEAD00065 | B66: CTD00017 | C66: Outreach Ativo | D66: Em Contato | F66: 10 | G66: =INDEX(Base!$D$2:$D$601,MATCH(B66,Base!$A$2:$A$601,0)) -> Autônomo | H66: =INDEX(Base!$C$2:$C$601,MATCH(B66,Base!$A$2:$A$601,0)) -> Sudeste | I66: =INDEX(Base!$M$2:$M$601,MATCH(B66,Base!$A$2:$A$601,0)) -> 0 | J66: =IF(OR(D66="Ganho",D66="Perdido"),1,0) -> 0 | K66: =IF(D66="Ganho",1,0) -> 0 | L66: =IF(INDEX(Base!$U$2:$U$601,MATCH(B66,Base!$A$2:$A$601,0))="","",INDEX(Base!$U$2:$U$601,MATCH(B66,Base!$A$2:$A$601,0))) -> Baixa | M66: =INDEX(Base!$R$2:$R$601,MATCH(B66,Base!$A$2:$A$601,0)) -> 0 | N66: =INDEX(Base!$AB$2:$AB$601,MATCH(B66,Base!$A$2:$A$601,0)) -> Baixa | O66: 19
A67: LEAD00066 | B67: CTD00479 | C67: Evento | D67: Ganho | E67: 1754.89 | F67: 7 | G67: =INDEX(Base!$D$2:$D$601,MATCH(B67,Base!$A$2:$A$601,0)) -> Autônomo | H67: =INDEX(Base!$C$2:$C$601,MATCH(B67,Base!$A$2:$A$601,0)) -> Nordeste | I67: =INDEX(Base!$M$2:$M$601,MATCH(B67,Base!$A$2:$A$601,0)) -> 0 | J67: =IF(OR(D67="Ganho",D67="Perdido"),1,0) -> 1 | K67: =IF(D67="Ganho",1,0) -> 1 | L67: =IF(INDEX(Base!$U$2:$U$601,MATCH(B67,Base!$A$2:$A$601,0))="","",INDEX(Base!$U$2:$U$601,MATCH(B67,Base!$A$2:$A$601,0))) -> Baixa | M67: =INDEX(Base!$R$2:$R$601,MATCH(B67,Base!$A$2:$A$601,0)) -> 0 | N67: =INDEX(Base!$AB$2:$AB$601,MATCH(B67,Base!$A$2:$A$601,0)) -> Baixa | O67: 66 | P67: 46088
A68: LEAD00067 | B68: CTD00187 | C68: Inbound | D68: Ganho | E68: 1340.56 | F68: 6 | G68: =INDEX(Base!$D$2:$D$601,MATCH(B68,Base!$A$2:$A$601,0)) -> Autônomo | H68: =INDEX(Base!$C$2:$C$601,MATCH(B68,Base!$A$2:$A$601,0)) -> Nordeste | I68: =INDEX(Base!$M$2:$M$601,MATCH(B68,Base!$A$2:$A$601,0)) -> 0 | J68: =IF(OR(D68="Ganho",D68="Perdido"),1,0) -> 1 | K68: =IF(D68="Ganho",1,0) -> 1 | L68: =IF(INDEX(Base!$U$2:$U$601,MATCH(B68,Base!$A$2:$A$601,0))="","",INDEX(Base!$U$2:$U$601,MATCH(B68,Base!$A$2:$A$601,0))) -> Baixa | M68: =INDEX(Base!$R$2:$R$601,MATCH(B68,Base!$A$2:$A$601,0)) -> 0 | N68: =INDEX(Base!$AB$2:$AB$601,MATCH(B68,Base!$A$2:$A$601,0)) -> Baixa | O68: 38 | P68: 46027
A69: LEAD00068 | B69: CTD00292 | C69: Indicação | D69: Perdido | F69: 10 | G69: =INDEX(Base!$D$2:$D$601,MATCH(B69,Base!$A$2:$A$601,0)) -> Autônomo | H69: =INDEX(Base!$C$2:$C$601,MATCH(B69,Base!$A$2:$A$601,0)) -> Centro-Oeste | I69: =INDEX(Base!$M$2:$M$601,MATCH(B69,Base!$A$2:$A$601,0)) -> 0 | J69: =IF(OR(D69="Ganho",D69="Perdido"),1,0) -> 1 | K69: =IF(D69="Ganho",1,0) -> 0 | L69: =IF(INDEX(Base!$U$2:$U$601,MATCH(B69,Base!$A$2:$A$601,0))="","",INDEX(Base!$U$2:$U$601,MATCH(B69,Base!$A$2:$A$601,0))) -> Baixa | M69: =INDEX(Base!$R$2:$R$601,MATCH(B69,Base!$A$2:$A$601,0)) -> 0 | N69: =INDEX(Base!$AB$2:$AB$601,MATCH(B69,Base!$A$2:$A$601,0)) -> Média | O69: 42
A70: LEAD00069 | B70: CTD00595 | C70: Outreach Ativo | D70: Ganho | E70: 1180.19 | F70: 10 | G70: =INDEX(Base!$D$2:$D$601,MATCH(B70,Base!$A$2:$A$601,0)) -> Autônomo | H70: =INDEX(Base!$C$2:$C$601,MATCH(B70,Base!$A$2:$A$601,0)) -> Sudeste | I70: =INDEX(Base!$M$2:$M$601,MATCH(B70,Base!$A$2:$A$601,0)) -> 0 | J70: =IF(OR(D70="Ganho",D70="Perdido"),1,0) -> 1 | K70: =IF(D70="Ganho",1,0) -> 1 | L70: =IF(INDEX(Base!$U$2:$U$601,MATCH(B70,Base!$A$2:$A$601,0))="","",INDEX(Base!$U$2:$U$601,MATCH(B70,Base!$A$2:$A$601,0))) -> Baixa | M70: =INDEX(Base!$R$2:$R$601,MATCH(B70,Base!$A$2:$A$601,0)) -> 0 | N70: =INDEX(Base!$AB$2:$AB$601,MATCH(B70,Base!$A$2:$A$601,0)) -> Baixa | O70: 69 | P70: 45817
A71: LEAD00070 | B71: CTD00254 | C71: Outreach Ativo | D71: Em Contato | F71: 11 | G71: =INDEX(Base!$D$2:$D$601,MATCH(B71,Base!$A$2:$A$601,0)) -> Pequeno Escritório | H71: =INDEX(Base!$C$2:$C$601,MATCH(B71,Base!$A$2:$A$601,0)) -> Sudeste | I71: =INDEX(Base!$M$2:$M$601,MATCH(B71,Base!$A$2:$A$601,0)) -> 0 | J71: =IF(OR(D71="Ganho",D71="Perdido"),1,0) -> 0 | K71: =IF(D71="Ganho",1,0) -> 0 | L71: =IF(INDEX(Base!$U$2:$U$601,MATCH(B71,Base!$A$2:$A$601,0))="","",INDEX(Base!$U$2:$U$601,MATCH(B71,Base!$A$2:$A$601,0))) -> Baixa | M71: =INDEX(Base!$R$2:$R$601,MATCH(B71,Base!$A$2:$A$601,0)) -> 0 | N71: =INDEX(Base!$AB$2:$AB$601,MATCH(B71,Base!$A$2:$A$601,0)) -> Média | O71: 108
A72: LEAD00071 | B72: CTD00544 | C72: Outreach Ativo | D72: Novo | F72: 9 | G72: =INDEX(Base!$D$2:$D$601,MATCH(B72,Base!$A$2:$A$601,0)) -> Médio Escritório | H72: =INDEX(Base!$C$2:$C$601,MATCH(B72,Base!$A$2:$A$601,0)) -> Sudeste | I72: =INDEX(Base!$M$2:$M$601,MATCH(B72,Base!$A$2:$A$601,0)) -> 1 | J72: =IF(OR(D72="Ganho",D72="Perdido"),1,0) -> 0 | K72: =IF(D72="Ganho",1,0) -> 0 | L72: =IF(INDEX(Base!$U$2:$U$601,MATCH(B72,Base!$A$2:$A$601,0))="","",INDEX(Base!$U$2:$U$601,MATCH(B72,Base!$A$2:$A$601,0))) | M72: =INDEX(Base!$R$2:$R$601,MATCH(B72,Base!$A$2:$A$601,0)) -> 1 | N72: =INDEX(Base!$AB$2:$AB$601,MATCH(B72,Base!$A$2:$A$601,0)) -> Alta | O72: 90
A73: LEAD00072 | B73: CTD00122 | C73: Franquia | D73: Proposta Enviada | F73: 9 | G73: =INDEX(Base!$D$2:$D$601,MATCH(B73,Base!$A$2:$A$601,0)) -> Autônomo | H73: =INDEX(Base!$C$2:$C$601,MATCH(B73,Base!$A$2:$A$601,0)) -> Sul | I73: =INDEX(Base!$M$2:$M$601,MATCH(B73,Base!$A$2:$A$601,0)) -> 0 | J73: =IF(OR(D73="Ganho",D73="Perdido"),1,0) -> 0 | K73: =IF(D73="Ganho",1,0) -> 0 | L73: =IF(INDEX(Base!$U$2:$U$601,MATCH(B73,Base!$A$2:$A$601,0))="","",INDEX(Base!$U$2:$U$601,MATCH(B73,Base!$A$2:$A$601,0))) -> Média | M73: =INDEX(Base!$R$2:$R$601,MATCH(B73,Base!$A$2:$A$601,0)) -> 0 | N73: =INDEX(Base!$AB$2:$AB$601,MATCH(B73,Base!$A$2:$A$601,0)) -> Baixa | O73: 77
A74: LEAD00073 | B74: CTD00164 | C74: Franquia | D74: Em Contato | F74: 6 | G74: =INDEX(Base!$D$2:$D$601,MATCH(B74,Base!$A$2:$A$601,0)) -> Grande Escritório | H74: =INDEX(Base!$C$2:$C$601,MATCH(B74,Base!$A$2:$A$601,0)) -> Nordeste | I74: =INDEX(Base!$M$2:$M$601,MATCH(B74,Base!$A$2:$A$601,0)) -> 1 | J74: =IF(OR(D74="Ganho",D74="Perdido"),1,0) -> 0 | K74: =IF(D74="Ganho",1,0) -> 0 | L74: =IF(INDEX(Base!$U$2:$U$601,MATCH(B74,Base!$A$2:$A$601,0))="","",INDEX(Base!$U$2:$U$601,MATCH(B74,Base!$A$2:$A$601,0))) | M74: =INDEX(Base!$R$2:$R$601,MATCH(B74,Base!$A$2:$A$601,0)) -> 1 | N74: =INDEX(Base!$AB$2:$AB$601,MATCH(B74,Base!$A$2:$A$601,0)) -> Alta | O74: 167
A75: LEAD00074 | B75: CTD00018 | C75: Franquia | D75: Proposta Enviada | F75: 4 | G75: =INDEX(Base!$D$2:$D$601,MATCH(B75,Base!$A$2:$A$601,0)) -> Autônomo | H75: =INDEX(Base!$C$2:$C$601,MATCH(B75,Base!$A$2:$A$601,0)) -> Sul | I75: =INDEX(Base!$M$2:$M$601,MATCH(B75,Base!$A$2:$A$601,0)) -> 0 | J75: =IF(OR(D75="Ganho",D75="Perdido"),1,0) -> 0 | K75: =IF(D75="Ganho",1,0) -> 0 | L75: =IF(INDEX(Base!$U$2:$U$601,MATCH(B75,Base!$A$2:$A$601,0))="","",INDEX(Base!$U$2:$U$601,MATCH(B75,Base!$A$2:$A$601,0))) -> Média | M75: =INDEX(Base!$R$2:$R$601,MATCH(B75,Base!$A$2:$A$601,0)) -> 0 | N75: =INDEX(Base!$AB$2:$AB$601,MATCH(B75,Base!$A$2:$A$601,0)) -> Baixa | O75: 82
A76: LEAD00075 | B76: CTD00474 | C76: Outreach Ativo | D76: Novo | F76: 1 | G76: =INDEX(Base!$D$2:$D$601,MATCH(B76,Base!$A$2:$A$601,0)) -> Autônomo | H76: =INDEX(Base!$C$2:$C$601,MATCH(B76,Base!$A$2:$A$601,0)) -> Sudeste | I76: =INDEX(Base!$M$2:$M$601,MATCH(B76,Base!$A$2:$A$601,0)) -> 0 | J76: =IF(OR(D76="Ganho",D76="Perdido"),1,0) -> 0 | K76: =IF(D76="Ganho",1,0) -> 0 | L76: =IF(INDEX(Base!$U$2:$U$601,MATCH(B76,Base!$A$2:$A$601,0))="","",INDEX(Base!$U$2:$U$601,MATCH(B76,Base!$A$2:$A$601,0))) -> Baixa | M76: =INDEX(Base!$R$2:$R$601,MATCH(B76,Base!$A$2:$A$601,0)) -> 0 | N76: =INDEX(Base!$AB$2:$AB$601,MATCH(B76,Base!$A$2:$A$601,0)) -> Baixa | O76: 100
A77: LEAD00076 | B77: CTD00167 | C77: Franquia | D77: Novo | F77: 11 | G77: =INDEX(Base!$D$2:$D$601,MATCH(B77,Base!$A$2:$A$601,0)) -> Autônomo | H77: =INDEX(Base!$C$2:$C$601,MATCH(B77,Base!$A$2:$A$601,0)) -> Sudeste | I77: =INDEX(Base!$M$2:$M$601,MATCH(B77,Base!$A$2:$A$601,0)) -> 0 | J77: =IF(OR(D77="Ganho",D77="Perdido"),1,0) -> 0 | K77: =IF(D77="Ganho",1,0) -> 0 | L77: =IF(INDEX(Base!$U$2:$U$601,MATCH(B77,Base!$A$2:$A$601,0))="","",INDEX(Base!$U$2:$U$601,MATCH(B77,Base!$A$2:$A$601,0))) -> Alta | M77: =INDEX(Base!$R$2:$R$601,MATCH(B77,Base!$A$2:$A$601,0)) -> 0 | N77: =INDEX(Base!$AB$2:$AB$601,MATCH(B77,Base!$A$2:$A$601,0)) -> Baixa | O77: 36
A78: LEAD00077 | B78: CTD00331 | C78: Inbound | D78: Ganho | E78: 709.32 | F78: 4 | G78: =INDEX(Base!$D$2:$D$601,MATCH(B78,Base!$A$2:$A$601,0)) -> Autônomo | H78: =INDEX(Base!$C$2:$C$601,MATCH(B78,Base!$A$2:$A$601,0)) -> Nordeste | I78: =INDEX(Base!$M$2:$M$601,MATCH(B78,Base!$A$2:$A$601,0)) -> 0 | J78: =IF(OR(D78="Ganho",D78="Perdido"),1,0) -> 1 | K78: =IF(D78="Ganho",1,0) -> 1 | L78: =IF(INDEX(Base!$U$2:$U$601,MATCH(B78,Base!$A$2:$A$601,0))="","",INDEX(Base!$U$2:$U$601,MATCH(B78,Base!$A$2:$A$601,0))) -> Baixa | M78: =INDEX(Base!$R$2:$R$601,MATCH(B78,Base!$A$2:$A$601,0)) -> 0 | N78: =INDEX(Base!$AB$2:$AB$601,MATCH(B78,Base!$A$2:$A$601,0)) -> Média | O78: 58 | P78: 45936
A79: LEAD00078 | B79: CTD00387 | C79: Outreach Ativo | D79: Proposta Enviada | F79: 11 | G79: =INDEX(Base!$D$2:$D$601,MATCH(B79,Base!$A$2:$A$601,0)) -> Pequeno Escritório | H79: =INDEX(Base!$C$2:$C$601,MATCH(B79,Base!$A$2:$A$601,0)) -> Sudeste | I79: =INDEX(Base!$M$2:$M$601,MATCH(B79,Base!$A$2:$A$601,0)) -> 1 | J79: =IF(OR(D79="Ganho",D79="Perdido"),1,0) -> 0 | K79: =IF(D79="Ganho",1,0) -> 0 | L79: =IF(INDEX(Base!$U$2:$U$601,MATCH(B79,Base!$A$2:$A$601,0))="","",INDEX(Base!$U$2:$U$601,MATCH(B79,Base!$A$2:$A$601,0))) | M79: =INDEX(Base!$R$2:$R$601,MATCH(B79,Base!$A$2:$A$601,0)) -> 0 | N79: =INDEX(Base!$AB$2:$AB$601,MATCH(B79,Base!$A$2:$A$601,0)) -> Alta | O79: 175
A80: LEAD00079 | B80: CTD00026 | C80: Inbound | D80: Em Contato | F80: 5 | G80: =INDEX(Base!$D$2:$D$601,MATCH(B80,Base!$A$2:$A$601,0)) -> Pequeno Escritório | H80: =INDEX(Base!$C$2:$C$601,MATCH(B80,Base!$A$2:$A$601,0)) -> Sudeste | I80: =INDEX(Base!$M$2:$M$601,MATCH(B80,Base!$A$2:$A$601,0)) -> 0 | J80: =IF(OR(D80="Ganho",D80="Perdido"),1,0) -> 0 | K80: =IF(D80="Ganho",1,0) -> 0 | L80: =IF(INDEX(Base!$U$2:$U$601,MATCH(B80,Base!$A$2:$A$601,0))="","",INDEX(Base!$U$2:$U$601,MATCH(B80,Base!$A$2:$A$601,0))) -> Alta | M80: =INDEX(Base!$R$2:$R$601,MATCH(B80,Base!$A$2:$A$601,0)) -> 0 | N80: =INDEX(Base!$AB$2:$AB$601,MATCH(B80,Base!$A$2:$A$601,0)) -> Média | O80: 77
A81: LEAD00080 | B81: CTD00434 | C81: Outreach Ativo | D81: Ganho | E81: 1007.45 | F81: 4 | G81: =INDEX(Base!$D$2:$D$601,MATCH(B81,Base!$A$2:$A$601,0)) -> Autônomo | H81: =INDEX(Base!$C$2:$C$601,MATCH(B81,Base!$A$2:$A$601,0)) -> Nordeste | I81: =INDEX(Base!$M$2:$M$601,MATCH(B81,Base!$A$2:$A$601,0)) -> 0 | J81: =IF(OR(D81="Ganho",D81="Perdido"),1,0) -> 1 | K81: =IF(D81="Ganho",1,0) -> 1 | L81: =IF(INDEX(Base!$U$2:$U$601,MATCH(B81,Base!$A$2:$A$601,0))="","",INDEX(Base!$U$2:$U$601,MATCH(B81,Base!$A$2:$A$601,0))) | M81: =INDEX(Base!$R$2:$R$601,MATCH(B81,Base!$A$2:$A$601,0)) -> 0 | N81: =INDEX(Base!$AB$2:$AB$601,MATCH(B81,Base!$A$2:$A$601,0)) -> Baixa | O81: 48 | P81: 45926
A82: LEAD00081 | B82: CTD00470 | C82: Franquia | D82: Em Contato | F82: 6 | G82: =INDEX(Base!$D$2:$D$601,MATCH(B82,Base!$A$2:$A$601,0)) -> Autônomo | H82: =INDEX(Base!$C$2:$C$601,MATCH(B82,Base!$A$2:$A$601,0)) -> Sudeste | I82: =INDEX(Base!$M$2:$M$601,MATCH(B82,Base!$A$2:$A$601,0)) -> 0 | J82: =IF(OR(D82="Ganho",D82="Perdido"),1,0) -> 0 | K82: =IF(D82="Ganho",1,0) -> 0 | L82: =IF(INDEX(Base!$U$2:$U$601,MATCH(B82,Base!$A$2:$A$601,0))="","",INDEX(Base!$U$2:$U$601,MATCH(B82,Base!$A$2:$A$601,0))) -> Baixa | M82: =INDEX(Base!$R$2:$R$601,MATCH(B82,Base!$A$2:$A$601,0)) -> 0 | N82: =INDEX(Base!$AB$2:$AB$601,MATCH(B82,Base!$A$2:$A$601,0)) -> Baixa | O82: 121
A83: LEAD00082 | B83: CTD00034 | C83: Franquia | D83: Perdido | F83: 2 | G83: =INDEX(Base!$D$2:$D$601,MATCH(B83,Base!$A$2:$A$601,0)) -> Autônomo | H83: =INDEX(Base!$C$2:$C$601,MATCH(B83,Base!$A$2:$A$601,0)) -> Norte | I83: =INDEX(Base!$M$2:$M$601,MATCH(B83,Base!$A$2:$A$601,0)) -> 0 | J83: =IF(OR(D83="Ganho",D83="Perdido"),1,0) -> 1 | K83: =IF(D83="Ganho",1,0) -> 0 | L83: =IF(INDEX(Base!$U$2:$U$601,MATCH(B83,Base!$A$2:$A$601,0))="","",INDEX(Base!$U$2:$U$601,MATCH(B83,Base!$A$2:$A$601,0))) -> Baixa | M83: =INDEX(Base!$R$2:$R$601,MATCH(B83,Base!$A$2:$A$601,0)) -> 0 | N83: =INDEX(Base!$AB$2:$AB$601,MATCH(B83,Base!$A$2:$A$601,0)) -> Média | O83: 20
A84: LEAD00083 | B84: CTD00538 | C84: Inbound | D84: Proposta Enviada | F84: 8 | G84: =INDEX(Base!$D$2:$D$601,MATCH(B84,Base!$A$2:$A$601,0)) -> Autônomo | H84: =INDEX(Base!$C$2:$C$601,MATCH(B84,Base!$A$2:$A$601,0)) -> Sul | I84: =INDEX(Base!$M$2:$M$601,MATCH(B84,Base!$A$2:$A$601,0)) -> 0 | J84: =IF(OR(D84="Ganho",D84="Perdido"),1,0) -> 0 | K84: =IF(D84="Ganho",1,0) -> 0 | L84: =IF(INDEX(Base!$U$2:$U$601,MATCH(B84,Base!$A$2:$A$601,0))="","",INDEX(Base!$U$2:$U$601,MATCH(B84,Base!$A$2:$A$601,0))) -> Alta | M84: =INDEX(Base!$R$2:$R$601,MATCH(B84,Base!$A$2:$A$601,0)) -> 0 | N84: =INDEX(Base!$AB$2:$AB$601,MATCH(B84,Base!$A$2:$A$601,0)) -> Baixa | O84: 24
A85: LEAD00084 | B85: CTD00189 | C85: Franquia | D85: Proposta Enviada | F85: 9 | G85: =INDEX(Base!$D$2:$D$601,MATCH(B85,Base!$A$2:$A$601,0)) -> Pequeno Escritório | H85: =INDEX(Base!$C$2:$C$601,MATCH(B85,Base!$A$2:$A$601,0)) -> Sudeste | I85: =INDEX(Base!$M$2:$M$601,MATCH(B85,Base!$A$2:$A$601,0)) -> 0 | J85: =IF(OR(D85="Ganho",D85="Perdido"),1,0) -> 0 | K85: =IF(D85="Ganho",1,0) -> 0 | L85: =IF(INDEX(Base!$U$2:$U$601,MATCH(B85,Base!$A$2:$A$601,0))="","",INDEX(Base!$U$2:$U$601,MATCH(B85,Base!$A$2:$A$601,0))) -> Média | M85: =INDEX(Base!$R$2:$R$601,MATCH(B85,Base!$A$2:$A$601,0)) -> 0 | N85: =INDEX(Base!$AB$2:$AB$601,MATCH(B85,Base!$A$2:$A$601,0)) -> Média | O85: 106
A86: LEAD00085 | B86: CTD00179 | C86: Indicação | D86: Proposta Enviada | F86: 7 | G86: =INDEX(Base!$D$2:$D$601,MATCH(B86,Base!$A$2:$A$601,0)) -> Autônomo | H86: =INDEX(Base!$C$2:$C$601,MATCH(B86,Base!$A$2:$A$601,0)) -> Sudeste | I86: =INDEX(Base!$M$2:$M$601,MATCH(B86,Base!$A$2:$A$601,0)) -> 0 | J86: =IF(OR(D86="Ganho",D86="Perdido"),1,0) -> 0 | K86: =IF(D86="Ganho",1,0) -> 0 | L86: =IF(INDEX(Base!$U$2:$U$601,MATCH(B86,Base!$A$2:$A$601,0))="","",INDEX(Base!$U$2:$U$601,MATCH(B86,Base!$A$2:$A$601,0))) -> Baixa | M86: =INDEX(Base!$R$2:$R$601,MATCH(B86,Base!$A$2:$A$601,0)) -> 0 | N86: =INDEX(Base!$AB$2:$AB$601,MATCH(B86,Base!$A$2:$A$601,0)) -> Baixa | O86: 117
A87: LEAD00086 | B87: CTD00039 | C87: Outreach Ativo | D87: Ganho | E87: 1509.29 | F87: 3 | G87: =INDEX(Base!$D$2:$D$601,MATCH(B87,Base!$A$2:$A$601,0)) -> Autônomo | H87: =INDEX(Base!$C$2:$C$601,MATCH(B87,Base!$A$2:$A$601,0)) -> Nordeste | I87: =INDEX(Base!$M$2:$M$601,MATCH(B87,Base!$A$2:$A$601,0)) -> 0 | J87: =IF(OR(D87="Ganho",D87="Perdido"),1,0) -> 1 | K87: =IF(D87="Ganho",1,0) -> 1 | L87: =IF(INDEX(Base!$U$2:$U$601,MATCH(B87,Base!$A$2:$A$601,0))="","",INDEX(Base!$U$2:$U$601,MATCH(B87,Base!$A$2:$A$601,0))) -> Baixa | M87: =INDEX(Base!$R$2:$R$601,MATCH(B87,Base!$A$2:$A$601,0)) -> 0 | N87: =INDEX(Base!$AB$2:$AB$601,MATCH(B87,Base!$A$2:$A$601,0)) -> Média | O87: 53 | P87: 45846
A88: LEAD00087 | B88: CTD00574 | C88: Inbound | D88: Ganho | E88: 1747.25 | F88: 9 | G88: =INDEX(Base!$D$2:$D$601,MATCH(B88,Base!$A$2:$A$601,0)) -> Autônomo | H88: =INDEX(Base!$C$2:$C$601,MATCH(B88,Base!$A$2:$A$601,0)) -> Norte | I88: =INDEX(Base!$M$2:$M$601,MATCH(B88,Base!$A$2:$A$601,0)) -> 0 | J88: =IF(OR(D88="Ganho",D88="Perdido"),1,0) -> 1 | K88: =IF(D88="Ganho",1,0) -> 1 | L88: =IF(INDEX(Base!$U$2:$U$601,MATCH(B88,Base!$A$2:$A$601,0))="","",INDEX(Base!$U$2:$U$601,MATCH(B88,Base!$A$2:$A$601,0))) -> Baixa | M88: =INDEX(Base!$R$2:$R$601,MATCH(B88,Base!$A$2:$A$601,0)) -> 0 | N88: =INDEX(Base!$AB$2:$AB$601,MATCH(B88,Base!$A$2:$A$601,0)) -> Baixa | O88: 16 | P88: 45804
A89: LEAD00088 | B89: CTD00539 | C89: Indicação | D89: Ganho | E89: 931.04 | F89: 12 | G89: =INDEX(Base!$D$2:$D$601,MATCH(B89,Base!$A$2:$A$601,0)) -> Autônomo | H89: =INDEX(Base!$C$2:$C$601,MATCH(B89,Base!$A$2:$A$601,0)) -> Centro-Oeste | I89: =INDEX(Base!$M$2:$M$601,MATCH(B89,Base!$A$2:$A$601,0)) -> 0 | J89: =IF(OR(D89="Ganho",D89="Perdido"),1,0) -> 1 | K89: =IF(D89="Ganho",1,0) -> 1 | L89: =IF(INDEX(Base!$U$2:$U$601,MATCH(B89,Base!$A$2:$A$601,0))="","",INDEX(Base!$U$2:$U$601,MATCH(B89,Base!$A$2:$A$601,0))) | M89: =INDEX(Base!$R$2:$R$601,MATCH(B89,Base!$A$2:$A$601,0)) -> 0 | N89: =INDEX(Base!$AB$2:$AB$601,MATCH(B89,Base!$A$2:$A$601,0)) -> Média | O89: 58 | P89: 45470
A90: LEAD00089 | B90: CTD00404 | C90: Franquia | D90: Perdido | F90: 10 | G90: =INDEX(Base!$D$2:$D$601,MATCH(B90,Base!$A$2:$A$601,0)) -> Pequeno Escritório | H90: =INDEX(Base!$C$2:$C$601,MATCH(B90,Base!$A$2:$A$601,0)) -> Nordeste | I90: =INDEX(Base!$M$2:$M$601,MATCH(B90,Base!$A$2:$A$601,0)) -> 0 | J90: =IF(OR(D90="Ganho",D90="Perdido"),1,0) -> 1 | K90: =IF(D90="Ganho",1,0) -> 0 | L90: =IF(INDEX(Base!$U$2:$U$601,MATCH(B90,Base!$A$2:$A$601,0))="","",INDEX(Base!$U$2:$U$601,MATCH(B90,Base!$A$2:$A$601,0))) -> Baixa | M90: =INDEX(Base!$R$2:$R$601,MATCH(B90,Base!$A$2:$A$601,0)) -> 0 | N90: =INDEX(Base!$AB$2:$AB$601,MATCH(B90,Base!$A$2:$A$601,0)) -> Média | O90: 109
A91: LEAD00090 | B91: CTD00532 | C91: Franquia | D91: Em Contato | F91: 9 | G91: =INDEX(Base!$D$2:$D$601,MATCH(B91,Base!$A$2:$A$601,0)) -> Grande Escritório | H91: =INDEX(Base!$C$2:$C$601,MATCH(B91,Base!$A$2:$A$601,0)) -> Centro-Oeste | I91: =INDEX(Base!$M$2:$M$601,MATCH(B91,Base!$A$2:$A$601,0)) -> 1 | J91: =IF(OR(D91="Ganho",D91="Perdido"),1,0) -> 0 | K91: =IF(D91="Ganho",1,0) -> 0 | L91: =IF(INDEX(Base!$U$2:$U$601,MATCH(B91,Base!$A$2:$A$601,0))="","",INDEX(Base!$U$2:$U$601,MATCH(B91,Base!$A$2:$A$601,0))) | M91: =INDEX(Base!$R$2:$R$601,MATCH(B91,Base!$A$2:$A$601,0)) -> 1 | N91: =INDEX(Base!$AB$2:$AB$601,MATCH(B91,Base!$A$2:$A$601,0)) -> Alta | O91: 44
A92: LEAD00091 | B92: CTD00239 | C92: Franquia | D92: Em Contato | F92: 8 | G92: =INDEX(Base!$D$2:$D$601,MATCH(B92,Base!$A$2:$A$601,0)) -> Autônomo | H92: =INDEX(Base!$C$2:$C$601,MATCH(B92,Base!$A$2:$A$601,0)) -> Sul | I92: =INDEX(Base!$M$2:$M$601,MATCH(B92,Base!$A$2:$A$601,0)) -> 0 | J92: =IF(OR(D92="Ganho",D92="Perdido"),1,0) -> 0 | K92: =IF(D92="Ganho",1,0) -> 0 | L92: =IF(INDEX(Base!$U$2:$U$601,MATCH(B92,Base!$A$2:$A$601,0))="","",INDEX(Base!$U$2:$U$601,MATCH(B92,Base!$A$2:$A$601,0))) -> Média | M92: =INDEX(Base!$R$2:$R$601,MATCH(B92,Base!$A$2:$A$601,0)) -> 0 | N92: =INDEX(Base!$AB$2:$AB$601,MATCH(B92,Base!$A$2:$A$601,0)) -> Baixa | O92: 12
A93: LEAD00092 | B93: CTD00504 | C93: Outreach Ativo | D93: Ganho | E93: 230.27 | F93: 5 | G93: =INDEX(Base!$D$2:$D$601,MATCH(B93,Base!$A$2:$A$601,0)) -> Autônomo | H93: =INDEX(Base!$C$2:$C$601,MATCH(B93,Base!$A$2:$A$601,0)) -> Sul | I93: =INDEX(Base!$M$2:$M$601,MATCH(B93,Base!$A$2:$A$601,0)) -> 0 | J93: =IF(OR(D93="Ganho",D93="Perdido"),1,0) -> 1 | K93: =IF(D93="Ganho",1,0) -> 1 | L93: =IF(INDEX(Base!$U$2:$U$601,MATCH(B93,Base!$A$2:$A$601,0))="","",INDEX(Base!$U$2:$U$601,MATCH(B93,Base!$A$2:$A$601,0))) -> Baixa | M93: =INDEX(Base!$R$2:$R$601,MATCH(B93,Base!$A$2:$A$601,0)) -> 0 | N93: =INDEX(Base!$AB$2:$AB$601,MATCH(B93,Base!$A$2:$A$601,0)) -> Média | O93: 53 | P93: 45490
